Workbook

Sheet 总表
A1: 序号 | B1: 客户名称 | C1: 付款时间 | D1: 购买时长（月） | E1: 任务分配日期 | F1: 客成经理 | G1: 订单编号 | H1: 产品 | I1: 工具版本 | J1: 交付产品 | K1: 工具到期日期 | L1: 信息收集完成时间 | M1: 社媒平台 | N1: 服务状态 | O1: 是否培训 | P1: 备注 | Q1: 特殊情况 | T1: 客成经理名单 | U1: 服务客户量 | V1: 埃米平台+埃米陪跑服务 | W1: 埃米平台+埃米代运营服务+埃米广告通 | X1: 埃米平台
A2: 1 | B2: 邯郸市扬发贸易有限公司 | C2: 46077.472 | D2: 12 | E2: 46077 | F2: 张楠 | G2: KJ2026022498043554197 | H2: 埃米平台+埃米陪跑服务 | I2: 成长版 | J2: ==_xlfn.TEXTJOIN("+",TRUE,_xlfn._xlws.FILTER(_xlfn.TEXTSPLIT(H2,,"+"),(_xlfn.TEXTSPLIT(H2,,"+")<>"埃米工具")*(_xlfn.TEXTSPLIT(H2,,"+")<>"埃米广告通"))) -> 埃米平台+埃米陪跑服务 | K2: ==EDATE(C2,D2) -> 46442 | L2: 46080 | M2: TK, X, INS, Youtube, FB | N2: 服务中 | O2: 2026/3/3已培训完毕 | T2: 刘帝 | U2: ==COUNTIF(F:F,T2) -> 82 | V2: ==COUNTIFS($F:$F,$T2,$H:$H,$V$1) -> 27 | W2: ==COUNTIFS($F:$F,$T2,$H:$H,$W$1) -> 6 | X2: ==COUNTIFS($F:$F,$T2,$H:$H,$X$1) -> 49
A3: 2 | B3: 山东万国金属制品有限公司 | C3: 46078.675 | D3: 12 | E3: 46078 | F3: 武卓玉 | G3: KJ2026022546842686222 | H3: 埃米平台 | I3: 成长版 | J3: ==_xlfn.TEXTJOIN("+",TRUE,_xlfn._xlws.FILTER(_xlfn.TEXTSPLIT(H3,,"+"),(_xlfn.TEXTSPLIT(H3,,"+")<>"埃米工具")*(_xlfn.TEXTSPLIT(H3,,"+")<>"埃米广告通"))) -> 埃米平台 | K3: ==EDATE(C3,D3) -> 46443 | N3: 服务中 | O3: 2月27日15点培训完毕 | T3: 张楠 | U3: ==COUNTIF(F:F,T3) -> 82 | V3: ==COUNTIFS($F:$F,$T3,$H:$H,$V$1) -> 28 | W3: ==COUNTIFS($F:$F,$T3,$H:$H,$W$1) -> 5 | X3: ==COUNTIFS($F:$F,$T3,$H:$H,$X$1) -> 49
A4: 3 | B4: 青岛盈盛达五金制品有限公司 | C4: 46078.695 | D4: 12 | E4: 46078 | F4: 刘帝 | G4: KJ2026022592874936213 | H4: 埃米平台 | I4: 成长版 | J4: ==_xlfn.TEXTJOIN("+",TRUE,_xlfn._xlws.FILTER(_xlfn.TEXTSPLIT(H4,,"+"),(_xlfn.TEXTSPLIT(H4,,"+")<>"埃米工具")*(_xlfn.TEXTSPLIT(H4,,"+")<>"埃米广告通"))) -> 埃米平台 | K4: ==EDATE(C4,D4) -> 46443 | N4: 服务中 | O4: 3月5日 14点培训 | T4: 谭婷 | U4: ==COUNTIF(F:F,T4) -> 81 | V4: ==COUNTIFS($F:$F,$T4,$H:$H,$V$1) -> 25 | W4: ==COUNTIFS($F:$F,$T4,$H:$H,$W$1) -> 3 | X4: ==COUNTIFS($F:$F,$T4,$H:$H,$X$1) -> 53
A5: 4 | B5: 江阴市金励诚科技有限公司 | C5: 46078.661 | D5: 12 | E5: 46078 | F5: 武卓玉 | G5: KJ2026022547195281372 | H5: 埃米平台 | I5: 成长版 | J5: ==_xlfn.TEXTJOIN("+",TRUE,_xlfn._xlws.FILTER(_xlfn.TEXTSPLIT(H5,,"+"),(_xlfn.TEXTSPLIT(H5,,"+")<>"埃米工具")*(_xlfn.TEXTSPLIT(H5,,"+")<>"埃米广告通"))) -> 埃米平台 | K5: ==EDATE(C5,D5) -> 46443 | N5: 服务中 | O5: 3月4日14点培训 | P5: ==7/92 -> 0.076086957 | T5: 武卓玉 | U5: ==COUNTIF(F:F,T5) -> 82 | V5: ==COUNTIFS($F:$F,$T5,$H:$H,$V$1) -> 26 | W5: ==COUNTIFS($F:$F,$T5,$H:$H,$W$1) -> 4 | X5: ==COUNTIFS($F:$F,$T5,$H:$H,$X$1) -> 52
A6: 5 | B6: 威海卡洛威机械科技有限公司 | C6: 46078.677 | D6: 12 | E6: 46078 | F6: 刘帝 | G6: KJ2026022518377057083 | H6: 埃米平台 | I6: 成长版 | J6: ==_xlfn.TEXTJOIN("+",TRUE,_xlfn._xlws.FILTER(_xlfn.TEXTSPLIT(H6,,"+"),(_xlfn.TEXTSPLIT(H6,,"+")<>"埃米工具")*(_xlfn.TEXTSPLIT(H6,,"+")<>"埃米广告通"))) -> 埃米平台 | K6: ==EDATE(C6,D6) -> 46443 | N6: 服务中 | O6: 2月28日 10点培训完毕 | P6: ==56/92 -> 0.60869565 | T6: 彭才杰 | U6: ==COUNTIF(F:F,T6) -> 73 | V6: ==COUNTIFS($F:$F,$T6,$H:$H,$V$1) -> 26 | W6: ==COUNTIFS($F:$F,$T6,$H:$H,$W$1) -> 7 | X6: ==COUNTIFS($F:$F,$T6,$H:$H,$X$1) -> 40
A7: 6 | B7: 聊城铭康金属材料有限公司 | C7: 46078.609 | D7: 12 | E7: 46078 | F7: 武卓玉 | G7: KJ2026022535334346216 | H7: 埃米平台 | I7: 成长版 | J7: ==_xlfn.TEXTJOIN("+",TRUE,_xlfn._xlws.FILTER(_xlfn.TEXTSPLIT(H7,,"+"),(_xlfn.TEXTSPLIT(H7,,"+")<>"埃米工具")*(_xlfn.TEXTSPLIT(H7,,"+")<>"埃米广告通"))) -> 埃米平台 | K7: ==EDATE(C7,D7) -> 46443 | N7: 服务中 | O7: 3月2日11点培训 | T7: 高晴 | U7: ==COUNTIF(F:F,T7) -> 27 | V7: ==COUNTIFS($F:$F,$T7,$H:$H,$V$1) -> 6 | W7: ==COUNTIFS($F:$F,$T7,$H:$H,$W$1) -> 2 | X7: ==COUNTIFS($F:$F,$T7,$H:$H,$X$1) -> 19
A8: 7 | B8: 湖南文盛新能源科技有限公司 | C8: 46078.666 | D8: 12 | E8: 46078 | F8: 刘帝 | G8: KJ2026022540694727364 | H8: 埃米平台 | I8: 成长版 | J8: ==_xlfn.TEXTJOIN("+",TRUE,_xlfn._xlws.FILTER(_xlfn.TEXTSPLIT(H8,,"+"),(_xlfn.TEXTSPLIT(H8,,"+")<>"埃米工具")*(_xlfn.TEXTSPLIT(H8,,"+")<>"埃米广告通"))) -> 埃米平台 | K8: ==EDATE(C8,D8) -> 46443 | N8: 服务中 | O8: 3月4日 10点培训 | T8: 董德隆 | U8: ==COUNTIF(F:F,T8) -> 21 | V8: ==COUNTIFS($F:$F,$T8,$H:$H,$V$1) -> 7 | W8: ==COUNTIFS($F:$F,$T8,$H:$H,$W$1) -> 1 | X8: ==COUNTIFS($F:$F,$T8,$H:$H,$X$1) -> 13
A9: 8 | B9: 威海市庆东渔具有限公司 | C9: 46078.564 | D9: 12 | E9: 46078 | F9: 刘帝 | G9: KJ2026022562465558535 | H9: 埃米平台 | I9: 成长版 | J9: ==_xlfn.TEXTJOIN("+",TRUE,_xlfn._xlws.FILTER(_xlfn.TEXTSPLIT(H9,,"+"),(_xlfn.TEXTSPLIT(H9,,"+")<>"埃米工具")*(_xlfn.TEXTSPLIT(H9,,"+")<>"埃米广告通"))) -> 埃米平台 | K9: ==EDATE(C9,D9) -> 46443 | N9: 服务中 | O9: 46084 | T9: 金雪 | U9: ==COUNTIF(F:F,T9) -> 9 | V9: ==COUNTIFS($F:$F,$T9,$H:$H,$V$1) -> 6 | W9: ==COUNTIFS($F:$F,$T9,$H:$H,$W$1) -> 1 | X9: ==COUNTIFS($F:$F,$T9,$H:$H,$X$1) -> 2
A10: 9 | B10: 永东发（廊坊）科技有限公司 | C10: 46078.879 | D10: 12 | E10: 46079 | F10: 武卓玉 | G10: KJ2026022584829241980 | H10: 埃米平台+埃米陪跑服务 | I10: 成长版 | J10: ==_xlfn.TEXTJOIN("+",TRUE,_xlfn._xlws.FILTER(_xlfn.TEXTSPLIT(H10,,"+"),(_xlfn.TEXTSPLIT(H10,,"+")<>"埃米工具")*(_xlfn.TEXTSPLIT(H10,,"+")<>"埃米广告通"))) -> 埃米平台+埃米陪跑服务 | K10: ==EDATE(C10,D10) -> 46443 | L10: 46091 | M10: FB,TK, INS | N10: 服务中 | O10: 3月3日 10点培训 | T10: 李政 | U10: ==COUNTIF(F:F,T10) -> 9 | V10: ==COUNTIFS($F:$F,$T10,$H:$H,$V$1) -> 3 | W10: ==COUNTIFS($F:$F,$T10,$H:$H,$W$1) -> 0 | X10: ==COUNTIFS($F:$F,$T10,$H:$H,$X$1) -> 6
A11: 10 | B11: 军芳复合材料科技（威海）有限公司 | C11: 46078.761 | D11: 12 | E11: 46079 | F11: 武卓玉 | G11: KJ2026022599703483243 | H11: 埃米平台 | I11: 成长版 | J11: ==_xlfn.TEXTJOIN("+",TRUE,_xlfn._xlws.FILTER(_xlfn.TEXTSPLIT(H11,,"+"),(_xlfn.TEXTSPLIT(H11,,"+")<>"埃米工具")*(_xlfn.TEXTSPLIT(H11,,"+")<>"埃米广告通"))) -> 埃米平台 | K11: ==EDATE(C11,D11) -> 46443 | N11: 服务中 | O11: 已培训2次 | T11: 孙启萌 | U11: ==COUNTIF(F:F,T11) -> 5 | V11: ==COUNTIFS($F:$F,$T11,$H:$H,$V$1) -> 3 | W11: ==COUNTIFS($F:$F,$T11,$H:$H,$W$1) -> 0 | X11: ==COUNTIFS($F:$F,$T11,$H:$H,$X$1) -> 2
A12: 11 | B12: 河北卓好科技有限公司 | C12: 46078.729 | D12: 24 | E12: 46079 | F12: 武卓玉 | G12: KJ2026022526465781043 | H12: 埃米平台+埃米代运营服务+埃米广告通 | I12: 成长版 | J12: ==_xlfn.TEXTJOIN("+",TRUE,_xlfn._xlws.FILTER(_xlfn.TEXTSPLIT(H12,,"+"),(_xlfn.TEXTSPLIT(H12,,"+")<>"埃米工具")*(_xlfn.TEXTSPLIT(H12,,"+")<>"埃米广告通"))) -> 埃米平台+埃米代运营服务 | K12: ==EDATE(C12,D12) -> 46808 | L12: 46080 | M12: TK, INS, Youtube, FB, X, Linkedin | N12: 服务中 | O12: 3月2日11点30点培训+下午3点 | T12: 叶佩 | U12: ==COUNTIF(F:F,T12) -> 0 | V12: ==COUNTIFS($F:$F,$T12,$H:$H,$V$1) -> 0 | W12: ==COUNTIFS($F:$F,$T12,$H:$H,$W$1) -> 0 | X12: ==COUNTIFS($F:$F,$T12,$H:$H,$X$1) -> 0
A13: 12 | B13: 聊城市金硕机电设备有限公司 | C13: 46078.813 | D13: 12 | E13: 46079 | F13: 刘帝 | G13: KJ2026022567963250877 | H13: 埃米平台+埃米陪跑服务 | I13: 成长版 | J13: ==_xlfn.TEXTJOIN("+",TRUE,_xlfn._xlws.FILTER(_xlfn.TEXTSPLIT(H13,,"+"),(_xlfn.TEXTSPLIT(H13,,"+")<>"埃米工具")*(_xlfn.TEXTSPLIT(H13,,"+")<>"埃米广告通"))) -> 埃米平台+埃米陪跑服务 | K13: ==EDATE(C13,D13) -> 46443 | L13: 46097 | M13: TK, X, INS, Youtube, FB | N13: 服务中 | O13: 46086 | T13: 林剑伟 | U13: ==COUNTIF(F:F,T13) -> 0 | V13: ==COUNTIFS($F:$F,$T13,$H:$H,$V$1) -> 0 | W13: ==COUNTIFS($F:$F,$T13,$H:$H,$W$1) -> 0 | X13: ==COUNTIFS($F:$F,$T13,$H:$H,$X$1) -> 0
A14: 13 | B14: 徐州沃卡重工机械有限公司 | C14: 46078.723 | D14: 12 | E14: 46079 | F14: 刘帝 | G14: KJ2026022503070905587 | H14: 埃米平台+埃米陪跑服务 | I14: 高级版 | J14: ==_xlfn.TEXTJOIN("+",TRUE,_xlfn._xlws.FILTER(_xlfn.TEXTSPLIT(H14,,"+"),(_xlfn.TEXTSPLIT(H14,,"+")<>"埃米工具")*(_xlfn.TEXTSPLIT(H14,,"+")<>"埃米广告通"))) -> 埃米平台+埃米陪跑服务 | K14: ==EDATE(C14,D14) -> 46443 | L14: 46079 | M14: TK, Youtube, FB | N14: 服务中 | O14: 4月1日预约培训 | T14: 姬玉晶 | U14: ==COUNTIF(F:F,T14) -> 0 | V14: ==COUNTIFS($F:$F,$T14,$H:$H,$V$1) -> 0 | W14: ==COUNTIFS($F:$F,$T14,$H:$H,$W$1) -> 0 | X14: ==COUNTIFS($F:$F,$T14,$H:$H,$X$1) -> 0
A15: 14 | B15: 广州弗御莱科技有限公司 | C15: 46078.755 | D15: 12 | E15: 46079 | F15: 刘帝 | G15: KJ2026022584300542211 | H15: 埃米平台 | I15: 成长版 | J15: ==_xlfn.TEXTJOIN("+",TRUE,_xlfn._xlws.FILTER(_xlfn.TEXTSPLIT(H15,,"+"),(_xlfn.TEXTSPLIT(H15,,"+")<>"埃米工具")*(_xlfn.TEXTSPLIT(H15,,"+")<>"埃米广告通"))) -> 埃米平台 | K15: ==EDATE(C15,D15) -> 46443 | N15: 服务中 | O15: 3月2日 培训完毕 | T15: 丁震 | U15: ==COUNTIF(F:F,T15) -> 0 | V15: ==COUNTIFS($F:$F,$T15,$H:$H,$V$1) -> 0 | W15: ==COUNTIFS($F:$F,$T15,$H:$H,$W$1) -> 0 | X15: ==COUNTIFS($F:$F,$T15,$H:$H,$X$1) -> 0
A16: 15 | B16: 深圳市深岩科技有限公司 | C16: 46078.78 | D16: 12 | E16: 46079 | F16: 刘帝 | G16: KJ2026022581454511703 | H16: 埃米平台 | I16: 成长版 | J16: ==_xlfn.TEXTJOIN("+",TRUE,_xlfn._xlws.FILTER(_xlfn.TEXTSPLIT(H16,,"+"),(_xlfn.TEXTSPLIT(H16,,"+")<>"埃米工具")*(_xlfn.TEXTSPLIT(H16,,"+")<>"埃米广告通"))) -> 埃米平台 | K16: ==EDATE(C16,D16) -> 46443 | N16: 服务中 | O16: 2月27日 10点培训完毕 | T16: 马康 | U16: ==COUNTIF(F:F,T16) -> 0 | V16: ==COUNTIFS($F:$F,$T16,$H:$H,$V$1) -> 0 | W16: ==COUNTIFS($F:$F,$T16,$H:$H,$W$1) -> 0 | X16: ==COUNTIFS($F:$F,$T16,$H:$H,$X$1) -> 0
A17: 16 | B17: 临清市星扬机械设备有限公司 | C17: 46079.44 | D17: 12 | E17: 46079 | F17: 武卓玉 | G17: KJ2026022506660952618 | H17: 埃米平台+埃米陪跑服务 | I17: 成长版 | J17: ==_xlfn.TEXTJOIN("+",TRUE,_xlfn._xlws.FILTER(_xlfn.TEXTSPLIT(H17,,"+"),(_xlfn.TEXTSPLIT(H17,,"+")<>"埃米工具")*(_xlfn.TEXTSPLIT(H17,,"+")<>"埃米广告通"))) -> 埃米平台+埃米陪跑服务 | K17: ==EDATE(C17,D17) -> 46444 | L17: 46080 | M17: TK, Youtube, FB | N17: 服务中 | O17: 46106 | T17: 张辉李 | U17: ==COUNTIF(F:F,T17) -> 0 | V17: ==COUNTIFS($F:$F,$T17,$H:$H,$V$1) -> 0 | W17: ==COUNTIFS($F:$F,$T17,$H:$H,$W$1) -> 0 | X17: ==COUNTIFS($F:$F,$T17,$H:$H,$X$1) -> 0
A18: 17 | B18: 山东忠阳化工有限公司 | C18: 46079.481 | D18: 12 | E18: 46079 | F18: 刘帝 | G18: KJ2026022613288611870 | H18: 埃米平台+埃米陪跑服务 | I18: 成长版 | J18: ==_xlfn.TEXTJOIN("+",TRUE,_xlfn._xlws.FILTER(_xlfn.TEXTSPLIT(H18,,"+"),(_xlfn.TEXTSPLIT(H18,,"+")<>"埃米工具")*(_xlfn.TEXTSPLIT(H18,,"+")<>"埃米广告通"))) -> 埃米平台+埃米陪跑服务 | K18: ==EDATE(C18,D18) -> 46444 | L18: 46105 | M18: TK, X, INS, Youtube, FB | N18: 服务中 | O18: 4月1日预约培训 | T18: 姜一 | U18: ==COUNTIF(F:F,T18) -> 0 | V18: ==COUNTIFS($F:$F,$T18,$H:$H,$V$1) -> 0 | W18: ==COUNTIFS($F:$F,$T18,$H:$H,$W$1) -> 0 | X18: ==COUNTIFS($F:$F,$T18,$H:$H,$X$1) -> 0
A19: 18 | B19: 大连佳显电子有限公司 | C19: 46079.566 | D19: 12 | E19: 46079 | F19: 武卓玉 | G19: KJ2026022688098476910 | H19: 埃米平台 | I19: 成长版 | J19: ==_xlfn.TEXTJOIN("+",TRUE,_xlfn._xlws.FILTER(_xlfn.TEXTSPLIT(H19,,"+"),(_xlfn.TEXTSPLIT(H19,,"+")<>"埃米工具")*(_xlfn.TEXTSPLIT(H19,,"+")<>"埃米广告通"))) -> 埃米平台 | K19: ==EDATE(C19,D19) -> 46444 | N19: 服务中 | O19: 2月28已培训 | T19: 吴东 | U19: ==COUNTIF(F:F,T19) -> 0 | V19: ==COUNTIFS($F:$F,$T19,$H:$H,$V$1) -> 0 | W19: ==COUNTIFS($F:$F,$T19,$H:$H,$W$1) -> 0 | X19: ==COUNTIFS($F:$F,$T19,$H:$H,$X$1) -> 0
A20: 19 | B20: 山东鸿星工程机械有限公司 | C20: 46079.642 | D20: 12 | E20: 46079 | F20: 刘帝 | G20: KJ2026022664167571119 | H20: 埃米平台+埃米陪跑服务 | I20: 成长版 | J20: ==_xlfn.TEXTJOIN("+",TRUE,_xlfn._xlws.FILTER(_xlfn.TEXTSPLIT(H20,,"+"),(_xlfn.TEXTSPLIT(H20,,"+")<>"埃米工具")*(_xlfn.TEXTSPLIT(H20,,"+")<>"埃米广告通"))) -> 埃米平台+埃米陪跑服务 | K20: ==EDATE(C20,D20) -> 46444 | L20: 46080 | M20: TK, X, INS, Youtube, FB | N20: 服务中 | O20: 2月28下午14点培训完毕 | T20: 金星 | U20: ==COUNTIF(F:F,T20) -> 0 | V20: ==COUNTIFS($F:$F,$T20,$H:$H,$V$1) -> 0 | W20: ==COUNTIFS($F:$F,$T20,$H:$H,$W$1) -> 0 | X20: ==COUNTIFS($F:$F,$T20,$H:$H,$X$1) -> 0
A21: 20 | B21: 长松国际贸易（大连）有限公司 | C21: 46079.643 | D21: 12 | E21: 46079 | F21: 武卓玉 | G21: KJ2026022687432633719 | H21: 埃米平台 | I21: 成长版 | J21: ==_xlfn.TEXTJOIN("+",TRUE,_xlfn._xlws.FILTER(_xlfn.TEXTSPLIT(H21,,"+"),(_xlfn.TEXTSPLIT(H21,,"+")<>"埃米工具")*(_xlfn.TEXTSPLIT(H21,,"+")<>"埃米广告通"))) -> 埃米平台 | K21: ==EDATE(C21,D21) -> 46444 | N21: 服务中 | O21: 3月18日参加联播 | T21: 史倩云 | U21: ==COUNTIF(F:F,T21) -> 0 | V21: ==COUNTIFS($F:$F,$T21,$H:$H,$V$1) -> 0 | W21: ==COUNTIFS($F:$F,$T21,$H:$H,$W$1) -> 0 | X21: ==COUNTIFS($F:$F,$T21,$H:$H,$X$1) -> 0
A22: 21 | B22: 珈诺生物（武汉）有限公司 | C22: 46079.617 | D22: 12 | E22: 46079 | F22: 武卓玉 | G22: KJ2026022679280664791 | H22: 埃米平台 | I22: 成长版 | J22: ==_xlfn.TEXTJOIN("+",TRUE,_xlfn._xlws.FILTER(_xlfn.TEXTSPLIT(H22,,"+"),(_xlfn.TEXTSPLIT(H22,,"+")<>"埃米工具")*(_xlfn.TEXTSPLIT(H22,,"+")<>"埃米广告通"))) -> 埃米平台 | K22: ==EDATE(C22,D22) -> 46444 | N22: 服务中 | O22: 2月28培训完毕 | T22: 李嘉颖 | U22: ==COUNTIF(F:F,T22) -> 0 | V22: ==COUNTIFS($F:$F,$T22,$H:$H,$V$1) -> 0 | W22: ==COUNTIFS($F:$F,$T22,$H:$H,$W$1) -> 0 | X22: ==COUNTIFS($F:$F,$T22,$H:$H,$X$1) -> 0
A23: 22 | B23: 济南昊阳铸锻有限公司 | C23: 46079.694 | D23: 12 | E23: 46079 | F23: 刘帝 | G23: KJ2026022654221856124 | H23: 埃米平台 | I23: 成长版 | J23: ==_xlfn.TEXTJOIN("+",TRUE,_xlfn._xlws.FILTER(_xlfn.TEXTSPLIT(H23,,"+"),(_xlfn.TEXTSPLIT(H23,,"+")<>"埃米工具")*(_xlfn.TEXTSPLIT(H23,,"+")<>"埃米广告通"))) -> 埃米平台 | K23: ==EDATE(C23,D23) -> 46444 | N23: 服务中 | O23: 2月28下午16点30点培训完毕 | T23: 任晶惠 | U23: ==COUNTIF(F:F,T23) -> 0 | V23: ==COUNTIFS($F:$F,$T23,$H:$H,$V$1) -> 0 | W23: ==COUNTIFS($F:$F,$T23,$H:$H,$W$1) -> 0 | X23: ==COUNTIFS($F:$F,$T23,$H:$H,$X$1) -> 0
A24: 23 | B24: 威海市昊宇金属制品有限公司 | C24: 46079.696 | D24: 12 | E24: 46079 | F24: 武卓玉 | G24: KJ2026022610577386848 | H24: 埃米平台 | I24: 成长版 | J24: ==_xlfn.TEXTJOIN("+",TRUE,_xlfn._xlws.FILTER(_xlfn.TEXTSPLIT(H24,,"+"),(_xlfn.TEXTSPLIT(H24,,"+")<>"埃米工具")*(_xlfn.TEXTSPLIT(H24,,"+")<>"埃米广告通"))) -> 埃米平台 | K24: ==EDATE(C24,D24) -> 46444 | N24: 服务中 | O24: 2月27日 16点培训完毕 | T24: 杨豪芳 | U24: ==COUNTIF(F:F,T24) -> 0 | V24: ==COUNTIFS($F:$F,$T24,$H:$H,$V$1) -> 0 | W24: ==COUNTIFS($F:$F,$T24,$H:$H,$W$1) -> 0 | X24: ==COUNTIFS($F:$F,$T24,$H:$H,$X$1) -> 0
A25: 24 | B25: 梁山铭大机械设备有限公司 | C25: 46079.779 | D25: 12 | E25: 46080 | F25: 张楠 | G25: KJ2026022622130651481 | H25: 埃米平台+埃米陪跑服务 | I25: 成长版 | J25: ==_xlfn.TEXTJOIN("+",TRUE,_xlfn._xlws.FILTER(_xlfn.TEXTSPLIT(H25,,"+"),(_xlfn.TEXTSPLIT(H25,,"+")<>"埃米工具")*(_xlfn.TEXTSPLIT(H25,,"+")<>"埃米广告通"))) -> 埃米平台+埃米陪跑服务 | K25: ==EDATE(C25,D25) -> 46444 | L25: 46080 | M25: TK, X, INS, Youtube, FB | N25: 服务中 | O25: 3月13日15：00已培训完毕 | T25: 桑田 | U25: ==COUNTIF(F:F,T25) -> 0 | V25: ==COUNTIFS($F:$F,$T25,$H:$H,$V$1) -> 0 | W25: ==COUNTIFS($F:$F,$T25,$H:$H,$W$1) -> 0 | X25: ==COUNTIFS($F:$F,$T25,$H:$H,$X$1) -> 0
A26: 25 | B26: 焜傲机器人（成都）有限公司 | C26: 46079.817 | D26: 12 | E26: 46080 | F26: 张楠 | G26: KJ2026022667244554822 | H26: 埃米平台+埃米陪跑服务 | I26: 高级版 | J26: ==_xlfn.TEXTJOIN("+",TRUE,_xlfn._xlws.FILTER(_xlfn.TEXTSPLIT(H26,,"+"),(_xlfn.TEXTSPLIT(H26,,"+")<>"埃米工具")*(_xlfn.TEXTSPLIT(H26,,"+")<>"埃米广告通"))) -> 埃米平台+埃米陪跑服务 | K26: ==EDATE(C26,D26) -> 46444 | L26: 46085 | M26: TK, X, INS, Youtube, FB | N26: 服务中 | T26: 韩明伟 | U26: ==COUNTIF(F:F,T26) -> 0 | V26: ==COUNTIFS($F:$F,$T26,$H:$H,$V$1) -> 0 | W26: ==COUNTIFS($F:$F,$T26,$H:$H,$W$1) -> 0 | X26: ==COUNTIFS($F:$F,$T26,$H:$H,$X$1) -> 0
A27: 26 | B27: 深圳市极星科技有限公司 | C27: 46080.694 | D27: 12 | E27: 46080 | F27: 武卓玉 | G27: KJ2026022714105057311 | H27: 埃米平台 | I27: 高级版 | J27: ==_xlfn.TEXTJOIN("+",TRUE,_xlfn._xlws.FILTER(_xlfn.TEXTSPLIT(H27,,"+"),(_xlfn.TEXTSPLIT(H27,,"+")<>"埃米工具")*(_xlfn.TEXTSPLIT(H27,,"+")<>"埃米广告通"))) -> 埃米平台 | K27: ==EDATE(C27,D27) -> 46445 | N27: 服务中 | O27: 3月2培训完毕 | T27: 崔芳魁 | U27: ==COUNTIF(F:F,T27) -> 0 | V27: ==COUNTIFS($F:$F,$T27,$H:$H,$V$1) -> 0 | W27: ==COUNTIFS($F:$F,$T27,$H:$H,$W$1) -> 0 | X27: ==COUNTIFS($F:$F,$T27,$H:$H,$X$1) -> 0
A28: 27 | B28: 青岛腾本味食品有限公司 | C28: 46080.4 | D28: 12 | E28: 46080 | F28: 张楠 | G28: KJ2026022656711821702 | H28: 埃米平台 | I28: 成长版 | J28: ==_xlfn.TEXTJOIN("+",TRUE,_xlfn._xlws.FILTER(_xlfn.TEXTSPLIT(H28,,"+"),(_xlfn.TEXTSPLIT(H28,,"+")<>"埃米工具")*(_xlfn.TEXTSPLIT(H28,,"+")<>"埃米广告通"))) -> 埃米平台 | K28: ==EDATE(C28,D28) -> 46445 | N28: 服务中 | O28: 3月2日下午17点 | T28: 张琪 | U28: ==COUNTIF(F:F,T28) -> 0 | V28: ==COUNTIFS($F:$F,$T28,$H:$H,$V$1) -> 0 | W28: ==COUNTIFS($F:$F,$T28,$H:$H,$W$1) -> 0 | X28: ==COUNTIFS($F:$F,$T28,$H:$H,$X$1) -> 0
A29: 28 | B29: 威海波塞冬户外用品有限公司 | C29: 46080.434 | D29: 12 | E29: 46080 | F29: 谭婷 | G29: KJ2026022708416506714 | H29: 埃米平台 | I29: 成长版 | J29: ==_xlfn.TEXTJOIN("+",TRUE,_xlfn._xlws.FILTER(_xlfn.TEXTSPLIT(H29,,"+"),(_xlfn.TEXTSPLIT(H29,,"+")<>"埃米工具")*(_xlfn.TEXTSPLIT(H29,,"+")<>"埃米广告通"))) -> 埃米平台 | K29: ==EDATE(C29,D29) -> 46445 | N29: 服务中 | O29: 3.2培训完成 | T29: 李睿琦 | U29: ==COUNTIF(F:F,T29) -> 0 | V29: ==COUNTIFS($F:$F,$T29,$H:$H,$V$1) -> 0 | W29: ==COUNTIFS($F:$F,$T29,$H:$H,$W$1) -> 0 | X29: ==COUNTIFS($F:$F,$T29,$H:$H,$X$1) -> 0
A30: 29 | B30: 者尼文化传媒（北京）有限责任公司 | C30: 46079.714 | D30: 12 | E30: 46080 | F30: 张楠 | G30: KJ2026022638689026001 | H30: 埃米平台 | I30: 成长版 | J30: ==_xlfn.TEXTJOIN("+",TRUE,_xlfn._xlws.FILTER(_xlfn.TEXTSPLIT(H30,,"+"),(_xlfn.TEXTSPLIT(H30,,"+")<>"埃米工具")*(_xlfn.TEXTSPLIT(H30,,"+")<>"埃米广告通"))) -> 埃米平台 | K30: ==EDATE(C30,D30) -> 46444 | N30: 服务中 | O30: 3月2日 10点培训完成 | T30: 柳详 | U30: ==COUNTIF(F:F,T30) -> 0 | V30: ==COUNTIFS($F:$F,$T30,$H:$H,$V$1) -> 0 | W30: ==COUNTIFS($F:$F,$T30,$H:$H,$W$1) -> 0 | X30: ==COUNTIFS($F:$F,$T30,$H:$H,$X$1) -> 0
A31: 30 | B31: 苏州市依雯家居服饰有限公司 | C31: 46080.476 | D31: 12 | E31: 46080 | F31: 张楠 | G31: KJ2026022780573574355 | H31: 埃米平台 | I31: 成长版 | J31: ==_xlfn.TEXTJOIN("+",TRUE,_xlfn._xlws.FILTER(_xlfn.TEXTSPLIT(H31,,"+"),(_xlfn.TEXTSPLIT(H31,,"+")<>"埃米工具")*(_xlfn.TEXTSPLIT(H31,,"+")<>"埃米广告通"))) -> 埃米平台 | K31: ==EDATE(C31,D31) -> 46445 | N31: 服务中 | O31: 3.18公开课 | T31: 曾欢 | U31: ==COUNTIF(F:F,T31) -> 0 | V31: ==COUNTIFS($F:$F,$T31,$H:$H,$V$1) -> 0 | W31: ==COUNTIFS($F:$F,$T31,$H:$H,$W$1) -> 0 | X31: ==COUNTIFS($F:$F,$T31,$H:$H,$X$1) -> 0
A32: 31 | B32: 武汉卓越高压测试设备有限公司 | C32: 46080.608 | D32: 12 | E32: 46080 | F32: 谭婷 | G32: KJ2026022705707608135 | H32: 埃米平台+埃米陪跑服务 | I32: 成长版 | J32: ==_xlfn.TEXTJOIN("+",TRUE,_xlfn._xlws.FILTER(_xlfn.TEXTSPLIT(H32,,"+"),(_xlfn.TEXTSPLIT(H32,,"+")<>"埃米工具")*(_xlfn.TEXTSPLIT(H32,,"+")<>"埃米广告通"))) -> 埃米平台+埃米陪跑服务 | K32: ==EDATE(C32,D32) -> 46445 | L32: 46084 | M32: TK, FB | N32: 服务中 | O32: 3.18公开课 | T32: 陈俊生 | U32: ==COUNTIF(F:F,T32) -> 0 | V32: ==COUNTIFS($F:$F,$T32,$H:$H,$V$1) -> 0 | W32: ==COUNTIFS($F:$F,$T32,$H:$H,$W$1) -> 0 | X32: ==COUNTIFS($F:$F,$T32,$H:$H,$X$1) -> 0
A33: 32 | B33: 威海基尔新能源装备有限公司 | C33: 46080.776 | D33: 12 | E33: 46081 | F33: 张楠 | G33: KJ2026022770053911799 | H33: 埃米平台+埃米代运营服务+埃米广告通 | I33: 成长版 | J33: ==_xlfn.TEXTJOIN("+",TRUE,_xlfn._xlws.FILTER(_xlfn.TEXTSPLIT(H33,,"+"),(_xlfn.TEXTSPLIT(H33,,"+")<>"埃米工具")*(_xlfn.TEXTSPLIT(H33,,"+")<>"埃米广告通"))) -> 埃米平台+埃米代运营服务 | K33: ==EDATE(C33,D33) -> 46445 | L33: 46083 | M33: TK, FB, X, INS, Youtube | N33: 服务中 | O33: 3月18日参加联播 | T33: 赵娟 | U33: ==COUNTIF(F:F,T33) -> 0 | V33: ==COUNTIFS($F:$F,$T33,$H:$H,$V$1) -> 0 | W33: ==COUNTIFS($F:$F,$T33,$H:$H,$W$1) -> 0 | X33: ==COUNTIFS($F:$F,$T33,$H:$H,$X$1) -> 0
A34: 33 | B34: 东营市迈特莱汽配有限公司 | C34: 46080.77 | D34: 12 | E34: 46081 | F34: 张楠 | G34: KJ2026022758390230467 | H34: 埃米平台 | I34: 成长版 | J34: ==_xlfn.TEXTJOIN("+",TRUE,_xlfn._xlws.FILTER(_xlfn.TEXTSPLIT(H34,,"+"),(_xlfn.TEXTSPLIT(H34,,"+")<>"埃米工具")*(_xlfn.TEXTSPLIT(H34,,"+")<>"埃米广告通"))) -> 埃米平台 | K34: ==EDATE(C34,D34) -> 46445 | N34: 服务中 | O34: 3月5日培训完毕 | T34: 陈俊生 | U34: ==COUNTIF(F:F,T34) -> 0 | V34: ==COUNTIFS($F:$F,$T34,$H:$H,$V$1) -> 0 | W34: ==COUNTIFS($F:$F,$T34,$H:$H,$W$1) -> 0 | X34: ==COUNTIFS($F:$F,$T34,$H:$H,$X$1) -> 0
A35: 34 | B35: 江阴市冶金液压机械厂 | C35: 46080.668 | D35: 12 | E35: 46081 | F35: 张楠 | G35: KJ2026022784884238546 | H35: 埃米平台 | I35: 成长版 | J35: ==_xlfn.TEXTJOIN("+",TRUE,_xlfn._xlws.FILTER(_xlfn.TEXTSPLIT(H35,,"+"),(_xlfn.TEXTSPLIT(H35,,"+")<>"埃米工具")*(_xlfn.TEXTSPLIT(H35,,"+")<>"埃米广告通"))) -> 埃米平台 | K35: ==EDATE(C35,D35) -> 46445 | N35: 服务中 | O35: 3月3已培训完毕 | T35: 赵娟 | U35: ==COUNTIF(F:F,T35) -> 0 | V35: ==COUNTIFS($F:$F,$T35,$H:$H,$V$1) -> 0 | W35: ==COUNTIFS($F:$F,$T35,$H:$H,$W$1) -> 0 | X35: ==COUNTIFS($F:$F,$T35,$H:$H,$X$1) -> 0
A36: 35 | B36: 威海尚品机械设备科技有限公司 | C36: 46080.751 | D36: 12 | E36: 46081 | F36: 张楠 | G36: KJ2026022767149961731 | H36: 埃米平台 | I36: 成长版 | J36: ==_xlfn.TEXTJOIN("+",TRUE,_xlfn._xlws.FILTER(_xlfn.TEXTSPLIT(H36,,"+"),(_xlfn.TEXTSPLIT(H36,,"+")<>"埃米工具")*(_xlfn.TEXTSPLIT(H36,,"+")<>"埃米广告通"))) -> 埃米平台 | K36: ==EDATE(C36,D36) -> 46445 | N36: 服务中 | O36: 3月4完成培训 | P36: 商务不知道AIMI开始时间，导致老社媒还未结束，AIMI已开启，无法和客户解释，未拉群 | T36: 钱小二 | U36: ==COUNTIF(F:F,T36) -> 0 | V36: ==COUNTIFS($F:$F,$T36,$H:$H,$V$1) -> 0 | W36: ==COUNTIFS($F:$F,$T36,$H:$H,$W$1) -> 0 | X36: ==COUNTIFS($F:$F,$T36,$H:$H,$X$1) -> 0
A37: 36 | B37: 合肥燊智工程机械有限公司 | C37: 46080.749 | D37: 12 | E37: 46081 | F37: 刘帝 | G37: KJ2026022715666421272 | H37: 埃米平台+埃米代运营服务+埃米广告通 | I37: 成长版 | J37: ==_xlfn.TEXTJOIN("+",TRUE,_xlfn._xlws.FILTER(_xlfn.TEXTSPLIT(H37,,"+"),(_xlfn.TEXTSPLIT(H37,,"+")<>"埃米工具")*(_xlfn.TEXTSPLIT(H37,,"+")<>"埃米广告通"))) -> 埃米平台+埃米代运营服务 | K37: ==EDATE(C37,D37) -> 46445 | L37: 46085 | M37: TK, X, INS, FB | N37: 服务中 | O37: 3月4已培训完毕 | T37: 钱小二 | U37: ==COUNTIF(F:F,T37) -> 0 | V37: ==COUNTIFS($F:$F,$T37,$H:$H,$V$1) -> 0 | W37: ==COUNTIFS($F:$F,$T37,$H:$H,$W$1) -> 0 | X37: ==COUNTIFS($F:$F,$T37,$H:$H,$X$1) -> 0
A38: 37 | B38: 霸州市腾旭国际贸易有限公司 | C38: 46115.639 | D38: 1 | E38: 46081 | F38: 刘帝 | G38: KJ2026022792267178521 | H38: 埃米平台 | I38: 基础版 | J38: ==_xlfn.TEXTJOIN("+",TRUE,_xlfn._xlws.FILTER(_xlfn.TEXTSPLIT(H38,,"+"),(_xlfn.TEXTSPLIT(H38,,"+")<>"埃米工具")*(_xlfn.TEXTSPLIT(H38,,"+")<>"埃米广告通"))) -> 埃米平台 | K38: ==EDATE(C38,D38) -> 46145 | N38: 服务中 | O38: 2月28日培训完毕 | P38: 设计背景图 | T38: 陈波
A39: 38 | B39: 深圳市汇丰创新技术有限公司 | C39: 46080.795 | D39: 2 | E39: 46081 | F39: 谭婷 | G39: KJ2026022748975961103 | H39: 埃米平台 | I39: 高级版 | J39: ==_xlfn.TEXTJOIN("+",TRUE,_xlfn._xlws.FILTER(_xlfn.TEXTSPLIT(H39,,"+"),(_xlfn.TEXTSPLIT(H39,,"+")<>"埃米工具")*(_xlfn.TEXTSPLIT(H39,,"+")<>"埃米广告通"))) -> 埃米平台 | K39: ==EDATE(C39,D39) -> 46139 | N39: 服务中 | O39: 2.28培训完成 | T39: 苏晓晨 | U39: ==COUNTIF(F:F,T39) -> 0 | V39: ==COUNTIFS($F:$F,$T39,$H:$H,$V$1) -> 0 | W39: ==COUNTIFS($F:$F,$T39,$H:$H,$W$1) -> 0 | X39: ==COUNTIFS($F:$F,$T39,$H:$H,$X$1) -> 0
A40: 39 | B40: 大连泰维精密模具股份有限公司 | C40: 46081.427 | D40: 12 | E40: 46081 | F40: 张楠 | G40: KJ2026022674798700657 | H40: 埃米平台+埃米陪跑服务 | I40: 成长版 | J40: ==_xlfn.TEXTJOIN("+",TRUE,_xlfn._xlws.FILTER(_xlfn.TEXTSPLIT(H40,,"+"),(_xlfn.TEXTSPLIT(H40,,"+")<>"埃米工具")*(_xlfn.TEXTSPLIT(H40,,"+")<>"埃米广告通"))) -> 埃米平台+埃米陪跑服务 | K40: ==EDATE(C40,D40) -> 46446 | L40: 46084 | M40: TK, X, INS, Linkedin, FB | N40: 服务中 | O40: 2.28 3点培训完成 | T40: 葛延凤 | U40: ==COUNTIF(F:F,T40) -> 0 | V40: ==COUNTIFS($F:$F,$T40,$H:$H,$V$1) -> 0 | W40: ==COUNTIFS($F:$F,$T40,$H:$H,$W$1) -> 0
A41: 40 | B41: 大连春利消防设备有限公司 | C41: 46080.403 | D41: 12 | E41: 46081 | F41: 张楠 | G41: KJ2026022633314142618 | H41: 埃米平台 | I41: 成长版 | J41: ==_xlfn.TEXTJOIN("+",TRUE,_xlfn._xlws.FILTER(_xlfn.TEXTSPLIT(H41,,"+"),(_xlfn.TEXTSPLIT(H41,,"+")<>"埃米工具")*(_xlfn.TEXTSPLIT(H41,,"+")<>"埃米广告通"))) -> 埃米平台 | K41: ==EDATE(C41,D41) -> 46445 | N41: 服务中 | O41: 3月9已完成培训 | T41: 杨鲁栋 | U41: ==COUNTIF(F:F,T41) -> 0 | V41: ==COUNTIFS($F:$F,$T41,$H:$H,$V$1) -> 0 | W41: ==COUNTIFS($F:$F,$T41,$H:$H,$W$1) -> 0
A42: 41 | B42: 武汉中岩科技股份有限公司 | C42: 46080.745 | D42: 12 | E42: 46081 | F42: 谭婷 | G42: KJ2026022659384715716 | H42: 埃米平台 | I42: 成长版 | J42: ==_xlfn.TEXTJOIN("+",TRUE,_xlfn._xlws.FILTER(_xlfn.TEXTSPLIT(H42,,"+"),(_xlfn.TEXTSPLIT(H42,,"+")<>"埃米工具")*(_xlfn.TEXTSPLIT(H42,,"+")<>"埃米广告通"))) -> 埃米平台 | K42: ==EDATE(C42,D42) -> 46445 | N42: 服务中 | O42: 商务已经培训完成 | T42: 蔡锐丹 | U42: ==COUNTIF(F:F,T42) -> 0 | V42: ==COUNTIFS($F:$F,$T42,$H:$H,$V$1) -> 0 | W42: ==COUNTIFS($F:$F,$T42,$H:$H,$W$1) -> 0 | X42: ==COUNTIFS($F:$F,$T42,$H:$H,$X$1) -> 0
A43: 42 | B43: 海南智械云联工贸有限公司 | C43: 46080.724 | D43: 24 | E43: 46081 | F43: 谭婷 | G43: KJ2026022744828593584 | H43: 埃米平台+埃米陪跑服务 | I43: 成长版 | J43: ==_xlfn.TEXTJOIN("+",TRUE,_xlfn._xlws.FILTER(_xlfn.TEXTSPLIT(H43,,"+"),(_xlfn.TEXTSPLIT(H43,,"+")<>"埃米工具")*(_xlfn.TEXTSPLIT(H43,,"+")<>"埃米广告通"))) -> 埃米平台+埃米陪跑服务 | K43: ==EDATE(C43,D43) -> 46810 | L43: 46083 | M43: TK, X, INS | N43: 服务中 | O43: 3.10培训完成
A44: 43 | B44: 河北生茂包装材料有限公司 | C44: 46080.677 | D44: 12 | E44: 46081 | F44: 刘帝 | G44: KJ2026022748565218029 | H44: 埃米平台+埃米陪跑服务 | I44: 成长版 | J44: ==_xlfn.TEXTJOIN("+",TRUE,_xlfn._xlws.FILTER(_xlfn.TEXTSPLIT(H44,,"+"),(_xlfn.TEXTSPLIT(H44,,"+")<>"埃米工具")*(_xlfn.TEXTSPLIT(H44,,"+")<>"埃米广告通"))) -> 埃米平台+埃米陪跑服务 | K44: ==EDATE(C44,D44) -> 46445 | L44: 46106 | M44: INS, FB, Linkedin,TK, VK | N44: 服务中 | O44: 3月10日 11:00培训完成
A45: 44 | B45: 山东剑齿虎数控设备有限公司 | C45: 46081.388 | D45: 12 | E45: 46081 | F45: 张楠 | G45: KJ2026022723466122336 | H45: 埃米平台 | I45: 成长版 | J45: ==_xlfn.TEXTJOIN("+",TRUE,_xlfn._xlws.FILTER(_xlfn.TEXTSPLIT(H45,,"+"),(_xlfn.TEXTSPLIT(H45,,"+")<>"埃米工具")*(_xlfn.TEXTSPLIT(H45,,"+")<>"埃米广告通"))) -> 埃米平台 | K45: ==EDATE(C45,D45) -> 46446 | N45: 服务中 | O45: 3月3已培训完毕
A46: 45 | B46: 威海水悦宏科户外用品有限公司 | C46: 46081.459 | D46: 12 | E46: 46081 | F46: 武卓玉 | G46: KJ2026022717436184335 | H46: 埃米平台 | I46: 成长版 | J46: ==_xlfn.TEXTJOIN("+",TRUE,_xlfn._xlws.FILTER(_xlfn.TEXTSPLIT(H46,,"+"),(_xlfn.TEXTSPLIT(H46,,"+")<>"埃米工具")*(_xlfn.TEXTSPLIT(H46,,"+")<>"埃米广告通"))) -> 埃米平台 | K46: ==EDATE(C46,D46) -> 46446 | N46: 服务中 | O46: 2026/3/3已培训完毕
A47: 46 | B47: 四川欧威尔赛思科技有限公司 | C47: 46081.397 | D47: 12 | E47: 46081 | F47: 武卓玉 | G47: KJ2026022782768837931 | H47: 埃米平台 | I47: 高级版 | J47: ==_xlfn.TEXTJOIN("+",TRUE,_xlfn._xlws.FILTER(_xlfn.TEXTSPLIT(H47,,"+"),(_xlfn.TEXTSPLIT(H47,,"+")<>"埃米工具")*(_xlfn.TEXTSPLIT(H47,,"+")<>"埃米广告通"))) -> 埃米平台 | K47: ==EDATE(C47,D47) -> 46446 | N47: 服务中 | O47: 2026/3/2已培训完毕；3月20号再次培训
A48: 47 | B48: 佛山市豪特自动化科技有限公司 | C48: 46081.41 | D48: 12 | E48: 46081 | F48: 刘帝 | G48: KJ2026022703165421973 | H48: 埃米平台 | I48: 成长版 | J48: ==_xlfn.TEXTJOIN("+",TRUE,_xlfn._xlws.FILTER(_xlfn.TEXTSPLIT(H48,,"+"),(_xlfn.TEXTSPLIT(H48,,"+")<>"埃米工具")*(_xlfn.TEXTSPLIT(H48,,"+")<>"埃米广告通"))) -> 埃米平台 | K48: ==EDATE(C48,D48) -> 46446 | N48: 服务中 | O48: 客户出国未回商务说等客户回国后开始
A49: 48 | B49: 青岛泽宏锦盛商贸有限公司 | C49: 46081.518 | D49: 12 | E49: 46081 | F49: 武卓玉 | G49: KJ2026022814710401432 | H49: 埃米平台 | I49: 成长版 | J49: ==_xlfn.TEXTJOIN("+",TRUE,_xlfn._xlws.FILTER(_xlfn.TEXTSPLIT(H49,,"+"),(_xlfn.TEXTSPLIT(H49,,"+")<>"埃米工具")*(_xlfn.TEXTSPLIT(H49,,"+")<>"埃米广告通"))) -> 埃米平台 | K49: ==EDATE(C49,D49) -> 46446 | N49: 服务中
A50: 49 | B50: 山东通祥机械科技有限公司 | C50: 46081.461 | D50: 12 | E50: 46081 | F50: 张楠 | G50: KJ2026022835149343271 | H50: 埃米平台 | I50: 基础版 | J50: ==_xlfn.TEXTJOIN("+",TRUE,_xlfn._xlws.FILTER(_xlfn.TEXTSPLIT(H50,,"+"),(_xlfn.TEXTSPLIT(H50,,"+")<>"埃米工具")*(_xlfn.TEXTSPLIT(H50,,"+")<>"埃米广告通"))) -> 埃米平台 | K50: ==EDATE(C50,D50) -> 46446 | N50: 服务中 | O50: 3月2已培训完毕
A51: 50 | B51: 青岛帝森旅居车辆制造有限公司 | C51: 46081.561 | D51: 12 | E51: 46081 | F51: 刘帝 | G51: KJ2026022838514341641 | H51: 埃米平台 | I51: 成长版 | J51: ==_xlfn.TEXTJOIN("+",TRUE,_xlfn._xlws.FILTER(_xlfn.TEXTSPLIT(H51,,"+"),(_xlfn.TEXTSPLIT(H51,,"+")<>"埃米工具")*(_xlfn.TEXTSPLIT(H51,,"+")<>"埃米广告通"))) -> 埃米平台 | K51: ==EDATE(C51,D51) -> 46446 | N51: 服务中 | O51: 2026/3/2已培训完毕
A52: 51 | B52: 平原百斯特机械工具有限公司 | C52: 46081.527 | D52: 12 | E52: 46081 | F52: 张楠 | G52: KJ2026022809368280119 | H52: 埃米平台+埃米陪跑服务 | I52: 成长版 | J52: ==_xlfn.TEXTJOIN("+",TRUE,_xlfn._xlws.FILTER(_xlfn.TEXTSPLIT(H52,,"+"),(_xlfn.TEXTSPLIT(H52,,"+")<>"埃米工具")*(_xlfn.TEXTSPLIT(H52,,"+")<>"埃米广告通"))) -> 埃米平台+埃米陪跑服务 | K52: ==EDATE(C52,D52) -> 46446 | L52: 46083 | M52: TK, INS, X, Youtube, FB | N52: 服务中 | O52: 3月3日 14点培训
A53: 52 | B53: 威海帝皇游艇有限公司 | C53: 46081.611 | D53: 12 | E53: 46081 | F53: 刘帝 | G53: KJ2026022812823358565 | H53: 埃米平台 | I53: 成长版 | J53: ==_xlfn.TEXTJOIN("+",TRUE,_xlfn._xlws.FILTER(_xlfn.TEXTSPLIT(H53,,"+"),(_xlfn.TEXTSPLIT(H53,,"+")<>"埃米工具")*(_xlfn.TEXTSPLIT(H53,,"+")<>"埃米广告通"))) -> 埃米平台 | K53: ==EDATE(C53,D53) -> 46446 | N53: 服务中 | O53: 3月10号培训完毕
A54: 53 | B54: 河北津宏玮邦化工有限公司 | C54: 46081.637 | D54: 12 | E54: 46081 | F54: 谭婷 | G54: KJ2026022802334477265 | H54: 埃米平台 | I54: 成长版 | J54: ==_xlfn.TEXTJOIN("+",TRUE,_xlfn._xlws.FILTER(_xlfn.TEXTSPLIT(H54,,"+"),(_xlfn.TEXTSPLIT(H54,,"+")<>"埃米工具")*(_xlfn.TEXTSPLIT(H54,,"+")<>"埃米广告通"))) -> 埃米平台 | K54: ==EDATE(C54,D54) -> 46446 | N54: 服务中 | O54: 3.2培训完成
A55: 54 | B55: 湖南闪晶贸易有限公司 | C55: 46081.649 | D55: 12 | E55: 46081 | F55: 张楠 | G55: KJ2026022834126320658 | H55: 埃米平台 | I55: 成长版 | J55: ==_xlfn.TEXTJOIN("+",TRUE,_xlfn._xlws.FILTER(_xlfn.TEXTSPLIT(H55,,"+"),(_xlfn.TEXTSPLIT(H55,,"+")<>"埃米工具")*(_xlfn.TEXTSPLIT(H55,,"+")<>"埃米广告通"))) -> 埃米平台 | K55: ==EDATE(C55,D55) -> 46446 | N55: 服务中 | O55: 3月2日 9.30培训完成
A56: 55 | B56: 威海倚春服装有限公司 | C56: 46081.663 | D56: 12 | E56: 46081 | F56: 武卓玉 | G56: KJ2026022891512230322 | H56: 埃米平台+埃米陪跑服务 | I56: 成长版 | J56: ==_xlfn.TEXTJOIN("+",TRUE,_xlfn._xlws.FILTER(_xlfn.TEXTSPLIT(H56,,"+"),(_xlfn.TEXTSPLIT(H56,,"+")<>"埃米工具")*(_xlfn.TEXTSPLIT(H56,,"+")<>"埃米广告通"))) -> 埃米平台+埃米陪跑服务 | K56: ==EDATE(C56,D56) -> 46446 | L56: 46093 | M56: TK, FB, X, Youtube, INS | N56: 服务中 | O56: 3月9已完成培训
A57: 56 | B57: 青岛斯科畜牧科技有限公司 | C57: 46081.617 | D57: 12 | E57: 46081 | F57: 张楠 | G57: KJ2026022646419386256 | H57: 埃米平台 | I57: 成长版 | J57: ==_xlfn.TEXTJOIN("+",TRUE,_xlfn._xlws.FILTER(_xlfn.TEXTSPLIT(H57,,"+"),(_xlfn.TEXTSPLIT(H57,,"+")<>"埃米工具")*(_xlfn.TEXTSPLIT(H57,,"+")<>"埃米广告通"))) -> 埃米平台 | K57: ==EDATE(C57,D57) -> 46446 | N57: 服务中
A58: 57 | B58: 威海托罗服饰有限公司 | C58: 46081.673 | D58: 12 | E58: 46081 | F58: 武卓玉 | G58: KJ2026022732230432556 | H58: 埃米平台+埃米陪跑服务 | I58: 成长版 | J58: ==_xlfn.TEXTJOIN("+",TRUE,_xlfn._xlws.FILTER(_xlfn.TEXTSPLIT(H58,,"+"),(_xlfn.TEXTSPLIT(H58,,"+")<>"埃米工具")*(_xlfn.TEXTSPLIT(H58,,"+")<>"埃米广告通"))) -> 埃米平台+埃米陪跑服务 | K58: ==EDATE(C58,D58) -> 46446 | L58: 46097 | M58: TK, X, INS, Youtube, FB | N58: 服务中 | O58: 3.18公开课
A59: 58 | B59: 成都蒽科科技有限公司 | C59: 46081.654 | D59: 12 | E59: 46081 | F59: 谭婷 | G59: KJ2026022879140041358 | H59: 埃米平台+埃米陪跑服务 | I59: 成长版 | J59: ==_xlfn.TEXTJOIN("+",TRUE,_xlfn._xlws.FILTER(_xlfn.TEXTSPLIT(H59,,"+"),(_xlfn.TEXTSPLIT(H59,,"+")<>"埃米工具")*(_xlfn.TEXTSPLIT(H59,,"+")<>"埃米广告通"))) -> 埃米平台+埃米陪跑服务 | K59: ==EDATE(C59,D59) -> 46446 | L59: 46091 | M59: TK, X, INS, Youtube, FB, Linkedin | N59: 服务中 | O59: 3.18公开课
A60: 59 | B60: 湖北锦金机械电子科技有限公司 | C60: 46081.629 | D60: 12 | E60: 46081 | F60: 刘帝 | G60: KJ2026022815404481096 | H60: 埃米平台 | I60: 成长版 | J60: ==_xlfn.TEXTJOIN("+",TRUE,_xlfn._xlws.FILTER(_xlfn.TEXTSPLIT(H60,,"+"),(_xlfn.TEXTSPLIT(H60,,"+")<>"埃米工具")*(_xlfn.TEXTSPLIT(H60,,"+")<>"埃米广告通"))) -> 埃米平台 | K60: ==EDATE(C60,D60) -> 46446 | N60: 服务中 | O60: 参加3月18日联播 | Q60: 延迟交付
A61: 60 | B61: 杭州迅影科技有限公司 | C61: 46081.717 | D61: 12 | E61: 46081 | F61: 张楠 | G61: KJ2026022851407027901 | H61: 埃米平台 | I61: 成长版 | J61: ==_xlfn.TEXTJOIN("+",TRUE,_xlfn._xlws.FILTER(_xlfn.TEXTSPLIT(H61,,"+"),(_xlfn.TEXTSPLIT(H61,,"+")<>"埃米工具")*(_xlfn.TEXTSPLIT(H61,,"+")<>"埃米广告通"))) -> 埃米平台 | K61: ==EDATE(C61,D61) -> 46446 | N61: 服务中 | P61: 潜在客诉，客户对商务有抱怨，客户活跃度极低
A62: 61 | B62: 苏州市恒协机械有限公司 | C62: 46081.864 | D62: 12 | E62: 46083 | F62: 武卓玉 | G62: KJ2026022870765540596 | H62: 埃米平台+埃米代运营服务+埃米广告通 | I62: 成长版 | J62: ==_xlfn.TEXTJOIN("+",TRUE,_xlfn._xlws.FILTER(_xlfn.TEXTSPLIT(H62,,"+"),(_xlfn.TEXTSPLIT(H62,,"+")<>"埃米工具")*(_xlfn.TEXTSPLIT(H62,,"+")<>"埃米广告通"))) -> 埃米平台+埃米代运营服务 | K62: ==EDATE(C62,D62) -> 46446 | L62: 46083 | M62: FB,TK, Linkedin, VK | N62: 服务中 | O62: 3.18公开课
A63: 62 | B63: 北京星光陆通视音频广播技术有限公司 | C63: 46081.773 | D63: 12 | E63: 46083 | F63: 刘帝 | G63: KJ2026022883044374426 | H63: 埃米平台+埃米陪跑服务 | I63: 成长版 | J63: ==_xlfn.TEXTJOIN("+",TRUE,_xlfn._xlws.FILTER(_xlfn.TEXTSPLIT(H63,,"+"),(_xlfn.TEXTSPLIT(H63,,"+")<>"埃米工具")*(_xlfn.TEXTSPLIT(H63,,"+")<>"埃米广告通"))) -> 埃米平台+埃米陪跑服务 | K63: ==EDATE(C63,D63) -> 46446 | L63: 46087 | M63: TK, FB, X, INS, Youtube | N63: 服务中 | O63: 3月4号培训 | P63: 老社媒
A64: 63 | B64: 上海克础机械（集团）有限公司 | C64: 46081.79 | D64: 12 | E64: 46083 | F64: 张楠 | G64: KJ2026022752484397110 | H64: 埃米平台+埃米陪跑服务 | I64: 成长版 | J64: ==_xlfn.TEXTJOIN("+",TRUE,_xlfn._xlws.FILTER(_xlfn.TEXTSPLIT(H64,,"+"),(_xlfn.TEXTSPLIT(H64,,"+")<>"埃米工具")*(_xlfn.TEXTSPLIT(H64,,"+")<>"埃米广告通"))) -> 埃米平台+埃米陪跑服务 | K64: ==EDATE(C64,D64) -> 46446 | N64: 服务中 | O64: 3月4日 15点培训
A65: 64 | B65: 领智人工智能科技（威海）有限公司 | C65: 46081.722 | D65: 12 | E65: 46083 | F65: 武卓玉 | G65: KJ2026022803671263297 | H65: 埃米平台 | I65: 成长版 | J65: ==_xlfn.TEXTJOIN("+",TRUE,_xlfn._xlws.FILTER(_xlfn.TEXTSPLIT(H65,,"+"),(_xlfn.TEXTSPLIT(H65,,"+")<>"埃米工具")*(_xlfn.TEXTSPLIT(H65,,"+")<>"埃米广告通"))) -> 埃米平台 | K65: ==EDATE(C65,D65) -> 46446 | N65: 服务中 | Q65: 延迟交付
A66: 65 | B66: 山东中联化学有限公司 | C66: 46083.511 | D66: 12 | E66: 46083 | F66: 谭婷 | G66: KJ2026030270232630054 | H66: 埃米平台 | I66: 成长版 | J66: ==_xlfn.TEXTJOIN("+",TRUE,_xlfn._xlws.FILTER(_xlfn.TEXTSPLIT(H66,,"+"),(_xlfn.TEXTSPLIT(H66,,"+")<>"埃米工具")*(_xlfn.TEXTSPLIT(H66,,"+")<>"埃米广告通"))) -> 埃米平台 | K66: ==EDATE(C66,D66) -> 46448 | N66: 服务中 | O66: 3.2培训完成
A67: 66 | B67: 佛山市南海区粤柯创机械设备销售行 | C67: 46083.592 | D67: 12 | E67: 46083 | F67: 谭婷 | G67: KJ2026030277987254407 | H67: 埃米平台 | I67: 成长版 | J67: ==_xlfn.TEXTJOIN("+",TRUE,_xlfn._xlws.FILTER(_xlfn.TEXTSPLIT(H67,,"+"),(_xlfn.TEXTSPLIT(H67,,"+")<>"埃米工具")*(_xlfn.TEXTSPLIT(H67,,"+")<>"埃米广告通"))) -> 埃米平台 | K67: ==EDATE(C67,D67) -> 46448 | N67: 服务中 | O67: 3.3培训完成
A68: 67 | B68: 湖北宏宇专用汽车有限公司 | C68: 46083.645 | D68: 12 | E68: 46083 | F68: 武卓玉 | G68: KJ2026022639154446430 | H68: 埃米平台+埃米陪跑服务 | I68: 成长版 | J68: ==_xlfn.TEXTJOIN("+",TRUE,_xlfn._xlws.FILTER(_xlfn.TEXTSPLIT(H68,,"+"),(_xlfn.TEXTSPLIT(H68,,"+")<>"埃米工具")*(_xlfn.TEXTSPLIT(H68,,"+")<>"埃米广告通"))) -> 埃米平台+埃米陪跑服务 | K68: ==EDATE(C68,D68) -> 46448 | L68: 46086 | M68: X, INS, Youtube, FB,TK | N68: 服务中 | O68: 3月3日 14：00培训完成
A69: 68 | B69: 苏州市圣马丁服装有限公司 | C69: 46083.687 | D69: 12 | E69: 46083 | F69: 刘帝 | G69: KJ2026030278182375324 | H69: 埃米平台+埃米陪跑服务 | I69: 成长版 | J69: ==_xlfn.TEXTJOIN("+",TRUE,_xlfn._xlws.FILTER(_xlfn.TEXTSPLIT(H69,,"+"),(_xlfn.TEXTSPLIT(H69,,"+")<>"埃米工具")*(_xlfn.TEXTSPLIT(H69,,"+")<>"埃米广告通"))) -> 埃米平台+埃米陪跑服务 | K69: ==EDATE(C69,D69) -> 46448 | L69: 46084 | M69: FB, INS,TK | N69: 服务中
A70: 69 | B70: 威海帅威户外用品有限公司 | C70: 46083.751 | D70: 12 | E70: 46083 | F70: 张楠 | G70: KJ2026030206011935019 | H70: 埃米平台 | I70: 高级版 | J70: ==_xlfn.TEXTJOIN("+",TRUE,_xlfn._xlws.FILTER(_xlfn.TEXTSPLIT(H70,,"+"),(_xlfn.TEXTSPLIT(H70,,"+")<>"埃米工具")*(_xlfn.TEXTSPLIT(H70,,"+")<>"埃米广告通"))) -> 埃米平台 | K70: ==EDATE(C70,D70) -> 46448 | N70: 服务中 | O70: 3月4完成培训 | P70: 客户要更改AIMI 账号，修改成功后拉群
A71: 70 | B71: 佛山市牧风科技有限公司 | C71: 46083.911 | D71: 12 | E71: 46084 | F71: 武卓玉 | G71: KJ2026030215890987862 | H71: 埃米平台+埃米陪跑服务 | I71: 成长版 | J71: ==_xlfn.TEXTJOIN("+",TRUE,_xlfn._xlws.FILTER(_xlfn.TEXTSPLIT(H71,,"+"),(_xlfn.TEXTSPLIT(H71,,"+")<>"埃米工具")*(_xlfn.TEXTSPLIT(H71,,"+")<>"埃米广告通"))) -> 埃米平台+埃米陪跑服务 | K71: ==EDATE(C71,D71) -> 46448 | L71: 46111 | M71: FB | N71: 服务中 | O71: 3月4已培训完毕 | P71: 信息在旧的收集表
A72: 71 | B72: 济南鑫沃通达贸易有限公司 | C72: 46084.423 | D72: 12 | E72: 46084 | G72: KJ2026030391091106184 | H72: 埃米平台 | I72: 成长版 | J72: ==_xlfn.TEXTJOIN("+",TRUE,_xlfn._xlws.FILTER(_xlfn.TEXTSPLIT(H72,,"+"),(_xlfn.TEXTSPLIT(H72,,"+")<>"埃米工具")*(_xlfn.TEXTSPLIT(H72,,"+")<>"埃米广告通"))) -> 埃米平台 | K72: ==EDATE(C72,D72) -> 46449 | N72: 服务中 | O72: 3.4培训完成
A73: 72 | B73: 北京而为科技有限公司 | C73: 46084.603 | D73: 12 | E73: 46084 | F73: 张楠 | G73: KJ2026030398497935579 | H73: 埃米平台+埃米陪跑服务 | I73: 成长版 | J73: ==_xlfn.TEXTJOIN("+",TRUE,_xlfn._xlws.FILTER(_xlfn.TEXTSPLIT(H73,,"+"),(_xlfn.TEXTSPLIT(H73,,"+")<>"埃米工具")*(_xlfn.TEXTSPLIT(H73,,"+")<>"埃米广告通"))) -> 埃米平台+埃米陪跑服务 | K73: ==EDATE(C73,D73) -> 46449 | L73: 46086 | M73: X, FB, INS,TK, VK | N73: 服务中 | O73: 3月4日 10：00培训完成
A74: 73 | B74: 青岛泰康和顺海绵制品有限公司 | C74: 46084.631 | D74: 12 | E74: 46084 | F74: 刘帝 | G74: KJ2026030372288565115 | H74: 埃米平台 | I74: 成长版 | J74: ==_xlfn.TEXTJOIN("+",TRUE,_xlfn._xlws.FILTER(_xlfn.TEXTSPLIT(H74,,"+"),(_xlfn.TEXTSPLIT(H74,,"+")<>"埃米工具")*(_xlfn.TEXTSPLIT(H74,,"+")<>"埃米广告通"))) -> 埃米平台 | K74: ==EDATE(C74,D74) -> 46449 | N74: 服务中 | O74: 3月6日完成培训
A75: 74 | B75: 上海明辉标签有限公司 | C75: 46084.665 | D75: 12 | E75: 46084 | F75: 刘帝 | G75: KJ2026030301813402994 | H75: 埃米平台 | I75: 成长版 | J75: ==_xlfn.TEXTJOIN("+",TRUE,_xlfn._xlws.FILTER(_xlfn.TEXTSPLIT(H75,,"+"),(_xlfn.TEXTSPLIT(H75,,"+")<>"埃米工具")*(_xlfn.TEXTSPLIT(H75,,"+")<>"埃米广告通"))) -> 埃米平台 | K75: ==EDATE(C75,D75) -> 46449 | N75: 服务中 | O75: 2026.3.20 | Q75: 延迟交付
A76: 75 | B76: 金华正邦传动有限公司 | C76: 46084.666 | D76: 12 | E76: 46084 | F76: 张楠 | G76: KJ2026030383795402056 | H76: 埃米平台 | I76: 成长版 | J76: ==_xlfn.TEXTJOIN("+",TRUE,_xlfn._xlws.FILTER(_xlfn.TEXTSPLIT(H76,,"+"),(_xlfn.TEXTSPLIT(H76,,"+")<>"埃米工具")*(_xlfn.TEXTSPLIT(H76,,"+")<>"埃米广告通"))) -> 埃米平台 | K76: ==EDATE(C76,D76) -> 46449 | N76: 服务中 | O76: 3月6完成培训
A77: 76 | B77: 海宁市方圣包装材料有限公司 | C77: 46084.707 | D77: 12 | E77: 46084 | F77: 武卓玉 | G77: KJ2026030387712441442 | H77: 埃米平台 | I77: 成长版 | J77: ==_xlfn.TEXTJOIN("+",TRUE,_xlfn._xlws.FILTER(_xlfn.TEXTSPLIT(H77,,"+"),(_xlfn.TEXTSPLIT(H77,,"+")<>"埃米工具")*(_xlfn.TEXTSPLIT(H77,,"+")<>"埃米广告通"))) -> 埃米平台 | K77: ==EDATE(C77,D77) -> 46449 | N77: 服务中 | O77: 3月6日完成培训
A78: 77 | B78: 嘉兴市集珵机械有限公司 | C78: 46084.696 | D78: 12 | E78: 46084 | F78: 刘帝 | G78: KJ2026030393658094056 | H78: 埃米平台 | I78: 成长版 | J78: ==_xlfn.TEXTJOIN("+",TRUE,_xlfn._xlws.FILTER(_xlfn.TEXTSPLIT(H78,,"+"),(_xlfn.TEXTSPLIT(H78,,"+")<>"埃米工具")*(_xlfn.TEXTSPLIT(H78,,"+")<>"埃米广告通"))) -> 埃米平台 | K78: ==EDATE(C78,D78) -> 46449 | N78: 服务中 | O78: 3月6日16：45培训
A79: 78 | B79: 广州大鲸游乐设备有限公司 | C79: 46084.707 | D79: 12 | E79: 46084 | F79: 张楠 | G79: KJ2026030386192936014 | H79: 埃米平台 | I79: 成长版 | J79: ==_xlfn.TEXTJOIN("+",TRUE,_xlfn._xlws.FILTER(_xlfn.TEXTSPLIT(H79,,"+"),(_xlfn.TEXTSPLIT(H79,,"+")<>"埃米工具")*(_xlfn.TEXTSPLIT(H79,,"+")<>"埃米广告通"))) -> 埃米平台 | K79: ==EDATE(C79,D79) -> 46449 | N79: 服务中 | O79: 3月12培训完成
A80: 79 | B80: 山东铂迪兰机械有限公司 | C80: 46084.699 | D80: 12 | E80: 46084 | F80: 武卓玉 | G80: KJ2026030322144320458 | H80: 埃米平台 | I80: 成长版 | J80: ==_xlfn.TEXTJOIN("+",TRUE,_xlfn._xlws.FILTER(_xlfn.TEXTSPLIT(H80,,"+"),(_xlfn.TEXTSPLIT(H80,,"+")<>"埃米工具")*(_xlfn.TEXTSPLIT(H80,,"+")<>"埃米广告通"))) -> 埃米平台 | K80: ==EDATE(C80,D80) -> 46449 | N80: 服务中 | O80: 3月12培训完成
A81: 80 | B81: 佛山市富琪家具有限公司 | C81: 46084.737 | D81: 12 | E81: 46085 | F81: 刘帝 | G81: KJ2026030383596728419 | H81: 埃米平台+埃米代运营服务+埃米广告通 | I81: 成长版 | J81: ==_xlfn.TEXTJOIN("+",TRUE,_xlfn._xlws.FILTER(_xlfn.TEXTSPLIT(H81,,"+"),(_xlfn.TEXTSPLIT(H81,,"+")<>"埃米工具")*(_xlfn.TEXTSPLIT(H81,,"+")<>"埃米广告通"))) -> 埃米平台+埃米代运营服务 | K81: ==EDATE(C81,D81) -> 46449 | L81: 46095 | M81: TK, X, INS, Youtube, FB | N81: 服务中 | O81: 4月1日预约培训
A82: 81 | B82: 东莞市沃富五金制品有限公司 | C82: 46090.747 | D82: 12 | E82: 46085 | F82: 武卓玉 | G82: KJ2026030367354133027 | H82: 埃米平台+埃米陪跑服务 | I82: 高级版 | J82: ==_xlfn.TEXTJOIN("+",TRUE,_xlfn._xlws.FILTER(_xlfn.TEXTSPLIT(H82,,"+"),(_xlfn.TEXTSPLIT(H82,,"+")<>"埃米工具")*(_xlfn.TEXTSPLIT(H82,,"+")<>"埃米广告通"))) -> 埃米平台+埃米陪跑服务 | K82: ==EDATE(C82,D82) -> 46455 | L82: 46097 | M82: FB,TK, X, Youtube, INS | N82: 服务中 | O82: 3月18日参加联播
A83: 82 | B83: 湖北龙瑞铝业有限公司 | C83: 46084.791 | D83: 12 | E83: 46085 | F83: 张楠 | G83: KJ2026030347778421036 | H83: 埃米平台+埃米陪跑服务 | I83: 成长版 | J83: ==_xlfn.TEXTJOIN("+",TRUE,_xlfn._xlws.FILTER(_xlfn.TEXTSPLIT(H83,,"+"),(_xlfn.TEXTSPLIT(H83,,"+")<>"埃米工具")*(_xlfn.TEXTSPLIT(H83,,"+")<>"埃米广告通"))) -> 埃米平台+埃米陪跑服务 | K83: ==EDATE(C83,D83) -> 46449 | L83: 46091 | M83: FB,TK, INS | N83: 服务中 | O83: 3月16培训完成 | P83: 签A推B有审批邮件，审批耗时导致一直没分配运营专员 | Q83: 签A推B
A84: 83 | B84: 程力汽车（武汉）有限公司 | C84: 46084.505 | D84: 12 | E84: 46085 | F84: 张楠 | G84: KJ2026022869596905789 | H84: 埃米平台+埃米代运营服务+埃米广告通 | I84: 成长版 | J84: ==_xlfn.TEXTJOIN("+",TRUE,_xlfn._xlws.FILTER(_xlfn.TEXTSPLIT(H84,,"+"),(_xlfn.TEXTSPLIT(H84,,"+")<>"埃米工具")*(_xlfn.TEXTSPLIT(H84,,"+")<>"埃米广告通"))) -> 埃米平台+埃米代运营服务 | K84: ==EDATE(C84,D84) -> 46449 | L84: 46085 | M84: TK, Youtube, FB, VK, Linkedin | N84: 服务中 | O84: 3月10培训完成 | P84: 1、群名：CLW-WH-埃米代运营服务群 2、更换过平台：最终是先行运营facebook youtube tiktok三个平台； linkedin vk两个平台客户注册并授权后，我们再开始运营
A85: 84 | B85: 湖北美睦恩医疗设备有限公司 | C85: 46084.706 | D85: 12 | E85: 46085 | F85: 刘帝 | G85: KJ2026030200453671747 | H85: 埃米平台 | I85: 成长版 | J85: ==_xlfn.TEXTJOIN("+",TRUE,_xlfn._xlws.FILTER(_xlfn.TEXTSPLIT(H85,,"+"),(_xlfn.TEXTSPLIT(H85,,"+")<>"埃米工具")*(_xlfn.TEXTSPLIT(H85,,"+")<>"埃米广告通"))) -> 埃米平台 | K85: ==EDATE(C85,D85) -> 46449 | N85: 服务中 | O85: 3月10培训完成
A86: 85 | B86: 烟台冠铭国际贸易有限公司 | C86: 46084.73 | D86: 12 | E86: 46085 | F86: 武卓玉 | G86: KJ2026030362766360904 | H86: 埃米平台 | I86: 高级版 | J86: ==_xlfn.TEXTJOIN("+",TRUE,_xlfn._xlws.FILTER(_xlfn.TEXTSPLIT(H86,,"+"),(_xlfn.TEXTSPLIT(H86,,"+")<>"埃米工具")*(_xlfn.TEXTSPLIT(H86,,"+")<>"埃米广告通"))) -> 埃米平台 | K86: ==EDATE(C86,D86) -> 46449 | N86: 服务中 | O86: 3月20培训完成
A87: 86 | B87: 浙江能兴电气科技有限公司 | C87: 46084.494 | D87: 12 | E87: 46085 | F87: 张楠 | G87: KJ2026030225913264117 | H87: 埃米平台 | I87: 成长版 | J87: ==_xlfn.TEXTJOIN("+",TRUE,_xlfn._xlws.FILTER(_xlfn.TEXTSPLIT(H87,,"+"),(_xlfn.TEXTSPLIT(H87,,"+")<>"埃米工具")*(_xlfn.TEXTSPLIT(H87,,"+")<>"埃米广告通"))) -> 埃米平台 | K87: ==EDATE(C87,D87) -> 46449 | P87: 已申请延迟服务：销售误以为是随时开启服务，所以和客户约定了4、5月份再开始 | Q87: 延迟交付
A88: 87 | B88: 江阴市钟联国际贸易有限公司 | C88: 46085.674 | D88: 24 | E88: 46085 | F88: 刘帝 | G88: KJ2026030211205282927 | H88: 埃米平台+埃米代运营服务+埃米广告通 | I88: 成长版 | J88: ==_xlfn.TEXTJOIN("+",TRUE,_xlfn._xlws.FILTER(_xlfn.TEXTSPLIT(H88,,"+"),(_xlfn.TEXTSPLIT(H88,,"+")<>"埃米工具")*(_xlfn.TEXTSPLIT(H88,,"+")<>"埃米广告通"))) -> 埃米平台+埃米代运营服务 | K88: ==EDATE(C88,D88) -> 46816 | L88: 46086 | M88: TK, X, INS, Youtube, FB | N88: 服务中 | P88: 销售以为是随时开启服务，所以和客户约定在4、5月份再开始。经过和客户沟通后 客户还是坚持4、5月份再对接，暂时不拉群
A89: 88 | B89: 北京电科能创技术有限公司天津分公司 | C89: 46085.698 | D89: 12 | E89: 46085 | F89: 武卓玉 | G89: KJ2026030478733003420 | H89: 埃米平台 | I89: 成长版 | J89: ==_xlfn.TEXTJOIN("+",TRUE,_xlfn._xlws.FILTER(_xlfn.TEXTSPLIT(H89,,"+"),(_xlfn.TEXTSPLIT(H89,,"+")<>"埃米工具")*(_xlfn.TEXTSPLIT(H89,,"+")<>"埃米广告通"))) -> 埃米平台 | K89: ==EDATE(C89,D89) -> 46450 | N89: 服务中 | O89: 3月11日培训 | P89: 陪跑服务-tk fb ins
A90: 89 | B90: 德州道行机械有限公司 | C90: 46085.687 | D90: 12 | E90: 46085 | F90: 张楠 | G90: KJ2026030493318516286 | H90: 埃米平台 | I90: 成长版 | J90: ==_xlfn.TEXTJOIN("+",TRUE,_xlfn._xlws.FILTER(_xlfn.TEXTSPLIT(H90,,"+"),(_xlfn.TEXTSPLIT(H90,,"+")<>"埃米工具")*(_xlfn.TEXTSPLIT(H90,,"+")<>"埃米广告通"))) -> 埃米平台 | K90: ==EDATE(C90,D90) -> 46450 | N90: 服务中 | O90: 3月11日三点半培训
A91: 90 | B91: 大连现代玻璃钢船艇有限公司 | C91: 46085.685 | D91: 12 | E91: 46085 | F91: 武卓玉 | G91: KJ2026022706675686366 | H91: 埃米平台 | I91: 成长版 | J91: ==_xlfn.TEXTJOIN("+",TRUE,_xlfn._xlws.FILTER(_xlfn.TEXTSPLIT(H91,,"+"),(_xlfn.TEXTSPLIT(H91,,"+")<>"埃米工具")*(_xlfn.TEXTSPLIT(H91,,"+")<>"埃米广告通"))) -> 埃米平台 | K91: ==EDATE(C91,D91) -> 46450 | N91: 服务中 | O91: 3月18日参加联播
A92: 91 | B92: 江阴市金光化纤有限公司 | C92: 46085.748 | D92: 12 | E92: 46085 | F92: 谭婷 | G92: KJ2026030496691058749 | H92: 埃米平台 | I92: 成长版 | J92: ==_xlfn.TEXTJOIN("+",TRUE,_xlfn._xlws.FILTER(_xlfn.TEXTSPLIT(H92,,"+"),(_xlfn.TEXTSPLIT(H92,,"+")<>"埃米工具")*(_xlfn.TEXTSPLIT(H92,,"+")<>"埃米广告通"))) -> 埃米平台 | K92: ==EDATE(C92,D92) -> 46450 | N92: 服务中 | P92: 客户很忙，说他到时候联系我
A93: 92 | B93: 浙江展用工贸有限公司 | C93: 46085.75 | D93: 12 | E93: 46086 | F93: 谭婷 | G93: KJ2026030267452445715 | H93: 埃米平台 | I93: 高级版 | J93: ==_xlfn.TEXTJOIN("+",TRUE,_xlfn._xlws.FILTER(_xlfn.TEXTSPLIT(H93,,"+"),(_xlfn.TEXTSPLIT(H93,,"+")<>"埃米工具")*(_xlfn.TEXTSPLIT(H93,,"+")<>"埃米广告通"))) -> 埃米平台 | K93: ==EDATE(C93,D93) -> 46450 | N93: 服务中 | O93: 3.12培训完成
A94: 93 | B94: 长沙悦翼医疗科技有限公司 | C94: 46086.476 | D94: 12 | E94: 46086 | F94: 刘帝 | G94: KJ2026030573714427620 | H94: 埃米平台 | I94: 基础版 | J94: ==_xlfn.TEXTJOIN("+",TRUE,_xlfn._xlws.FILTER(_xlfn.TEXTSPLIT(H94,,"+"),(_xlfn.TEXTSPLIT(H94,,"+")<>"埃米工具")*(_xlfn.TEXTSPLIT(H94,,"+")<>"埃米广告通"))) -> 埃米平台 | K94: ==EDATE(C94,D94) -> 46451 | N94: 服务中 | O94: 3月12日 10：00培训完成
A95: 94 | B95: 桐乡市飞琥科技有限公司 | C95: 46086.638 | D95: 12 | E95: 46086 | F95: 谭婷 | G95: KJ2026030582018055491 | H95: 埃米平台 | I95: 成长版 | J95: ==_xlfn.TEXTJOIN("+",TRUE,_xlfn._xlws.FILTER(_xlfn.TEXTSPLIT(H95,,"+"),(_xlfn.TEXTSPLIT(H95,,"+")<>"埃米工具")*(_xlfn.TEXTSPLIT(H95,,"+")<>"埃米广告通"))) -> 埃米平台 | K95: ==EDATE(C95,D95) -> 46451 | N95: 服务中 | O95: 3.6培训完成
A96: 95 | B96: 威海皓富机械设备有限公司 | C96: 46086.654 | D96: 12 | E96: 46086 | F96: 张楠 | G96: KJ2026030584765860251 | H96: 埃米平台 | I96: 成长版 | J96: ==_xlfn.TEXTJOIN("+",TRUE,_xlfn._xlws.FILTER(_xlfn.TEXTSPLIT(H96,,"+"),(_xlfn.TEXTSPLIT(H96,,"+")<>"埃米工具")*(_xlfn.TEXTSPLIT(H96,,"+")<>"埃米广告通"))) -> 埃米平台 | K96: ==EDATE(C96,D96) -> 46451 | N96: 服务中 | O96: 3月6日 13.30完成培训
A97: 96 | B97: 杭州赛途沃贸易有限公司 | C97: 46086.654 | D97: 12 | E97: 46086 | F97: 武卓玉 | G97: KJ2026030462216061490 | H97: 埃米平台+埃米陪跑服务 | I97: 成长版 | J97: ==_xlfn.TEXTJOIN("+",TRUE,_xlfn._xlws.FILTER(_xlfn.TEXTSPLIT(H97,,"+"),(_xlfn.TEXTSPLIT(H97,,"+")<>"埃米工具")*(_xlfn.TEXTSPLIT(H97,,"+")<>"埃米广告通"))) -> 埃米平台+埃米陪跑服务 | K97: ==EDATE(C97,D97) -> 46451 | L97: 46087 | M97: FB,TK, INS, X, Youtube | N97: 服务中 | O97: 3月9已完成培训
A98: 97 | B98: 广州艾鲁思机械设备有限公司 | C98: 46086.677 | D98: 12 | E98: 46086 | F98: 刘帝 | G98: KJ2026030500403661248 | H98: 埃米平台 | I98: 成长版 | J98: ==_xlfn.TEXTJOIN("+",TRUE,_xlfn._xlws.FILTER(_xlfn.TEXTSPLIT(H98,,"+"),(_xlfn.TEXTSPLIT(H98,,"+")<>"埃米工具")*(_xlfn.TEXTSPLIT(H98,,"+")<>"埃米广告通"))) -> 埃米平台 | K98: ==EDATE(C98,D98) -> 46451 | N98: 服务中 | O98: 3月6号培训完毕
A99: 98 | B99: 成都智诚筛网有限公司 | C99: 46086.709 | D99: 12 | E99: 46086 | F99: 谭婷 | G99: KJ2026030542825485992 | H99: 埃米平台 | I99: 成长版 | J99: ==_xlfn.TEXTJOIN("+",TRUE,_xlfn._xlws.FILTER(_xlfn.TEXTSPLIT(H99,,"+"),(_xlfn.TEXTSPLIT(H99,,"+")<>"埃米工具")*(_xlfn.TEXTSPLIT(H99,,"+")<>"埃米广告通"))) -> 埃米平台 | K99: ==EDATE(C99,D99) -> 46451 | N99: 服务中 | O99: 3.6培训完成
A100: 99 | B100: 金华它族宠物用品有限公司 | C100: 46086.747 | D100: 12 | E100: 46087 | F100: 武卓玉 | G100: KJ2026030366141191067 | H100: 埃米平台 | I100: 成长版 | J100: ==_xlfn.TEXTJOIN("+",TRUE,_xlfn._xlws.FILTER(_xlfn.TEXTSPLIT(H100,,"+"),(_xlfn.TEXTSPLIT(H100,,"+")<>"埃米工具")*(_xlfn.TEXTSPLIT(H100,,"+")<>"埃米广告通"))) -> 埃米平台 | K100: ==EDATE(C100,D100) -> 46451 | N100: 服务中 | O100: 3月6日 11：00完成培训
...

Sheet 产品培训公开课报名
A1: 序号 | B1: 公司名称 | C1: 培训日期 | D1: 提交人 | E1: 客户参加人 | F1: 是否参加
A2: ==_xlfn.XLOOKUP(B2,总表!B:B,总表!A:A) -> 190 | B2: 宁阳县琪升工贸有限公司 | C2: 2026.3.18 | D2: 刘帝 | E2: 任铭志 | F2: 是 | H2: 培训日期 | I2: （多项）
A3: ==_xlfn.XLOOKUP(B3,总表!B:B,总表!A:A) -> 172 | B3: 东莞市万家纸业有限公司 | C3: 2026.3.18 | D3: 刘帝 | E3: Céline | F3: 是
A4: ==_xlfn.XLOOKUP(B4,总表!B:B,总表!A:A) -> 205 | B4: 济南万顺机械制造有限公司 | C4: 2026.3.18 | D4: 刘帝 | E4: 吥棄（济南万顺机械制造有限公司） | F4: 是 | H4: 提交人 | I4: 计数项：公司名称
A5: ==_xlfn.XLOOKUP(B5,总表!B:B,总表!A:A) -> 131 | B5: 成都科达亨科技有限责任公司 | C5: 2026.3.18 | D5: 谭婷 | E5: SCARLETT | F5: 是 | H5: 刘帝 | I5: 13
A6: ==_xlfn.XLOOKUP(B6,总表!B:B,总表!A:A) -> 175 | B6: 成都爱尚里里商贸有限公司 | C6: 2026.3.18 | D6: 谭婷 | E6: 藝 | F6: 是 | H6: 彭才杰 | I6: 21
A7: ==_xlfn.XLOOKUP(B7,总表!B:B,总表!A:A) -> 200 | B7: 东莞市铝美铝型材有限公司 | C7: 2026.3.18 | D7: 谭婷 | E7: 见贤思齐 | F7: 否 | H7: 谭婷 | I7: 14
A8: ==_xlfn.XLOOKUP(B8,总表!B:B,总表!A:A) -> 169 | B8: 河南良晟畜牧设备有限公司 | C8: 2026.3.18 | D8: 谭婷 | E8: 王二二 | F8: 是 | H8: 武卓玉 | I8: 5
A9: ==_xlfn.XLOOKUP(B9,总表!B:B,总表!A:A) -> 31 | B9: 武汉卓越高压测试设备有限公司 | C9: 2026.3.18 | D9: 谭婷 | E9: 卓越高压商务17786556561 | F9: 是 | H9: 张楠 | I9: 2
A10: ==_xlfn.XLOOKUP(B10,总表!B:B,总表!A:A) -> 207 | B10: 瑞欧机械配件制造（山东）有限公司 | C10: 2026.3.18 | D10: 谭婷 | E10: A万向 天马 沈氏 十字轴总代理 | F10: 是 | H10: 董德隆 | I10: 14
A11: ==_xlfn.XLOOKUP(B11,总表!B:B,总表!A:A) -> 206 | B11: 大连科瑞气体有限公司 | C11: 2026.3.18 | D11: 谭婷 | E11: 大连科瑞-管15504266126 | F11: 是 | H11: 李政 | I11: 4
A12: ==_xlfn.XLOOKUP(B12,总表!B:B,总表!A:A) -> 146 | B12: 威海诚义贸易有限公司 | C12: 2026.3.18 | D12: 谭婷 | E12: 梁建飞 | F12: 是 | H12: 金雪 | I12: 3
A13: ==_xlfn.XLOOKUP(B13,总表!B:B,总表!A:A) -> 179 | B13: 广州众旭机电科技有限公司 | C13: 2026.3.18 | D13: 谭婷 | E13: 曉·🌙 | F13: 是
A14: ==_xlfn.XLOOKUP(B14,总表!B:B,总表!A:A) -> 209 | B14: 郑州方铭高温陶瓷新材料有限公司 | C14: 2026.3.18 | D14: 谭婷 | E14: 葛梦真 Calla | F14: 是 | H14: 总计 | I14: 76
A15: ==_xlfn.XLOOKUP(B15,总表!B:B,总表!A:A) -> 73 | B15: 青岛泰康和顺海绵制品有限公司 | C15: 2026.3.18 | D15: 刘帝 | E15: 泰山之峰 | F15: 是
A16: ==_xlfn.XLOOKUP(B16,总表!B:B,总表!A:A) -> 115 | B16: 天津泰发钢铁有限公司 | C16: 2026.3.18 | D16: 张楠 | E16: 赵普、C、今天好心情、Dahila、刘 | F16: 是
A17: ==_xlfn.XLOOKUP(B17,总表!B:B,总表!A:A) -> 30 | B17: 苏州市依雯家居服饰有限公司 | C17: 2026.3.18 | D17: 张楠 | E17: Z | F17: 是 | H17: 培训日期 | I17: （多项）
A18: ==_xlfn.XLOOKUP(B18,总表!B:B,总表!A:A) -> 201 | B18: 佛山市兴蒂丰建材装饰有限公司 | C18: 2026.3.18 | D18: 谭婷 | E18: 周遇FUN、Lucy Feng | F18: 是
A19: ==_xlfn.XLOOKUP(B19,总表!B:B,总表!A:A) -> 178 | B19: 佛山瑞电新能源有限公司 | C19: 2026.3.18 | D19: 谭婷 | E19: （Mary） | F19: 是 | H19: 是否参加 | I19: 计数项：是否参加
A20: ==_xlfn.XLOOKUP(B20,总表!B:B,总表!A:A) -> 176 | B20: 大连海川密封有限公司 | C20: 2026.3.18 | D20: 谭婷 | E20: 赵晓光 | F20: 是
A21: ==_xlfn.XLOOKUP(B21,总表!B:B,总表!A:A) -> 126 | B21: 北京市晋鹏鑫磊电气有限公司 | C21: 2026.3.18 | D21: 张楠 | E21: 再生天翼 | F21: 是 | H21: 是 | I21: 166
A22: ==_xlfn.XLOOKUP(B22,总表!B:B,总表!A:A) -> 168 | B22: 佛山市松汇科技有限公司 | C22: 2026.3.18 | D22: 谭婷 | E22: LSN | F22: 是 | H22: 否 | I22: 1
A23: ==_xlfn.XLOOKUP(B23,总表!B:B,总表!A:A) -> 213 | B23: 湖北绿洲源健康科技有限公司 | C23: 2026.3.18 | D23: 谭婷 | E23: Polly孙波 | F23: 是 | H23: 总计 | I23: 167
A24: ==_xlfn.XLOOKUP(B24,总表!B:B,总表!A:A) -> 58 | B24: 成都蒽科科技有限公司 | C24: 2026.3.18 | D24: 谭婷 | E24: 愚 | F24: 是
A25: ==_xlfn.XLOOKUP(B25,总表!B:B,总表!A:A) -> 184 | B25: 湖北瑞兹威科技有限公司 | C25: 2026.3.18 | D25: 张楠 | E25: 瑞兹威 | F25: 是 | H25: 培训日期 | I25: 2026.4.15
A26: ==_xlfn.XLOOKUP(B26,总表!B:B,总表!A:A) -> 129 | B26: 上海净迈包装科技有限公司 | C26: 2026.3.18 | D26: 谭婷 | E26: 冯亦笑 | F26: 是
A27: ==_xlfn.XLOOKUP(B27,总表!B:B,总表!A:A) -> 9 | B27: 永东发（廊坊）科技有限公司 | C27: 2026.3.18 | D27: 武卓玉 | E27: 玲儿 | F27: 是 | H27: 提交人 | I27: 计数项：公司名称
A28: ==_xlfn.XLOOKUP(B28,总表!B:B,总表!A:A) -> 135 | B28: 湖北碧澜天博来建筑股份有限公司 | C28: 2026.3.18 | D28: 武卓玉 | E28: 碧澜天-舒晓玲 | F28: 是 | H28: 彭才杰 | I28: 4
A29: ==_xlfn.XLOOKUP(B29,总表!B:B,总表!A:A) -> 218 | B29: 建德市新裕塑胶材料有限公司 | C29: 2026.3.18 | D29: 武卓玉 | E29: lisa.x | F29: 是 | H29: 谭婷 | I29: 2
A30: ==_xlfn.XLOOKUP(B30,总表!B:B,总表!A:A) -> 11 | B30: 河北卓好科技有限公司 | C30: 2026.3.18 | D30: 武卓玉 | E30: Donna | F30: 是 | H30: 武卓玉 | I30: 1
A31: ==_xlfn.XLOOKUP(B31,总表!B:B,总表!A:A) -> 171 | B31: 佛山市英菲桁架器材有限公司 | C31: 2026.3.18 | D31: 武卓玉 | E31: ITSCtruss | F31: 是 | H31: 高晴 | I31: 4
A32: ==_xlfn.XLOOKUP(B32,总表!B:B,总表!A:A) -> 123 | B32: 香河货不全商贸有限公司 | C32: 2026.3.18 | D32: 武卓玉 | E32: A张艳清货不全 | F32: 是 | H32: 董德隆 | I32: 6
A33: ==_xlfn.XLOOKUP(B33,总表!B:B,总表!A:A) -> 81 | B33: 东莞市沃富五金制品有限公司 | C33: 2026.3.18 | D33: 武卓玉 | E33: A萧 | F33: 是 | H33: 李政 | I33: 4
A34: ==_xlfn.XLOOKUP(B34,总表!B:B,总表!A:A) -> 159 | B34: 青岛盛华隆贸易有限责任公司 | C34: 2026.3.18 | D34: 谭婷 | E34: 李鹏飞 | F34: 是 | H34: 金雪 | I34: 3
A35: ==_xlfn.XLOOKUP(B35,总表!B:B,总表!A:A) -> 166 | B35: 永康市精航观光车有限公司 | C35: 2026.3.18 | D35: 刘帝 | E35: 深水的鱼 | F35: 是 | H35: 总计 | I35: 24
A36: ==_xlfn.XLOOKUP(B36,总表!B:B,总表!A:A) -> 108 | B36: 深圳市金亚诺电子有限公司 | C36: 2026.3.18 | D36: 张楠 | E36: 童林、Lori | F36: 是
A37: ==_xlfn.XLOOKUP(B37,总表!B:B,总表!A:A) -> 203 | B37: 上海金箭水射流设备制造有限公司 | C37: 2026.3.18 | D37: 谭婷 | E37: Lily(金箭水刀) | F37: 是
A38: ==_xlfn.XLOOKUP(B38,总表!B:B,总表!A:A) -> 163 | B38: 浙江众兴智能科技股份有限公司 | C38: 2026.3.18 | D38: 谭婷 | E38: 众兴智能 | F38: 是
A39: ==_xlfn.XLOOKUP(B39,总表!B:B,总表!A:A) -> 230 | B39: 大连金河机械有限公司 | C39: 2026.3.18 | D39: 彭才杰 | E39: 龙门RL仰望星空 | F39: 是
A40: ==_xlfn.XLOOKUP(B40,总表!B:B,总表!A:A) -> 19 | B40: 山东鸿星工程机械有限公司 | C40: 2026.3.18 | D40: 刘帝 | E40: 鸿星双缸液压剪 韩小宁15163737589 | F40: 是
A41: ==_xlfn.XLOOKUP(B41,总表!B:B,总表!A:A) -> 93 | B41: 长沙悦翼医疗科技有限公司 | C41: 2026.3.18 | D41: 刘帝 | E41: Ö | F41: 是
A42: ==_xlfn.XLOOKUP(B42,总表!B:B,总表!A:A) -> 231 | B42: 辽宁芯创智联电子科技有限公司 | C42: 2026.3.18 | D42: 谭婷 | E42: 🌻向日葵🌻15940997127 | F42: 是
A43: ==_xlfn.XLOOKUP(B43,总表!B:B,总表!A:A) -> 233 | B43: 山东鲁建装饰材料有限公司 | C43: 2026.3.20 | D43: 彭才杰 | E43: A铝单板加工厂家 | F43: 是
A44: ==_xlfn.XLOOKUP(B44,总表!B:B,总表!A:A) -> 241 | B44: 深圳市迎利电动门有限公司 | C44: 2026.3.20 | D44: 彭才杰 | E44: Automatic doors-Ella | F44: 是
A45: ==_xlfn.XLOOKUP(B45,总表!B:B,总表!A:A) -> 187 | B45: 南阳恒诺科技有限公司 | C45: 2026.3.20 | D45: 武卓玉 | E45: Jerry | F45: 是
A46: ==_xlfn.XLOOKUP(B46,总表!B:B,总表!A:A) -> 170 | B46: 梁山顺驰机械制造有限公司 | C46: 2026.3.20 | D46: 武卓玉 | E46: 张美阳 | F46: 是
A47: ==_xlfn.XLOOKUP(B47,总表!B:B,总表!A:A) -> 246 | B47: 成都威斯特邦贸易有限公司 | C47: 2026.3.20 | D47: 彭才杰 | E47: 胡焕英 | F47: 是
... A127: ==_xlfn.XLOOKUP(B127,总表!B:B,总表!A:A) -> 368 | B127: 广东西海雨水环境技术有限公司 | C127: 2026.4.1 | D127: 高晴 | E127: 依古比古 | F127: 是
B128: 大连烽卿贸易有限公司 | C128: 2026.4.3 | D128: 高晴 | F128: 是
B129: 佛山市格勒热工设备制造 | C129: 2026.4.3 | D129: 高晴 | F129: 是
B130: 楚辰志通（湖北）汽车销售 | C130: 2026.4.3 | D130: 高晴 | F130: 是
B131: 武汉嘉润汇茗茶叶有限公司 | C131: 2026.4.1 | D131: 刘帝 | E131: C浩。 | F131: 是
B132: 河南绿源水处理科技有限公司 | C132: 2026.4.1 | D132: 刘帝 | E132: Alice | F132: 是
B133: 山东谙达国际贸易有限公司 | C133: 2026.4.1 | D133: 刘帝 | E133: 于广飞 | F133: 是
B134: 河北威创新材料有限公司 | C134: 2026.4.1 | D134: 刘帝 | E134: Andy | F134: 是
B135: 梁山铭大机械设备有限公司 | C135: 2026.4.3 | D135: 张楠 | E135: 山东路翔达车辆 | F135: 是
B136: 平湖市旭阳电子科技 | C136: 2026.4.3 | D136: 高晴 | F136: 是
B137: 苏州心之力机器人有限公司 | C137: 2026.4.3 | D137: 武卓玉 | E137: 陈通 James T. Chen | F137: 是
B138: 山东三维商贸有限公司 | C138: 2026.4.3 | D138: 武卓玉 | E138: 靳杰 | F138: 是
B139: 河北御棠源生态农业有限公司 | C139: 2026.4.3 | D139: 谭婷 | E139: 御棠源外贸部孙利新15631397937 | F139: 是
B140: 东特矿安（山东）装备有限公司 | C140: 2026.4.3 | D140: 谭婷 | E140: A极道者 | F140: 是
B141: 青岛载利电力设备有限公司 | C141: 2026.4.3 | D141: 谭婷 | E141: 悟 | F141: 是
B142: 大连东轻金属材料有限公司 | C142: 2026.4.3 | D142: 武卓玉 | E142: 孙景林-船用铝板 | F142: 是
B143: 长沙市虢工机械设备 | C143: 2026.4.3 | D143: 张楠 | E143: Lynx | F143: 是
B144: 青岛沃瑞和丰国际贸易有限公司 | C144: 2026.4.3 | D144: 彭才杰 | E144: 白家琪 Henry | F144: 是
B145: 上海钲兴服饰有限公司 | C145: 2026.4.3 | D145: 彭才杰 | E145: 王婉萍~钲兴制服 | F145: 是
B146: 威海杜氏复合材料有限公司 | C146: 2026.4.3 | D146: 彭才杰 | E146: Neil | F146: 是
B147: 中山市古镇鑫纳精源金刚石工具厂 | C147: 2026.4.3 | D147: 彭才杰 | E147: 阿伟 | F147: 是
B148: 佛山市亮轩智能科技有限公司 | C148: 2026.4.3 | D148: 刘帝 | F148: 是
B149: 武义聚利工贸有限公司 | C149: 2026.4.3 | D149: 刘帝 | F149: 是
B150: 深圳市志成达智能自动化科技有限公司 | C150: 2026.4.3 | D150: 刘帝 | F150: 是
B151: 青岛塔姆沃新材料有限公司 | C151: 2026.4.8 | D151: 彭才杰 | E151: 未逝时光 | F151: 是
B152: 成都大宏立机器股份有限公司 | C152: 2026.4.8 | D152: 董德隆 | E152: I Never Told You | F152: 是
B153: 北京视远国际贸易有限公司 | C153: 2026.4.8 | D153: 谭婷 | E153: Claire | F153: 是
B154: 山东鸿拓智联科技有限公司 | C154: 2026.4.8 | D154: 董德隆 | E154: 鸿拓智联Jerry 15063713376、鸿拓智联Justin、鸿拓智联刘峰Milo Liu | F154: 是
B155: 河南鸿发养殖设备有限公司 | C155: 2026.4.8 | D155: 董德隆 | E155: 林岫便已皓然 | F155: 是
B156: 深圳市万维热传导技术有限公司 | C156: 2026.4.8 | D156: 董德隆 | E156: 张钘堰、李谨言 | F156: 是
B157: 深圳安威尔触控科技有限公司 | C157: 2026.4.8 | D157: 高晴 | E157: JAXI | F157: 是
B158: 深圳市鑫日升机械有限公司 | C158: 2026.4.8 | D158: 谭婷 | E158: 鑫日升自动化设备～黄仕武 | F158: 是
B159: 南通丁小墩贸易有限公司 | C159: 2026.4.8 | D159: 谭婷 | E159: 烟火起 | F159: 是
B160: 嘉兴市游漫箱包科技有限公司 | C160: 2026.4.8 | D160: 彭才杰 | E160: 吴俊 | F160: 是
B161: 缙云县刀浪车业有限公司 | C161: 2026.4.8 | D161: 彭才杰 | E161: 🌴 | F161: 是
B162: 东莞市广凡自动化科技有限公司 | C162: 2026.4.8 | D162: 彭才杰 | E162: Laura --- Polishing supplier | F162: 是
... B168: 兰溪市沁芳源日化有限公司 | C168: 2026.4.8 | D168: 高晴 | E168: 美丽华华捷水墨-叶柳18057918797 | F168: 是
B169: 成都武侯素美医疗美容门诊部 | C169: 2026.4.15 | D169: 高晴 | E169: 溢价男孩K
B170: 威海凯怡进出口有限公司 | C170: 2026.4.15 | D170: 董德隆 | E170: 刘莎
B171: 青岛万途思锐科技有限公司 | C171: 2026.4.15 | D171: 董德隆 | E171: Jackie
B172: 济南艺海激光科技 | C172: 2026.4.15 | D172: 高晴 | E172: @王丹外贸yandex社媒谷歌
B173: 上海易壳照明股份有限公司 | C173: 2026.4.15 | D173: 彭才杰 | E173: 兑兑
B174: 济南格拉斯进出口贸易有限公司 | C174: 2026.4.15 | D174: 彭才杰 | E174: A山东鲁玻中空玻璃设备荣明建，China-Лиза
B175: 住电装贸易（上海）有限公司 | C175: 2026.4.15 | D175: 武卓玉 | E175: 寂渊
B176: 山东大信钢铁有限公司 | C176: 2026.4.15 | D176: 董德隆 | E176: 山东大信钢铁刘
B177: 廊坊纽图家具有限公司 | C177: 2026.4.15 | D177: 董德隆 | E177: Ivy
B178: 青岛高宠宠物食品有限公司 | C178: 2026.4.15 | D178: 董德隆 | E178: Qingdao Yukang Pet Food Co,Ltd
B179: 湖北华耀达电气有限公司 | C179: 2026.4.15 | D179: 彭才杰 | E179: _祝喻星
B180: 马小平（SF：430524198804028231） | C180: 2026.4.15 | D180: 彭才杰 | E180: 正義砼商¦¦马小平
... B192: 成都世纪阳光密封件有限公司 | C192: 2026.4.15 | D192: 董德隆 | E192: 阳光

Sheet 规则备忘
A1: 运营专员进群规则 | E1: 分配人 | F1: 区域 | G1: 对应服务号
A2: 运营团队 | B2: 服务号 | C2: 步骤 | E2: 李姿霏 | F2: 北京 | G2: 社媒运营客服
A3: 北京 | B3: 社媒运营客服 | C3: 先拉服务号进群，服务号拉具体的人。拉服务号的时候就需要同步聊天记录
A4: 长沙 | B4: 社媒运营中心
A5: 洛阳 | B5: 直接拉对应的专员
A7: 只购买服务不够买工具，一律不支持分配客成
A10: 购买了代运营-广告通的客户，客户如有广告通相关咨询，客成统一先联系赵娟。
A15: 客户企业名称变更流程
A16: 商务/客户告知企业名称变更---提交企查查截图或更名后公司营业+工商盖章更名函件 -- -客成可支持信息收集表及推广展示的是变更后的公司名称---将【分配总表】名称相应做变更并评论加上以前的名称 -- 将群名同步变更---同步交付专员
A21: 签A推B流程
A22: 一、总则 原则上，已购买埃米陪跑及代运营产品的客户，不支持签A推B操作。 仅在A、B两家公司存在直接关联关系，并提供完整补充资料的前提下，可提交特殊审批申请，经审批通过后方可执行。 二、关联关系认定标准 申请签A推B的客户，须满足以下任意一项关联关系条件： 1、分总公司关系：B公司为A公司依法设立的分支机构（如“中企跨境***分公司”）； 2、分子公司关系：A、B公司同属一个集团，为该集团下属的分公司或子公司； 3、子母公司关系：A、B公司之间为100%全资控股关系； 4、控股公司关系：一方直接或间接持有另一方股份达到25%以上（含25%）且为大股东（根据税法规定）； 5、同一法定代表人：A、B公司法定代表人为同一自然人。 三、需提交的资料 1、A、B双方营业执照（电子版）； 2、A、B的关联关系证明（企信网截图即可） 3、《授权推广协议》（客户签署并加盖双方公章），协议原件须按照法务的要求寄到客成部门的地址存档。 四、审批及操作流程 1、商务反馈客成评估 商务人员将客户需求反馈至客户成功经理，并说明原因，客成评估是否支持。 2、商务提供上述2项资料： 3、资料归档 协议签署完毕后，商务人员将协议原件邮寄到客成部门，由客成部门统一存档。 4、服务开启 客成经理确认审批邮件及盖章协议均已归档后，方可开启对应推广服务。 五、风险揭示 1、《授权推广协议》原件管理 协议签署后，原件须邮寄至我司法务指定地址统一存档。要求原件存档的原因为： 法律证据效力保障：在发生争议或合规审计时，加盖双方鲜章的原件是证明授权关系真实性的唯一直接证据，复印件或扫描件在法律效力上存在瑕疵。 2、关联关系真实性核验 要求客户提供双方营业执照及关联关系证明，确保需求来源于客户。 3、客户真实意愿确认 协议签署须基于客户真实业务需求，严禁销售人员或客成人员引导、暗示或代替客户准备申请材料。所有盖章文件必须由客户自行完成用印流程，我司人员不得经手客户公章或代为盖章，以规避表见代理及合同无效风险。 六、发票开具提示 1、若签约主体与付款主体一致，可向付款主体开具增值税专用发票； 2、若签约主体与付款主体不一致，仅可向付款主体开具增值税普通发票。 附：纸质文件邮寄地址： 北京市大兴区亦庄经济技术开发区地盛西路1号 B座 3层，马旭蕊：15810128132
A28: 《外媒账号授权声明》的签署规则
A29: 1、凡是客户使用原有账号，不是我们帮助注册的账号都要签署(领英平台除外)。
A30: 2、《外媒账号授权声明》要在登录客户账号前，客户必须签订完成。
A31: 3、客户成功，负责确认声明中的主体是中企动力还是中企跨境，社媒运营专员负责发送给客户跟进客户签署
A32: 4、客户签订<<外媒账号授权协议>>发送邮件至邮箱:sns@300.cn。
A33: 5、客户签订完毕后，交付同步负责客成。
A34: ‼️声明中主体的定义：哪个主体售卖的 声明中的主体就是谁，例如：中企跨境售卖的苏州市恒协，主体就是 中企跨境 | D34: 中企动力主体名称 | E34: 中企动力科技股份有限公司
D35: 跨境主体名称 | E35: 中企动力跨境（北京）网络科技有限公司

Sheet 埃米退转款列表
B1: 退转款渠道 | C1: 公司名称 | D1: 订单号 | E1: 退转款类型 | F1: 退转款原因 | G1: 退转款商品
A2: 46087.607 | B2: 企微 | C2: 东莞市沃富五金制品有限公司 | D2: KJ2026030367354133027 | E2: 退款 | F2: 跟客户沟通的五个社媒账号陪跑，因为当时比较着 急录单客户要扫码，以为社媒陪跑还是跟之前一 样，是7选5个账号，所以就直接选了一个多增加了 -个后，发现需要生产的时候只有两个社媒账号， 所以需要重新录单补录，把沟通的账号都重新添加 录单， | G2: 埃米AIMI+埃米AIMI陪跑服务 | H2: 已重新录单，继续服务中
A3: 46093.725 | B3: 企微 | C3: 湖南泵多多科技有限公司 | D3: KJ2026031184036498703 | E3: 转款 | F3: 客户诉求是需要我们社媒进行注册和陪跑两个月，但是我们这边下单必须要购买埃米工具才行给客户注册，通过和客户沟通由商务自行给客户注册社媒账号，把此单埃米陪跑改成埃米工具 | G3: 埃米AIMI陪跑服务
A4: 46100.687 | B4: 业务平台 | C4: 济南鑫沃通达贸易有限公司 | D4: KJ2026030391091106184 | E4: 退款 | F4: 济南鑫沃通达贸易有限公司购买的埃米产品，在使用过程中不满意，客户投诉严重，现申请济南鑫沃通达贸易有限公司埃米产品5988元全额退款 | G4: 埃米AIMI
A5: 46099.727 | B5: 企微 | C5: 詹晓东（SF：429001197806307437） | D5: KJ2026031627282999564 | E5: 退款 | F5: 客户的想法是个人签单，但是社媒推广要公司名义，我司无法实现签A推B，商务未告知客户导致社媒陪跑服务无法生产，需要退单重新录单以公司的名义签单 | G5: 埃米AIMI+埃米AIMI陪跑服务
A6: 46113.444 | B6: 业务平台 | C6: 大连东宇精密机械有限公司 | D6: KJ2026030513382720076 | E6: 退款 | F6: 客户不想要了，要求终止合作 | G6: 埃米AIMI
A7: 46115.914 | B7: 业务平台 | C7: 河间市邵普玻璃制品有限公司 | D7: KJ2026032505594789033 | E7: 退款 | F7: 因客户想要使用app端海外社媒商务引导客户使用VPN导致客户不满，要求退款。且该客户已通过12345、黑猫投诉、拨打400客服电话、北京工商等能够投诉的渠道都进行了投诉，并且已经在法院正式立案。 | G7: 埃米AIMI
A8: 46121.688 | B8: 业务平台 | C8: 辽宁芯创智联电子科技有限公司 | D8: KJ2026031052052837400 | E8: 退款 | F8: 客户提出退款需求，绑定社媒封号，上传的视频不能直接发布还需要二次编辑。 | G8: 埃米AIMI

Sheet 服务进度表-交付实施
A1: 序号 | B1: 客成序号 | C1: 公司名称 （标红为未进入伙伴工作台的服务单） | D1: 产品类型 | E1: 信息完成收集时间 | F1: 平台类型 | G1: 签单时间 | H1: 客成 | I1: 备注 | J1: 分派专员时间 （赵娟填写） | K1: 运营团队 （运营团队填写） | L1: 运营专员 （运营团队填写） | M1: 服务开始时间 （全平台注册并授权为开始，运营专员填写） | N1: 状态 （运营专员填写） | O1: 超时预警 | P1: 上线是否超时 | Q1: 备注 | R1: 交付预警
A2: 1 | B2: ==_xlfn.XLOOKUP(C2,总表!B:B,总表!A:A,无,0) -> 1 | C2: 邯郸市扬发贸易有限公司 | D2: ==_xlfn.XLOOKUP(C2,总表!B:B,总表!J:J,无0) -> 埃米平台+埃米陪跑服务 | E2: ==_xlfn.XLOOKUP(C2,总表!B:B,总表!L:L,无,0) -> 46080 | F2: ==_xlfn.XLOOKUP(C2,总表!B:B,总表!M:M,无,0) -> TK, X, INS, Youtube, FB | G2: ==_xlfn.XLOOKUP(C2,总表!B:B,总表!C:C,无,0) -> 46077.472 | H2: ==_xlfn.XLOOKUP(C2,总表!B:B,总表!F:F,无,0) -> 张楠 | I2: ==_xlfn.XLOOKUP(C2,总表!B:B,总表!P:P,无,0) -> 0 | J2: 46080 | K2: 长沙 | L2: 曾欢 | M2: 46090 | N2: 服务中 | O2: 未超时 | P2: ==IF(K2<>"",IF(ISBLANK(M2),IF(TODAY()-J2>14,"超时","未超时"),IF(M2-J2>14,"超时","未超时")),"") -> 未超时
A3: 2 | B3: ==_xlfn.XLOOKUP(C3,总表!B:B,总表!A:A,无,0) -> 11 | C3: 河北卓好科技有限公司 | D3: ==_xlfn.XLOOKUP(C3,总表!B:B,总表!J:J,无0) -> 埃米平台+埃米代运营服务 | E3: ==_xlfn.XLOOKUP(C3,总表!B:B,总表!L:L,无,0) -> 46080 | F3: ==_xlfn.XLOOKUP(C3,总表!B:B,总表!M:M,无,0) -> TK, INS, Youtube, FB, X, Linkedin | G3: ==_xlfn.XLOOKUP(C3,总表!B:B,总表!C:C,无,0) -> 46078.729 | H3: ==_xlfn.XLOOKUP(C3,总表!B:B,总表!F:F,无,0) -> 武卓玉 | I3: ==_xlfn.XLOOKUP(C3,总表!B:B,总表!P:P,无,0) -> 0 | J3: 46080 | K3: 洛阳 | L3: 张艺 | M3: 46090 | N3: 服务中 | P3: ==IF(K3<>"",IF(ISBLANK(M3),IF(TODAY()-J3>14,"超时","未超时"),IF(M3-J3>14,"超时","未超时")),"") -> 未超时
A4: 3 | B4: ==_xlfn.XLOOKUP(C4,总表!B:B,总表!A:A,无,0) -> 13 | C4: 徐州沃卡重工机械有限公司 | D4: ==_xlfn.XLOOKUP(C4,总表!B:B,总表!J:J,无0) -> 埃米平台+埃米陪跑服务 | E4: ==_xlfn.XLOOKUP(C4,总表!B:B,总表!L:L,无,0) -> 46079 | F4: ==_xlfn.XLOOKUP(C4,总表!B:B,总表!M:M,无,0) -> TK, Youtube, FB | G4: ==_xlfn.XLOOKUP(C4,总表!B:B,总表!C:C,无,0) -> 46078.723 | H4: ==_xlfn.XLOOKUP(C4,总表!B:B,总表!F:F,无,0) -> 刘帝 | I4: ==_xlfn.XLOOKUP(C4,总表!B:B,总表!P:P,无,0) -> 0 | J4: 46080 | K4: 北京 | L4: 李睿琦 | M4: 46084 | N4: 服务中 | P4: ==IF(K4<>"",IF(ISBLANK(M4),IF(TODAY()-J4>14,"超时","未超时"),IF(M4-J4>14,"超时","未超时")),"") -> 未超时
A5: 4 | B5: ==_xlfn.XLOOKUP(C5,总表!B:B,总表!A:A,无,0) -> 16 | C5: 临清市星扬机械设备有限公司 | D5: ==_xlfn.XLOOKUP(C5,总表!B:B,总表!J:J,无0) -> 埃米平台+埃米陪跑服务 | E5: ==_xlfn.XLOOKUP(C5,总表!B:B,总表!L:L,无,0) -> 46080 | F5: ==_xlfn.XLOOKUP(C5,总表!B:B,总表!M:M,无,0) -> TK, Youtube, FB | G5: ==_xlfn.XLOOKUP(C5,总表!B:B,总表!C:C,无,0) -> 46079.44 | H5: ==_xlfn.XLOOKUP(C5,总表!B:B,总表!F:F,无,0) -> 武卓玉 | I5: ==_xlfn.XLOOKUP(C5,总表!B:B,总表!P:P,无,0) -> 0 | J5: 46080 | K5: 北京 | L5: 李睿琦 | M5: 46086 | N5: 服务中 | P5: ==IF(K5<>"",IF(ISBLANK(M5),IF(TODAY()-J5>14,"超时","未超时"),IF(M5-J5>14,"超时","未超时")),"") -> 未超时
A6: 5 | B6: ==_xlfn.XLOOKUP(C6,总表!B:B,总表!A:A,无,0) -> 19 | C6: 山东鸿星工程机械有限公司 | D6: ==_xlfn.XLOOKUP(C6,总表!B:B,总表!J:J,无0) -> 埃米平台+埃米陪跑服务 | E6: ==_xlfn.XLOOKUP(C6,总表!B:B,总表!L:L,无,0) -> 46080 | F6: ==_xlfn.XLOOKUP(C6,总表!B:B,总表!M:M,无,0) -> TK, X, INS, Youtube, FB | G6: ==_xlfn.XLOOKUP(C6,总表!B:B,总表!C:C,无,0) -> 46079.642 | H6: ==_xlfn.XLOOKUP(C6,总表!B:B,总表!F:F,无,0) -> 刘帝 | I6: ==_xlfn.XLOOKUP(C6,总表!B:B,总表!P:P,无,0) -> 0 | J6: 46080 | K6: 长沙 | L6: 曾欢 | M6: 46091 | N6: 服务中 | P6: ==IF(K6<>"",IF(ISBLANK(M6),IF(TODAY()-J6>14,"超时","未超时"),IF(M6-J6>14,"超时","未超时")),"") -> 未超时
A7: 6 | B7: ==_xlfn.XLOOKUP(C7,总表!B:B,总表!A:A,无,0) -> 24 | C7: 梁山铭大机械设备有限公司 | D7: ==_xlfn.XLOOKUP(C7,总表!B:B,总表!J:J,无0) -> 埃米平台+埃米陪跑服务 | E7: ==_xlfn.XLOOKUP(C7,总表!B:B,总表!L:L,无,0) -> 46080 | F7: ==_xlfn.XLOOKUP(C7,总表!B:B,总表!M:M,无,0) -> TK, X, INS, Youtube, FB | G7: ==_xlfn.XLOOKUP(C7,总表!B:B,总表!C:C,无,0) -> 46079.779 | H7: ==_xlfn.XLOOKUP(C7,总表!B:B,总表!F:F,无,0) -> 张楠 | J7: 46083 | K7: 北京 | L7: 李睿琦 | M7: 46085 | N7: 服务中 | P7: ==IF(K7<>"",IF(ISBLANK(M7),IF(TODAY()-J7>14,"超时","未超时"),IF(M7-J7>14,"超时","未超时")),"") -> 未超时
A8: 7 | B8: ==_xlfn.XLOOKUP(C8,总表!B:B,总表!A:A,无,0) -> 32 | C8: 威海基尔新能源装备有限公司 | D8: ==_xlfn.XLOOKUP(C8,总表!B:B,总表!J:J,无0) -> 埃米平台+埃米代运营服务 | E8: ==_xlfn.XLOOKUP(C8,总表!B:B,总表!L:L,无,0) -> 46083 | F8: ==_xlfn.XLOOKUP(C8,总表!B:B,总表!M:M,无,0) -> TK, FB, X, INS, Youtube | G8: ==_xlfn.XLOOKUP(C8,总表!B:B,总表!C:C,无,0) -> 46080.776 | H8: ==_xlfn.XLOOKUP(C8,总表!B:B,总表!F:F,无,0) -> 张楠 | I8: ==_xlfn.XLOOKUP(C8,总表!B:B,总表!P:P,无,0) -> 0 | J8: 46084 | K8: 北京 | L8: 韩明伟 | M8: 46091 | N8: 服务中 | P8: ==IF(K8<>"",IF(ISBLANK(M8),IF(TODAY()-J8>14,"超时","未超时"),IF(M8-J8>14,"超时","未超时")),"") -> 未超时
A9: 8 | B9: ==_xlfn.XLOOKUP(C9,总表!B:B,总表!A:A,无,0) -> 51 | C9: 平原百斯特机械工具有限公司 | D9: ==_xlfn.XLOOKUP(C9,总表!B:B,总表!J:J,无0) -> 埃米平台+埃米陪跑服务 | E9: ==_xlfn.XLOOKUP(C9,总表!B:B,总表!L:L,无,0) -> 46083 | F9: ==_xlfn.XLOOKUP(C9,总表!B:B,总表!M:M,无,0) -> TK, INS, X, Youtube, FB | G9: ==_xlfn.XLOOKUP(C9,总表!B:B,总表!C:C,无,0) -> 46081.527 | H9: ==_xlfn.XLOOKUP(C9,总表!B:B,总表!F:F,无,0) -> 张楠 | I9: ==_xlfn.XLOOKUP(C9,总表!B:B,总表!P:P,无,0) -> 0 | J9: 46084 | K9: 北京 | L9: 李睿琦 | M9: 46087 | N9: 服务中 | P9: ==IF(K9<>"",IF(ISBLANK(M9),IF(TODAY()-J9>14,"超时","未超时"),IF(M9-J9>14,"超时","未超时")),"") -> 未超时
A10: 9 | B10: ==_xlfn.XLOOKUP(C10,总表!B:B,总表!A:A,无,0) -> 9 | C10: 永东发（廊坊）科技有限公司 | D10: ==_xlfn.XLOOKUP(C10,总表!B:B,总表!J:J,无0) -> 埃米平台+埃米陪跑服务 | E10: ==_xlfn.XLOOKUP(C10,总表!B:B,总表!L:L,无,0) -> 46091 | F10: ==_xlfn.XLOOKUP(C10,总表!B:B,总表!M:M,无,0) -> FB,TK, INS | G10: ==_xlfn.XLOOKUP(C10,总表!B:B,总表!C:C,无,0) -> 46078.879 | H10: ==_xlfn.XLOOKUP(C10,总表!B:B,总表!F:F,无,0) -> 武卓玉 | I10: ==_xlfn.XLOOKUP(C10,总表!B:B,总表!P:P,无,0) -> 0 | J10: 46091 | K10: 北京 | L10: 王芷娇 | M10: 46101 | N10: 服务中 | P10: ==IF(K10<>"",IF(ISBLANK(M10),IF(TODAY()-J10>14,"超时","未超时"),IF(M10-J10>14,"超时","未超时")),"") -> 未超时
A11: 10 | B11: ==_xlfn.XLOOKUP(C11,总表!B:B,总表!A:A,无,0) -> 12 | C11: 聊城市金硕机电设备有限公司 | D11: ==_xlfn.XLOOKUP(C11,总表!B:B,总表!J:J,无0) -> 埃米平台+埃米陪跑服务 | E11: ==_xlfn.XLOOKUP(C11,总表!B:B,总表!L:L,无,0) -> 46097 | F11: ==_xlfn.XLOOKUP(C11,总表!B:B,总表!M:M,无,0) -> TK, X, INS, Youtube, FB | G11: ==_xlfn.XLOOKUP(C11,总表!B:B,总表!C:C,无,0) -> 46078.813 | H11: ==_xlfn.XLOOKUP(C11,总表!B:B,总表!F:F,无,0) -> 刘帝 | I11: ==_xlfn.XLOOKUP(C11,总表!B:B,总表!P:P,无,0) -> 0 | J11: 46098 | K11: 北京 | L11: 李睿琦 | M11: 46112 | N11: 服务中 | P11: ==IF(K11<>"",IF(ISBLANK(M11),IF(TODAY()-J11>14,"超时","未超时"),IF(M11-J11>14,"超时","未超时")),"") -> 未超时
A12: 11 | B12: ==_xlfn.XLOOKUP(C12,总表!B:B,总表!A:A,无,0) -> 17 | C12: 山东忠阳化工有限公司 | D12: ==_xlfn.XLOOKUP(C12,总表!B:B,总表!J:J,无0) -> 埃米平台+埃米陪跑服务 | E12: ==_xlfn.XLOOKUP(C12,总表!B:B,总表!L:L,无,0) -> 46105 | F12: ==_xlfn.XLOOKUP(C12,总表!B:B,总表!M:M,无,0) -> TK, X, INS, Youtube, FB | G12: ==_xlfn.XLOOKUP(C12,总表!B:B,总表!C:C,无,0) -> 46079.481 | H12: ==_xlfn.XLOOKUP(C12,总表!B:B,总表!F:F,无,0) -> 刘帝 | I12: 3月24日上午11点 | J12: 46105 | K12: 北京 | L12: 王芷娇 | M12: 46114 | N12: 服务中 | P12: ==IF(K12<>"",IF(ISBLANK(M12),IF(TODAY()-J12>14,"超时","未超时"),IF(M12-J12>14,"超时","未超时")),"") -> 未超时
A13: 12 | B13: ==_xlfn.XLOOKUP(C13,总表!B:B,总表!A:A,无,0) -> 25 | C13: 焜傲机器人（成都）有限公司 | D13: ==_xlfn.XLOOKUP(C13,总表!B:B,总表!J:J,无0) -> 埃米平台+埃米陪跑服务 | E13: ==_xlfn.XLOOKUP(C13,总表!B:B,总表!L:L,无,0) -> 46085 | F13: ==_xlfn.XLOOKUP(C13,总表!B:B,总表!M:M,无,0) -> TK, X, INS, Youtube, FB | G13: ==_xlfn.XLOOKUP(C13,总表!B:B,总表!C:C,无,0) -> 46079.817 | H13: ==_xlfn.XLOOKUP(C13,总表!B:B,总表!F:F,无,0) -> 张楠 | I13: ==_xlfn.XLOOKUP(C13,总表!B:B,总表!P:P,无,0) -> 0 | J13: 46085 | K13: 北京 | L13: 李睿琦 | M13: 46094 | N13: 服务中 | P13: ==IF(K13<>"",IF(ISBLANK(M13),IF(TODAY()-J13>14,"超时","未超时"),IF(M13-J13>14,"超时","未超时")),"") -> 未超时
A14: 13 | B14: ==_xlfn.XLOOKUP(C14,总表!B:B,总表!A:A,无,0) -> 31 | C14: 武汉卓越高压测试设备有限公司 | D14: ==_xlfn.XLOOKUP(C14,总表!B:B,总表!J:J,无0) -> 埃米平台+埃米陪跑服务 | E14: ==_xlfn.XLOOKUP(C14,总表!B:B,总表!L:L,无,0) -> 46084 | F14: ==_xlfn.XLOOKUP(C14,总表!B:B,总表!M:M,无,0) -> TK, FB | G14: ==_xlfn.XLOOKUP(C14,总表!B:B,总表!C:C,无,0) -> 46080.608 | H14: ==_xlfn.XLOOKUP(C14,总表!B:B,总表!F:F,无,0) -> 谭婷 | I14: ==_xlfn.XLOOKUP(C14,总表!B:B,总表!P:P,无,0) -> 0 | J14: 46084 | K14: 北京 | L14: 李睿琦 | M14: 46090 | N14: 服务中 | P14: ==IF(K14<>"",IF(ISBLANK(M14),IF(TODAY()-J14>14,"超时","未超时"),IF(M14-J14>14,"超时","未超时")),"") -> 未超时 | S14: fb被封
A15: 14 | B15: ==_xlfn.XLOOKUP(C15,总表!B:B,总表!A:A,无,0) -> 36 | C15: 合肥燊智工程机械有限公司 | D15: ==_xlfn.XLOOKUP(C15,总表!B:B,总表!J:J,无0) -> 埃米平台+埃米代运营服务 | E15: ==_xlfn.XLOOKUP(C15,总表!B:B,总表!L:L,无,0) -> 46085 | F15: ==_xlfn.XLOOKUP(C15,总表!B:B,总表!M:M,无,0) -> TK, X, INS, FB | G15: ==_xlfn.XLOOKUP(C15,总表!B:B,总表!C:C,无,0) -> 46080.749 | H15: ==_xlfn.XLOOKUP(C15,总表!B:B,总表!F:F,无,0) -> 刘帝 | I15: ==_xlfn.XLOOKUP(C15,总表!B:B,总表!P:P,无,0) -> 0 | J15: 46085 | K15: 北京 | L15: 周月静 | M15: 46093 | N15: 服务中 | P15: ==IF(K15<>"",IF(ISBLANK(M15),IF(TODAY()-J15>14,"超时","未超时"),IF(M15-J15>14,"超时","未超时")),"") -> 未超时 | Q15: 签单公司名称：合肥燊智商贸有限公司
A16: 15 | B16: ==_xlfn.XLOOKUP(C16,总表!B:B,总表!A:A,无,0) -> 39 | C16: 大连泰维精密模具股份有限公司 | D16: ==_xlfn.XLOOKUP(C16,总表!B:B,总表!J:J,无0) -> 埃米平台+埃米陪跑服务 | E16: ==_xlfn.XLOOKUP(C16,总表!B:B,总表!L:L,无,0) -> 46084 | F16: ==_xlfn.XLOOKUP(C16,总表!B:B,总表!M:M,无,0) -> TK, X, INS, Linkedin, FB | G16: ==_xlfn.XLOOKUP(C16,总表!B:B,总表!C:C,无,0) -> 46081.427 | H16: ==_xlfn.XLOOKUP(C16,总表!B:B,总表!F:F,无,0) -> 张楠 | I16: ==_xlfn.XLOOKUP(C16,总表!B:B,总表!P:P,无,0) -> 0 | J16: 46084 | K16: 北京 | L16: 李睿琦 | M16: 46094 | N16: 服务中 | P16: ==IF(K16<>"",IF(ISBLANK(M16),IF(TODAY()-J16>14,"超时","未超时"),IF(M16-J16>14,"超时","未超时")),"") -> 未超时
A17: 16 | B17: ==_xlfn.XLOOKUP(C17,总表!B:B,总表!A:A,无,0) -> 42 | C17: 海南智械云联工贸有限公司 | D17: ==_xlfn.XLOOKUP(C17,总表!B:B,总表!J:J,无0) -> 埃米平台+埃米陪跑服务 | E17: ==_xlfn.XLOOKUP(C17,总表!B:B,总表!L:L,无,0) -> 46083 | F17: ==_xlfn.XLOOKUP(C17,总表!B:B,总表!M:M,无,0) -> TK, X, INS | G17: ==_xlfn.XLOOKUP(C17,总表!B:B,总表!C:C,无,0) -> 46080.724 | H17: ==_xlfn.XLOOKUP(C17,总表!B:B,总表!F:F,无,0) -> 谭婷 | I17: ==_xlfn.XLOOKUP(C17,总表!B:B,总表!P:P,无,0) -> 0 | J17: 46084 | K17: 北京 | L17: 宋佳美 | M17: 46086 | N17: 服务中 | P17: ==IF(K17<>"",IF(ISBLANK(M17),IF(TODAY()-J17>14,"超时","未超时"),IF(M17-J17>14,"超时","未超时")),"") -> 未超时
A18: 17 | B18: ==_xlfn.XLOOKUP(C18,总表!B:B,总表!A:A,无,0) -> 43 | C18: 河北生茂包装材料有限公司 | D18: ==_xlfn.XLOOKUP(C18,总表!B:B,总表!J:J,无0) -> 埃米平台+埃米陪跑服务 | E18: ==_xlfn.XLOOKUP(C18,总表!B:B,总表!L:L,无,0) -> 46106 | F18: ==_xlfn.XLOOKUP(C18,总表!B:B,总表!M:M,无,0) -> INS, FB, Linkedin,TK, VK | G18: ==_xlfn.XLOOKUP(C18,总表!B:B,总表!C:C,无,0) -> 46080.677 | H18: ==_xlfn.XLOOKUP(C18,总表!B:B,总表!F:F,无,0) -> 刘帝 | I18: 3月25日上午 | J18: 46107 | K18: 北京 | L18: 王芷娇 | M18: 46120 | N18: 服务中 | P18: ==IF(K18<>"",IF(ISBLANK(M18),IF(TODAY()-J18>14,"超时","未超时"),IF(M18-J18>14,"超时","未超时")),"") -> 未超时
A19: 18 | B19: ==_xlfn.XLOOKUP(C19,总表!B:B,总表!A:A,无,0) -> 55 | C19: 威海倚春服装有限公司 | D19: ==_xlfn.XLOOKUP(C19,总表!B:B,总表!J:J,无0) -> 埃米平台+埃米陪跑服务 | E19: ==_xlfn.XLOOKUP(C19,总表!B:B,总表!L:L,无,0) -> 46093 | F19: ==_xlfn.XLOOKUP(C19,总表!B:B,总表!M:M,无,0) -> TK, FB, X, Youtube, INS | G19: ==_xlfn.XLOOKUP(C19,总表!B:B,总表!C:C,无,0) -> 46081.663 | H19: ==_xlfn.XLOOKUP(C19,总表!B:B,总表!F:F,无,0) -> 武卓玉 | I19: ==_xlfn.XLOOKUP(C19,总表!B:B,总表!P:P,无,0) -> 0 | J19: 46093 | K19: 北京 | L19: 王芷娇 | M19: 46099 | N19: 服务中 | P19: ==IF(K19<>"",IF(ISBLANK(M19),IF(TODAY()-J19>14,"超时","未超时"),IF(M19-J19>14,"超时","未超时")),"") -> 未超时
A20: 19 | B20: ==_xlfn.XLOOKUP(C20,总表!B:B,总表!A:A,无,0) -> 61 | C20: 苏州市恒协机械有限公司 | D20: ==_xlfn.XLOOKUP(C20,总表!B:B,总表!J:J,无0) -> 埃米平台+埃米代运营服务 | E20: ==_xlfn.XLOOKUP(C20,总表!B:B,总表!L:L,无,0) -> 46083 | F20: ==_xlfn.XLOOKUP(C20,总表!B:B,总表!M:M,无,0) -> FB,TK, Linkedin, VK | G20: ==_xlfn.XLOOKUP(C20,总表!B:B,总表!C:C,无,0) -> 46081.864 | H20: ==_xlfn.XLOOKUP(C20,总表!B:B,总表!F:F,无,0) -> 武卓玉 | I20: ==_xlfn.XLOOKUP(C20,总表!B:B,总表!P:P,无,0) -> 0 | J20: 46084 | K20: 北京 | L20: 崔芳魁 | M20: 46091 | N20: 服务中 | P20: ==IF(K20<>"",IF(ISBLANK(M20),IF(TODAY()-J20>14,"超时","未超时"),IF(M20-J20>14,"超时","未超时")),"") -> 未超时
A21: 20 | B21: ==_xlfn.XLOOKUP(C21,总表!B:B,总表!A:A,无,0) -> 62 | C21: 北京星光陆通视音频广播技术有限公司 | D21: ==_xlfn.XLOOKUP(C21,总表!B:B,总表!J:J,无0) -> 埃米平台+埃米陪跑服务 | E21: ==_xlfn.XLOOKUP(C21,总表!B:B,总表!L:L,无,0) -> 46087 | F21: ==_xlfn.XLOOKUP(C21,总表!B:B,总表!M:M,无,0) -> TK, FB, X, INS, Youtube | G21: ==_xlfn.XLOOKUP(C21,总表!B:B,总表!C:C,无,0) -> 46081.773 | H21: ==_xlfn.XLOOKUP(C21,总表!B:B,总表!F:F,无,0) -> 刘帝 | I21: 老社媒，裴雪珂服务中 | J21: 46087 | K21: 北京 | L21: 裴雪珂 | M21: 46087 | N21: 服务中 | P21: ==IF(K21<>"",IF(ISBLANK(M21),IF(TODAY()-J21>14,"超时","未超时"),IF(M21-J21>14,"超时","未超时")),"") -> 未超时
A22: 21 | B22: ==_xlfn.XLOOKUP(C22,总表!B:B,总表!A:A,无,0) -> 63 | C22: 上海克础机械（集团）有限公司 | D22: ==_xlfn.XLOOKUP(C22,总表!B:B,总表!J:J,无0) -> 埃米平台+埃米陪跑服务 | E22: ==_xlfn.XLOOKUP(C22,总表!B:B,总表!L:L,无,0) -> 0 | F22: ==_xlfn.XLOOKUP(C22,总表!B:B,总表!M:M,无,0) -> 0 | G22: ==_xlfn.XLOOKUP(C22,总表!B:B,总表!C:C,无,0) -> 46081.79 | H22: ==_xlfn.XLOOKUP(C22,总表!B:B,总表!F:F,无,0) -> 张楠 | I22: 客户内部人员调整，需要等新的市场经理入职。 | P22: ==IF(K22<>"",IF(ISBLANK(M22),IF(TODAY()-J22>14,"超时","未超时"),IF(M22-J22>14,"超时","未超时")),"")
A23: 22 | B23: ==_xlfn.XLOOKUP(C23,总表!B:B,总表!A:A,无,0) -> 67 | C23: 湖北宏宇专用汽车有限公司 | D23: ==_xlfn.XLOOKUP(C23,总表!B:B,总表!J:J,无0) -> 埃米平台+埃米陪跑服务 | E23: ==_xlfn.XLOOKUP(C23,总表!B:B,总表!L:L,无,0) -> 46086 | F23: ==_xlfn.XLOOKUP(C23,总表!B:B,总表!M:M,无,0) -> X, INS, Youtube, FB,TK | G23: ==_xlfn.XLOOKUP(C23,总表!B:B,总表!C:C,无,0) -> 46083.645 | H23: ==_xlfn.XLOOKUP(C23,总表!B:B,总表!F:F,无,0) -> 武卓玉 | I23: ==_xlfn.XLOOKUP(C23,总表!B:B,总表!P:P,无,0) -> 0 | J23: 46086 | K23: 洛阳 | L23: 朱冰蕊 | M23: 46100 | N23: 服务中 | P23: ==IF(K23<>"",IF(ISBLANK(M23),IF(TODAY()-J23>14,"超时","未超时"),IF(M23-J23>14,"超时","未超时")),"") -> 未超时
A24: 23 | B24: ==_xlfn.XLOOKUP(C24,总表!B:B,总表!A:A,无,0) -> 68 | C24: 苏州市圣马丁服装有限公司 | D24: ==_xlfn.XLOOKUP(C24,总表!B:B,总表!J:J,无0) -> 埃米平台+埃米陪跑服务 | E24: ==_xlfn.XLOOKUP(C24,总表!B:B,总表!L:L,无,0) -> 46084 | F24: ==_xlfn.XLOOKUP(C24,总表!B:B,总表!M:M,无,0) -> FB, INS,TK | G24: ==_xlfn.XLOOKUP(C24,总表!B:B,总表!C:C,无,0) -> 46083.687 | H24: ==_xlfn.XLOOKUP(C24,总表!B:B,总表!F:F,无,0) -> 刘帝 | I24: ==_xlfn.XLOOKUP(C24,总表!B:B,总表!P:P,无,0) -> 0 | J24: 46084 | K24: 北京 | L24: 宋佳美 | M24: 46086 | N24: 服务中 | P24: ==IF(K24<>"",IF(ISBLANK(M24),IF(TODAY()-J24>14,"超时","未超时"),IF(M24-J24>14,"超时","未超时")),"") -> 未超时
A25: 24 | B25: ==_xlfn.XLOOKUP(C25,总表!B:B,总表!A:A,无,0) -> 70 | C25: 佛山市牧风科技有限公司 | D25: ==_xlfn.XLOOKUP(C25,总表!B:B,总表!J:J,无0) -> 埃米平台+埃米陪跑服务 | E25: ==_xlfn.XLOOKUP(C25,总表!B:B,总表!L:L,无,0) -> 46111 | F25: ==_xlfn.XLOOKUP(C25,总表!B:B,总表!M:M,无,0) -> FB | G25: ==_xlfn.XLOOKUP(C25,总表!B:B,总表!C:C,无,0) -> 46083.911 | H25: ==_xlfn.XLOOKUP(C25,总表!B:B,总表!F:F,无,0) -> 武卓玉 | I25: ==_xlfn.XLOOKUP(C25,总表!B:B,总表!P:P,无,0) -> 信息在旧的收集表 | J25: 46111 | K25: 北京 | L25: 王芷娇 | N25: 注册装修中 | P25: ==IF(K25<>"",IF(ISBLANK(M25),IF(TODAY()-J25>14,"超时","未超时"),IF(M25-J25>14,"超时","未超时")),"") -> 超时
A26: 25 | B26: ==_xlfn.XLOOKUP(C26,总表!B:B,总表!A:A,无,0) -> 72 | C26: 北京而为科技有限公司 | D26: ==_xlfn.XLOOKUP(C26,总表!B:B,总表!J:J,无0) -> 埃米平台+埃米陪跑服务 | E26: ==_xlfn.XLOOKUP(C26,总表!B:B,总表!L:L,无,0) -> 46086 | F26: ==_xlfn.XLOOKUP(C26,总表!B:B,总表!M:M,无,0) -> X, FB, INS,TK, VK | G26: ==_xlfn.XLOOKUP(C26,总表!B:B,总表!C:C,无,0) -> 46084.603 | H26: ==_xlfn.XLOOKUP(C26,总表!B:B,总表!F:F,无,0) -> 张楠 | I26: ==_xlfn.XLOOKUP(C26,总表!B:B,总表!P:P,无,0) -> 0 | J26: 46087 | K26: 洛阳 | L26: 董轩豪 | M26: 46104 | N26: 服务中 | P26: ==IF(K26<>"",IF(ISBLANK(M26),IF(TODAY()-J26>14,"超时","未超时"),IF(M26-J26>14,"超时","未超时")),"") -> 超时 | Q26: 客户确认授权申请延迟
A27: 26 | B27: ==_xlfn.XLOOKUP(C27,总表!B:B,总表!A:A,无,0) -> 80 | C27: 佛山市富琪家具有限公司 | D27: ==_xlfn.XLOOKUP(C27,总表!B:B,总表!J:J,无0) -> 埃米平台+埃米代运营服务 | E27: ==_xlfn.XLOOKUP(C27,总表!B:B,总表!L:L,无,0) -> 46095 | F27: ==_xlfn.XLOOKUP(C27,总表!B:B,总表!M:M,无,0) -> TK, X, INS, Youtube, FB | G27: ==_xlfn.XLOOKUP(C27,总表!B:B,总表!C:C,无,0) -> 46084.737 | H27: ==_xlfn.XLOOKUP(C27,总表!B:B,总表!F:F,无,0) -> 刘帝 | I27: ==_xlfn.XLOOKUP(C27,总表!B:B,总表!P:P,无,0) -> 0 | J27: 46091 | K27: 北京 | L27: 强硕 | M27: 46105 | N27: 服务中 | P27: ==IF(K27<>"",IF(ISBLANK(M27),IF(TODAY()-J27>14,"超时","未超时"),IF(M27-J27>14,"超时","未超时")),"") -> 未超时
A28: 27 | B28: ==_xlfn.XLOOKUP(C28,总表!B:B,总表!A:A,无,0) -> 81 | C28: 东莞市沃富五金制品有限公司 | D28: ==_xlfn.XLOOKUP(C28,总表!B:B,总表!J:J,无0) -> 埃米平台+埃米陪跑服务 | E28: ==_xlfn.XLOOKUP(C28,总表!B:B,总表!L:L,无,0) -> 46097 | F28: ==_xlfn.XLOOKUP(C28,总表!B:B,总表!M:M,无,0) -> FB,TK, X, Youtube, INS | G28: ==_xlfn.XLOOKUP(C28,总表!B:B,总表!C:C,无,0) -> 46090.747 | H28: ==_xlfn.XLOOKUP(C28,总表!B:B,总表!F:F,无,0) -> 武卓玉 | I28: ==_xlfn.XLOOKUP(C28,总表!B:B,总表!P:P,无,0) -> 0 | J28: 46098 | K28: 北京 | L28: 王芷娇 | M28: 46106 | N28: 服务中 | P28: ==IF(K28<>"",IF(ISBLANK(M28),IF(TODAY()-J28>14,"超时","未超时"),IF(M28-J28>14,"超时","未超时")),"") -> 未超时
A29: 28 | B29: ==_xlfn.XLOOKUP(C29,总表!B:B,总表!A:A,无,0) -> 82 | C29: 湖北龙瑞铝业有限公司 | D29: ==_xlfn.XLOOKUP(C29,总表!B:B,总表!J:J,无0) -> 埃米平台+埃米陪跑服务 | E29: ==_xlfn.XLOOKUP(C29,总表!B:B,总表!L:L,无,0) -> 46091 | F29: ==_xlfn.XLOOKUP(C29,总表!B:B,总表!M:M,无,0) -> FB,TK, INS | G29: ==_xlfn.XLOOKUP(C29,总表!B:B,总表!C:C,无,0) -> 46084.791 | H29: ==_xlfn.XLOOKUP(C29,总表!B:B,总表!F:F,无,0) -> 张楠 | I29: 签A推B A公司：湖北龙瑞铝业有限公司 B公司：河南天冠铝业有限公司 | J29: 46100 | K29: 北京 | L29: 王芷娇 | M29: 46111 | N29: 服务中 | P29: ==IF(K29<>"",IF(ISBLANK(M29),IF(TODAY()-J29>14,"超时","未超时"),IF(M29-J29>14,"超时","未超时")),"") -> 未超时
A30: 29 | B30: ==_xlfn.XLOOKUP(C30,总表!B:B,总表!A:A,无,0) -> 83 | C30: 程力汽车（武汉）有限公司 | D30: ==_xlfn.XLOOKUP(C30,总表!B:B,总表!J:J,无0) -> 埃米平台+埃米代运营服务 | E30: ==_xlfn.XLOOKUP(C30,总表!B:B,总表!L:L,无,0) -> 46085 | F30: ==_xlfn.XLOOKUP(C30,总表!B:B,总表!M:M,无,0) -> TK, Youtube, FB, VK, Linkedin | G30: ==_xlfn.XLOOKUP(C30,总表!B:B,总表!C:C,无,0) -> 46084.505 | H30: ==_xlfn.XLOOKUP(C30,总表!B:B,总表!F:F,无,0) -> 张楠 | I30: ==_xlfn.XLOOKUP(C30,总表!B:B,总表!P:P,无,0) -> 1、群名：CLW-WH-埃米代运营服务群 2、更换过平台：最终是先行运营facebook youtube tiktok三个平台； linkedin vk两个平台客户注册并授权后，我们再开始运营 | J30: 46085 | K30: 洛阳 | L30: 冯珍 | M30: 46097 | N30: 服务中 | P30: ==IF(K30<>"",IF(ISBLANK(M30),IF(TODAY()-J30>14,"超时","未超时"),IF(M30-J30>14,"超时","未超时")),"") -> 未超时
A31: 30 | B31: ==_xlfn.XLOOKUP(C31,总表!B:B,总表!A:A,无,0) -> 87 | C31: 江阴市钟联国际贸易有限公司 | D31: ==_xlfn.XLOOKUP(C31,总表!B:B,总表!J:J,无0) -> 埃米平台+埃米代运营服务 | E31: ==_xlfn.XLOOKUP(C31,总表!B:B,总表!L:L,无,0) -> 46086 | F31: ==_xlfn.XLOOKUP(C31,总表!B:B,总表!M:M,无,0) -> TK, X, INS, Youtube, FB | G31: ==_xlfn.XLOOKUP(C31,总表!B:B,总表!C:C,无,0) -> 46085.674 | H31: ==_xlfn.XLOOKUP(C31,总表!B:B,总表!F:F,无,0) -> 刘帝 | J31: 46086 | K31: 洛阳 | L31: 黄晓晨 | M31: 46092 | N31: 服务中 | P31: ==IF(K31<>"",IF(ISBLANK(M31),IF(TODAY()-J31>14,"超时","未超时"),IF(M31-J31>14,"超时","未超时")),"") -> 未超时
A32: 31 | B32: ==_xlfn.XLOOKUP(C32,总表!B:B,总表!A:A,无,0) -> 96 | C32: 杭州赛途沃贸易有限公司 | D32: ==_xlfn.XLOOKUP(C32,总表!B:B,总表!J:J,无0) -> 埃米平台+埃米陪跑服务 | E32: ==_xlfn.XLOOKUP(C32,总表!B:B,总表!L:L,无,0) -> 46087 | F32: ==_xlfn.XLOOKUP(C32,总表!B:B,总表!M:M,无,0) -> FB,TK, INS, X, Youtube | G32: ==_xlfn.XLOOKUP(C32,总表!B:B,总表!C:C,无,0) -> 46086.654 | H32: ==_xlfn.XLOOKUP(C32,总表!B:B,总表!F:F,无,0) -> 武卓玉 | I32: ==_xlfn.XLOOKUP(C32,总表!B:B,总表!P:P,无,0) -> 0 | J32: 46087 | K32: 北京 | L32: 李睿琦 | M32: 46093 | N32: 服务中 | P32: ==IF(K32<>"",IF(ISBLANK(M32),IF(TODAY()-J32>14,"超时","未超时"),IF(M32-J32>14,"超时","未超时")),"") -> 未超时
A33: 32 | B33: ==_xlfn.XLOOKUP(C33,总表!B:B,总表!A:A,无,0) -> 100 | C33: 佛山市顺德区乐从镇银满鑫家具厂 | D33: ==_xlfn.XLOOKUP(C33,总表!B:B,总表!J:J,无0) -> 埃米平台+埃米陪跑服务 | E33: ==_xlfn.XLOOKUP(C33,总表!B:B,总表!L:L,无,0) -> 46087 | F33: ==_xlfn.XLOOKUP(C33,总表!B:B,总表!M:M,无,0) -> FB, X,TK, INS, Youtube | G33: ==_xlfn.XLOOKUP(C33,总表!B:B,总表!C:C,无,0) -> 46086.746 | H33: ==_xlfn.XLOOKUP(C33,总表!B:B,总表!F:F,无,0) -> 武卓玉 | I33: ==_xlfn.XLOOKUP(C33,总表!B:B,总表!P:P,无,0) -> 0 | J33: 46087 | K33: 北京 | L33: 李睿琦 | M33: 46094 | N33: 服务中 | P33: ==IF(K33<>"",IF(ISBLANK(M33),IF(TODAY()-J33>14,"超时","未超时"),IF(M33-J33>14,"超时","未超时")),"") -> 未超时
A34: 33 | B34: ==_xlfn.XLOOKUP(C34,总表!B:B,总表!A:A,无,0) -> 101 | C34: 安徽沃德刷业有限公司 | D34: ==_xlfn.XLOOKUP(C34,总表!B:B,总表!J:J,无0) -> 埃米平台+埃米陪跑服务 | E34: ==_xlfn.XLOOKUP(C34,总表!B:B,总表!L:L,无,0) -> 46092 | F34: ==_xlfn.XLOOKUP(C34,总表!B:B,总表!M:M,无,0) -> TK, FB | G34: ==_xlfn.XLOOKUP(C34,总表!B:B,总表!C:C,无,0) -> 46086.75 | H34: ==_xlfn.XLOOKUP(C34,总表!B:B,总表!F:F,无,0) -> 刘帝 | I34: ==_xlfn.XLOOKUP(C34,总表!B:B,总表!P:P,无,0) -> 0 | J34: 46093 | K34: 北京 | L34: 李睿琦 | M34: 46097 | N34: 服务中 | P34: ==IF(K34<>"",IF(ISBLANK(M34),IF(TODAY()-J34>14,"超时","未超时"),IF(M34-J34>14,"超时","未超时")),"") -> 未超时
A35: 34 | B35: ==_xlfn.XLOOKUP(C35,总表!B:B,总表!A:A,无,0) -> 103 | C35: 济南豪赛楼宇工程有限公司 | D35: ==_xlfn.XLOOKUP(C35,总表!B:B,总表!J:J,无0) -> 埃米平台+埃米陪跑服务 | E35: ==_xlfn.XLOOKUP(C35,总表!B:B,总表!L:L,无,0) -> 46086 | F35: ==_xlfn.XLOOKUP(C35,总表!B:B,总表!M:M,无,0) -> TK, FB, INS | G35: ==_xlfn.XLOOKUP(C35,总表!B:B,总表!C:C,无,0) -> 46086.734 | H35: ==_xlfn.XLOOKUP(C35,总表!B:B,总表!F:F,无,0) -> 刘帝 | I35: ==_xlfn.XLOOKUP(C35,总表!B:B,总表!P:P,无,0) -> 0 | J35: 46087 | K35: 北京 | L35: 李睿琦 | M35: 46097 | N35: 服务中 | P35: ==IF(K35<>"",IF(ISBLANK(M35),IF(TODAY()-J35>14,"超时","未超时"),IF(M35-J35>14,"超时","未超时")),"") -> 未超时
A36: 35 | B36: ==_xlfn.XLOOKUP(C36,总表!B:B,总表!A:A,无,0) -> 108 | C36: 深圳市金亚诺电子有限公司 | D36: ==_xlfn.XLOOKUP(C36,总表!B:B,总表!J:J,无0) -> 埃米平台+埃米陪跑服务 | E36: ==_xlfn.XLOOKUP(C36,总表!B:B,总表!L:L,无,0) -> 46092 | F36: ==_xlfn.XLOOKUP(C36,总表!B:B,总表!M:M,无,0) -> TK, INS, Youtube, FB, X | G36: ==_xlfn.XLOOKUP(C36,总表!B:B,总表!C:C,无,0) -> 46087.683 | H36: ==_xlfn.XLOOKUP(C36,总表!B:B,总表!F:F,无,0) -> 张楠 | I36: ==_xlfn.XLOOKUP(C36,总表!B:B,总表!P:P,无,0) -> 0 | J36: 46092 | K36: 北京 | L36: 王芷娇 | M36: 46099 | N36: 服务中 | P36: ==IF(K36<>"",IF(ISBLANK(M36),IF(TODAY()-J36>14,"超时","未超时"),IF(M36-J36>14,"超时","未超时")),"") -> 未超时
A37: 36 | B37: ==_xlfn.XLOOKUP(C37,总表!B:B,总表!A:A,无,0) -> 111 | C37: 深圳市莱特蒙光电科技有限公司 | D37: ==_xlfn.XLOOKUP(C37,总表!B:B,总表!J:J,无0) -> 埃米平台+埃米陪跑服务 | E37: ==_xlfn.XLOOKUP(C37,总表!B:B,总表!L:L,无,0) -> 46092 | F37: ==_xlfn.XLOOKUP(C37,总表!B:B,总表!M:M,无,0) -> TK, INS, Youtube, FB, X | G37: ==_xlfn.XLOOKUP(C37,总表!B:B,总表!C:C,无,0) -> 46087.661 | H37: ==_xlfn.XLOOKUP(C37,总表!B:B,总表!F:F,无,0) -> 武卓玉 | I37: ==_xlfn.XLOOKUP(C37,总表!B:B,总表!P:P,无,0) -> 0 | J37: 46093 | K37: 北京 | L37: 李睿琦 | M37: 46101 | N37: 服务中 | P37: ==IF(K37<>"",IF(ISBLANK(M37),IF(TODAY()-J37>14,"超时","未超时"),IF(M37-J37>14,"超时","未超时")),"") -> 未超时
A38: 37 | B38: ==_xlfn.XLOOKUP(C38,总表!B:B,总表!A:A,无,0) -> 112 | C38: 佛山市长富宝佳家居用品有限公司 | D38: ==_xlfn.XLOOKUP(C38,总表!B:B,总表!J:J,无0) -> 埃米平台+埃米陪跑服务 | E38: ==_xlfn.XLOOKUP(C38,总表!B:B,总表!L:L,无,0) -> 46092 | F38: ==_xlfn.XLOOKUP(C38,总表!B:B,总表!M:M,无,0) -> FB, INS,TK, Youtube | G38: ==_xlfn.XLOOKUP(C38,总表!B:B,总表!C:C,无,0) -> 46087.682 | H38: ==_xlfn.XLOOKUP(C38,总表!B:B,总表!F:F,无,0) -> 刘帝 | I38: ==_xlfn.XLOOKUP(C38,总表!B:B,总表!P:P,无,0) -> 0 | J38: 46093 | K38: 北京 | L38: 李睿琦 | M38: 46099 | N38: 服务中 | P38: ==IF(K38<>"",IF(ISBLANK(M38),IF(TODAY()-J38>14,"超时","未超时"),IF(M38-J38>14,"超时","未超时")),"") -> 未超时
A39: 38 | B39: ==_xlfn.XLOOKUP(C39,总表!B:B,总表!A:A,无,0) -> 113 | C39: 山东华江汽车贸易有限公司 | D39: ==_xlfn.XLOOKUP(C39,总表!B:B,总表!J:J,无0) -> 埃米平台+埃米陪跑服务 | E39: ==_xlfn.XLOOKUP(C39,总表!B:B,总表!L:L,无,0) -> 46097 | F39: ==_xlfn.XLOOKUP(C39,总表!B:B,总表!M:M,无,0) -> TK, INS, Youtube, FB, X | G39: ==_xlfn.XLOOKUP(C39,总表!B:B,总表!C:C,无,0) -> 46087.692 | H39: ==_xlfn.XLOOKUP(C39,总表!B:B,总表!F:F,无,0) -> 张楠 | I39: ==_xlfn.XLOOKUP(C39,总表!B:B,总表!P:P,无,0) -> 0 | J39: 46097 | K39: 北京 | L39: 李睿琦 | M39: 46101 | N39: 服务中 | P39: ==IF(K39<>"",IF(ISBLANK(M39),IF(TODAY()-J39>14,"超时","未超时"),IF(M39-J39>14,"超时","未超时")),"") -> 未超时
A40: 39 | B40: ==_xlfn.XLOOKUP(C40,总表!B:B,总表!A:A,无,0) -> 119 | C40: 深圳市龙岗区泽沐珠宝设计工作室 | D40: ==_xlfn.XLOOKUP(C40,总表!B:B,总表!J:J,无0) -> 埃米平台+埃米陪跑服务 | E40: ==_xlfn.XLOOKUP(C40,总表!B:B,总表!L:L,无,0) -> 0 | F40: ==_xlfn.XLOOKUP(C40,总表!B:B,总表!M:M,无,0) -> 0 | G40: ==_xlfn.XLOOKUP(C40,总表!B:B,总表!C:C,无,0) -> 46089.751 | H40: ==_xlfn.XLOOKUP(C40,总表!B:B,总表!F:F,无,0) -> 武卓玉 | I40: 客户侧迟迟未回复 | P40: ==IF(K40<>"",IF(ISBLANK(M40),IF(TODAY()-J40>14,"超时","未超时"),IF(M40-J40>14,"超时","未超时")),"")
A41: 40 | B41: ==_xlfn.XLOOKUP(C41,总表!B:B,总表!A:A,无,0) -> 120 | C41: 天津新禾国际经贸有限公司 | D41: ==_xlfn.XLOOKUP(C41,总表!B:B,总表!J:J,无0) -> 埃米平台+埃米陪跑服务 | E41: ==_xlfn.XLOOKUP(C41,总表!B:B,总表!L:L,无,0) -> 46121 | F41: ==_xlfn.XLOOKUP(C41,总表!B:B,总表!M:M,无,0) -> TK, X, INS, Youtube, FB | G41: ==_xlfn.XLOOKUP(C41,总表!B:B,总表!C:C,无,0) -> 46087.739 | H41: ==_xlfn.XLOOKUP(C41,总表!B:B,总表!F:F,无,0) -> 张楠 | I41: 签A推B： A公司：天津新禾国际经贸有限公司 B公司：天津新禾食品有限公司 | J41: 46121 | K41: 北京 | L41: 李睿琦 | P41: ==IF(K41<>"",IF(ISBLANK(M41),IF(TODAY()-J41>14,"超时","未超时"),IF(M41-J41>14,"超时","未超时")),"") -> 未超时
A42: 41 | B42: ==_xlfn.XLOOKUP(C42,总表!B:B,总表!A:A,无,0) -> 122 | C42: 武义深潮家居用品有限公司 | D42: ==_xlfn.XLOOKUP(C42,总表!B:B,总表!J:J,无0) -> 埃米平台+埃米陪跑服务 | E42: ==_xlfn.XLOOKUP(C42,总表!B:B,总表!L:L,无,0) -> 46097 | F42: ==_xlfn.XLOOKUP(C42,总表!B:B,总表!M:M,无,0) -> TK, INS, Youtube, FB, Linkedin | G42: ==_xlfn.XLOOKUP(C42,总表!B:B,总表!C:C,无,0) -> 46087.783 | H42: ==_xlfn.XLOOKUP(C42,总表!B:B,总表!F:F,无,0) -> 刘帝 | I42: ==_xlfn.XLOOKUP(C42,总表!B:B,总表!P:P,无,0) -> 0 | J42: 46097 | K42: 北京 | L42: 李睿琦 | M42: 46101 | N42: 服务中 | P42: ==IF(K42<>"",IF(ISBLANK(M42),IF(TODAY()-J42>14,"超时","未超时"),IF(M42-J42>14,"超时","未超时")),"") -> 未超时
A43: 42 | B43: ==_xlfn.XLOOKUP(C43,总表!B:B,总表!A:A,无,0) -> 123 | C43: 香河货不全商贸有限公司 | D43: ==_xlfn.XLOOKUP(C43,总表!B:B,总表!J:J,无0) -> 埃米平台+埃米陪跑服务 | E43: ==_xlfn.XLOOKUP(C43,总表!B:B,总表!L:L,无,0) -> 46090 | F43: ==_xlfn.XLOOKUP(C43,总表!B:B,总表!M:M,无,0) -> TK, INS, FB, X, Youtube, VK, Linkedin | G43: ==_xlfn.XLOOKUP(C43,总表!B:B,总表!C:C,无,0) -> 46087.742 | H43: ==_xlfn.XLOOKUP(C43,总表!B:B,总表!F:F,无,0) -> 武卓玉 | J43: 46090 | K43: 北京 | L43: 宋佳美 | M43: 46086 | N43: 服务中 | P43: ==IF(K43<>"",IF(ISBLANK(M43),IF(TODAY()-J43>14,"超时","未超时"),IF(M43-J43>14,"超时","未超时")),"") -> 未超时
A44: 43 | B44: ==_xlfn.XLOOKUP(C44,总表!B:B,总表!A:A,无,0) -> 125 | C44: 郑州金山化工有限公司 | D44: ==_xlfn.XLOOKUP(C44,总表!B:B,总表!J:J,无0) -> 埃米平台+埃米陪跑服务 | E44: ==_xlfn.XLOOKUP(C44,总表!B:B,总表!L:L,无,0) -> 46091 | F44: ==_xlfn.XLOOKUP(C44,总表!B:B,总表!M:M,无,0) -> TK, X, INS, Youtube, FB | G44: ==_xlfn.XLOOKUP(C44,总表!B:B,总表!C:C,无,0) -> 46090.46 | H44: ==_xlfn.XLOOKUP(C44,总表!B:B,总表!F:F,无,0) -> 谭婷 | I44: ==_xlfn.XLOOKUP(C44,总表!B:B,总表!P:P,无,0) -> 出差没时间 | J44: 46091 | K44: 北京 | L44: 王芷娇 | M44: 46099 | N44: 服务中 | P44: ==IF(K44<>"",IF(ISBLANK(M44),IF(TODAY()-J44>14,"超时","未超时"),IF(M44-J44>14,"超时","未超时")),"") -> 未超时
A45: 44 | B45: ==_xlfn.XLOOKUP(C45,总表!B:B,总表!A:A,无,0) -> 126 | C45: 北京市晋鹏鑫磊电气有限公司 | D45: ==_xlfn.XLOOKUP(C45,总表!B:B,总表!J:J,无0) -> 埃米平台+埃米陪跑服务 | E45: ==_xlfn.XLOOKUP(C45,总表!B:B,总表!L:L,无,0) -> 46093 | F45: ==_xlfn.XLOOKUP(C45,总表!B:B,总表!M:M,无,0) -> TK, X, INS, Youtube, FB | G45: ==_xlfn.XLOOKUP(C45,总表!B:B,总表!C:C,无,0) -> 46090.578 | H45: ==_xlfn.XLOOKUP(C45,总表!B:B,总表!F:F,无,0) -> 张楠 | I45: ==_xlfn.XLOOKUP(C45,总表!B:B,总表!P:P,无,0) -> 0 | J45: 46093 | K45: 北京 | L45: 宋佳美 | M45: 46108 | N45: 服务中 | P45: ==IF(K45<>"",IF(ISBLANK(M45),IF(TODAY()-J45>14,"超时","未超时"),IF(M45-J45>14,"超时","未超时")),"") -> 超时 | Q45: 客户确认授权时间延迟
A46: 45 | B46: ==_xlfn.XLOOKUP(C46,总表!B:B,总表!A:A,无,0) -> 127 | C46: 山东国冠金属制品有限公司 | D46: ==_xlfn.XLOOKUP(C46,总表!B:B,总表!J:J,无0) -> 埃米平台+埃米陪跑服务 | E46: ==_xlfn.XLOOKUP(C46,总表!B:B,总表!L:L,无,0) -> 46091 | F46: ==_xlfn.XLOOKUP(C46,总表!B:B,总表!M:M,无,0) -> TK,X,INS,Youtube,FB | G46: ==_xlfn.XLOOKUP(C46,总表!B:B,总表!C:C,无,0) -> 46090.594 | H46: ==_xlfn.XLOOKUP(C46,总表!B:B,总表!F:F,无,0) -> 刘帝 | I46: ==_xlfn.XLOOKUP(C46,总表!B:B,总表!P:P,无,0) -> 0 | J46: 46091 | K46: 北京 | L46: 王芷娇 | M46: 46098 | N46: 服务中 | P46: ==IF(K46<>"",IF(ISBLANK(M46),IF(TODAY()-J46>14,"超时","未超时"),IF(M46-J46>14,"超时","未超时")),"") -> 未超时
A47: 46 | B47: ==_xlfn.XLOOKUP(C47,总表!B:B,总表!A:A,无,0) -> 129 | C47: 上海净迈包装科技有限公司 | D47: ==_xlfn.XLOOKUP(C47,总表!B:B,总表!J:J,无0) -> 埃米平台+埃米陪跑服务 | E47: ==_xlfn.XLOOKUP(C47,总表!B:B,总表!L:L,无,0) -> 46091 | F47: ==_xlfn.XLOOKUP(C47,总表!B:B,总表!M:M,无,0) -> FB, INS, Linkedin | G47: ==_xlfn.XLOOKUP(C47,总表!B:B,总表!C:C,无,0) -> 46091.43 | H47: ==_xlfn.XLOOKUP(C47,总表!B:B,总表!F:F,无,0) -> 谭婷 | I47: ==_xlfn.XLOOKUP(C47,总表!B:B,总表!P:P,无,0) -> 0 | J47: 46092 | K47: 北京 | L47: 王芷娇 | M47: 46105 | N47: 服务中 | P47: ==IF(K47<>"",IF(ISBLANK(M47),IF(TODAY()-J47>14,"超时","未超时"),IF(M47-J47>14,"超时","未超时")),"") -> 未超时
A48: 47 | B48: ==_xlfn.XLOOKUP(C48,总表!B:B,总表!A:A,无,0) -> 131 | C48: 成都科达亨科技有限责任公司 | D48: ==_xlfn.XLOOKUP(C48,总表!B:B,总表!J:J,无0) -> 埃米平台+埃米陪跑服务 | E48: ==_xlfn.XLOOKUP(C48,总表!B:B,总表!L:L,无,0) -> 46092 | F48: ==_xlfn.XLOOKUP(C48,总表!B:B,总表!M:M,无,0) -> TK, X, INS, Youtube, FB | G48: ==_xlfn.XLOOKUP(C48,总表!B:B,总表!C:C,无,0) -> 46090.699 | H48: ==_xlfn.XLOOKUP(C48,总表!B:B,总表!F:F,无,0) -> 谭婷 | I48: ==_xlfn.XLOOKUP(C48,总表!B:B,总表!P:P,无,0) -> 0 | J48: 46092 | K48: 北京 | L48: 王芷娇 | M48: 46100 | N48: 服务中 | P48: ==IF(K48<>"",IF(ISBLANK(M48),IF(TODAY()-J48>14,"超时","未超时"),IF(M48-J48>14,"超时","未超时")),"") -> 未超时
A49: 48 | B49: ==_xlfn.XLOOKUP(C49,总表!B:B,总表!A:A,无,0) -> 132 | C49: 广东喜安居卫浴有限公司 | D49: ==_xlfn.XLOOKUP(C49,总表!B:B,总表!J:J,无0) -> 埃米平台+埃米陪跑服务 | E49: ==_xlfn.XLOOKUP(C49,总表!B:B,总表!L:L,无,0) -> 46092 | F49: ==_xlfn.XLOOKUP(C49,总表!B:B,总表!M:M,无,0) -> TK, X, INS, Youtube, FB | G49: ==_xlfn.XLOOKUP(C49,总表!B:B,总表!C:C,无,0) -> 46091.503 | H49: ==_xlfn.XLOOKUP(C49,总表!B:B,总表!F:F,无,0) -> 谭婷 | I49: 签A推B： A公司：广东喜安居卫浴有限公司 B公司：Great Sink LLC | J49: 46092 | K49: 北京 | L49: 李睿琦 | M49: 46097 | N49: 服务中 | P49: ==IF(K49<>"",IF(ISBLANK(M49),IF(TODAY()-J49>14,"超时","未超时"),IF(M49-J49>14,"超时","未超时")),"") -> 未超时 | S49: fb被封
A50: 49 | B50: ==_xlfn.XLOOKUP(C50,总表!B:B,总表!A:A,无,0) -> 133 | C50: 佛山市元基工业科技有限公司 | D50: ==_xlfn.XLOOKUP(C50,总表!B:B,总表!J:J,无0) -> 埃米平台+埃米陪跑服务 | E50: ==_xlfn.XLOOKUP(C50,总表!B:B,总表!L:L,无,0) -> 46101 | F50: ==_xlfn.XLOOKUP(C50,总表!B:B,总表!M:M,无,0) -> TK, X, INS, Youtube, FB | G50: ==_xlfn.XLOOKUP(C50,总表!B:B,总表!C:C,无,0) -> 46091.451 | H50: ==_xlfn.XLOOKUP(C50,总表!B:B,总表!F:F,无,0) -> 张楠 | I50: ==_xlfn.XLOOKUP(C50,总表!B:B,总表!P:P,无,0) -> ["https://wdcdn.qpic.cn/MTY4ODg1NjI5NTY2NzY5OA_583603_OWqkESOXKLcKXy0O_1773133853?w=1162&h=335",400,115.3184165232358] | J50: 46101 | K50: 北京 | L50: 王芷娇 | M50: 46105 | N50: 服务中 | P50: ==IF(K50<>"",IF(ISBLANK(M50),IF(TODAY()-J50>14,"超时","未超时"),IF(M50-J50>14,"超时","未超时")),"") -> 未超时
A51: 50 | B51: ==_xlfn.XLOOKUP(C51,总表!B:B,总表!A:A,无,0) -> 135 | C51: 湖北碧澜天博来建筑股份有限公司 | D51: ==_xlfn.XLOOKUP(C51,总表!B:B,总表!J:J,无0) -> 埃米平台+埃米陪跑服务 | E51: ==_xlfn.XLOOKUP(C51,总表!B:B,总表!L:L,无,0) -> 46097 | F51: ==_xlfn.XLOOKUP(C51,总表!B:B,总表!M:M,无,0) -> FB,TK | G51: ==_xlfn.XLOOKUP(C51,总表!B:B,总表!C:C,无,0) -> 46091.682 | H51: ==_xlfn.XLOOKUP(C51,总表!B:B,总表!F:F,无,0) -> 武卓玉 | J51: 46097 | K51: 北京 | L51: 王芷娇 | M51: 46100 | N51: 服务中 | P51: ==IF(K51<>"",IF(ISBLANK(M51),IF(TODAY()-J51>14,"超时","未超时"),IF(M51-J51>14,"超时","未超时")),"") -> 未超时
A52: 51 | B52: ==_xlfn.XLOOKUP(C52,总表!B:B,总表!A:A,无,0) -> 58 | C52: 成都蒽科科技有限公司 | D52: ==_xlfn.XLOOKUP(C52,总表!B:B,总表!J:J,无0) -> 埃米平台+埃米陪跑服务 | E52: ==_xlfn.XLOOKUP(C52,总表!B:B,总表!L:L,无,0) -> 46091 | F52: ==_xlfn.XLOOKUP(C52,总表!B:B,总表!M:M,无,0) -> TK, X, INS, Youtube, FB, Linkedin | G52: ==_xlfn.XLOOKUP(C52,总表!B:B,总表!C:C,无,0) -> 46081.654 | H52: ==_xlfn.XLOOKUP(C52,总表!B:B,总表!F:F,无,0) -> 谭婷 | I52: ==_xlfn.XLOOKUP(C52,总表!B:B,总表!P:P,无,0) -> 0 | J52: 46092 | K52: 北京 | L52: 宋佳美 | M52: 46105 | N52: 服务中 | P52: ==IF(K52<>"",IF(ISBLANK(M52),IF(TODAY()-J52>14,"超时","未超时"),IF(M52-J52>14,"超时","未超时")),"") -> 未超时
A53: 52 | B53: ==_xlfn.XLOOKUP(C53,总表!B:B,总表!A:A,无,0) -> 138 | C53: 广东鸿泉节能设备有限公司 | D53: ==_xlfn.XLOOKUP(C53,总表!B:B,总表!J:J,无0) -> 埃米平台+埃米陪跑服务 | E53: ==_xlfn.XLOOKUP(C53,总表!B:B,总表!L:L,无,0) -> 46112 | F53: ==_xlfn.XLOOKUP(C53,总表!B:B,总表!M:M,无,0) -> TK, X, INS, Youtube, FB | G53: ==_xlfn.XLOOKUP(C53,总表!B:B,总表!C:C,无,0) -> 46092.418 | H53: ==_xlfn.XLOOKUP(C53,总表!B:B,总表!F:F,无,0) -> 武卓玉 | I53: 3月31日下午 | J53: 46112 | K53: 北京 | L53: 王芷娇 | M53: 46122 | N53: 服务中 | P53: ==IF(K53<>"",IF(ISBLANK(M53),IF(TODAY()-J53>14,"超时","未超时"),IF(M53-J53>14,"超时","未超时")),"") -> 未超时
A54: 53 | B54: ==_xlfn.XLOOKUP(C54,总表!B:B,总表!A:A,无,0) -> 139 | C54: 霸州市钰荣家具厂 | D54: ==_xlfn.XLOOKUP(C54,总表!B:B,总表!J:J,无0) -> 埃米平台+埃米陪跑服务 | E54: ==_xlfn.XLOOKUP(C54,总表!B:B,总表!L:L,无,0) -> 46097 | F54: ==_xlfn.XLOOKUP(C54,总表!B:B,总表!M:M,无,0) -> TK, X, INS, Youtube, FB | G54: ==_xlfn.XLOOKUP(C54,总表!B:B,总表!C:C,无,0) -> 46092.455 | H54: ==_xlfn.XLOOKUP(C54,总表!B:B,总表!F:F,无,0) -> 张楠 | I54: ==_xlfn.XLOOKUP(C54,总表!B:B,总表!P:P,无,0) -> 0 | J54: 46097 | K54: 北京 | L54: 王芷娇 | M54: 46101 | N54: 服务中 | P54: ==IF(K54<>"",IF(ISBLANK(M54),IF(TODAY()-J54>14,"超时","未超时"),IF(M54-J54>14,"超时","未超时")),"") -> 未超时
A55: 54 | B55: ==_xlfn.XLOOKUP(C55,总表!B:B,总表!A:A,无,0) -> 145 | C55: 青岛鑫华星特钢科技有限公司 | D55: ==_xlfn.XLOOKUP(C55,总表!B:B,总表!J:J,无0) -> 埃米平台+埃米陪跑服务 | E55: ==_xlfn.XLOOKUP(C55,总表!B:B,总表!L:L,无,0) -> 46098 | F55: ==_xlfn.XLOOKUP(C55,总表!B:B,总表!M:M,无,0) -> TK, X, INS, Youtube, FB | G55: ==_xlfn.XLOOKUP(C55,总表!B:B,总表!C:C,无,0) -> 46092.491 | H55: ==_xlfn.XLOOKUP(C55,总表!B:B,总表!F:F,无,0) -> 武卓玉 | I55: ==_xlfn.XLOOKUP(C55,总表!B:B,总表!P:P,无,0) -> 0 | J55: 46100 | K55: 北京 | L55: 王芷娇 | M55: 46105 | N55: 服务中 | P55: ==IF(K55<>"",IF(ISBLANK(M55),IF(TODAY()-J55>14,"超时","未超时"),IF(M55-J55>14,"超时","未超时")),"") -> 未超时
A56: 55 | B56: ==_xlfn.XLOOKUP(C56,总表!B:B,总表!A:A,无,0) -> 155 | C56: 四川弘晟石油工程技术服务有限公司 | D56: ==_xlfn.XLOOKUP(C56,总表!B:B,总表!J:J,无0) -> 埃米平台+埃米陪跑服务 | E56: ==_xlfn.XLOOKUP(C56,总表!B:B,总表!L:L,无,0) -> 46106 | F56: ==_xlfn.XLOOKUP(C56,总表!B:B,总表!M:M,无,0) -> X, Youtube, FB, Linkedin | G56: ==_xlfn.XLOOKUP(C56,总表!B:B,总表!C:C,无,0) -> 46093.632 | H56: ==_xlfn.XLOOKUP(C56,总表!B:B,总表!F:F,无,0) -> 刘帝 | I56: 3月25日下午 | J56: 46106 | K56: 北京 | L56: 王芷娇 | M56: 46120 | N56: 服务中 | P56: ==IF(K56<>"",IF(ISBLANK(M56),IF(TODAY()-J56>14,"超时","未超时"),IF(M56-J56>14,"超时","未超时")),"") -> 未超时
A57: 56 | B57: ==_xlfn.XLOOKUP(C57,总表!B:B,总表!A:A,无,0) -> 157 | C57: 河北雄安肯威尔贸易有限公司 | D57: ==_xlfn.XLOOKUP(C57,总表!B:B,总表!J:J,无0) -> 埃米平台+埃米陪跑服务 | E57: ==_xlfn.XLOOKUP(C57,总表!B:B,总表!L:L,无,0) -> 46099 | F57: ==_xlfn.XLOOKUP(C57,总表!B:B,总表!M:M,无,0) -> TK, INS, FB | G57: ==_xlfn.XLOOKUP(C57,总表!B:B,总表!C:C,无,0) -> 46093.703 | H57: ==_xlfn.XLOOKUP(C57,总表!B:B,总表!F:F,无,0) -> 刘帝 | J57: 46099 | K57: 北京 | L57: 李睿琦 | M57: 46112 | N57: 服务中 | P57: ==IF(K57<>"",IF(ISBLANK(M57),IF(TODAY()-J57>14,"超时","未超时"),IF(M57-J57>14,"超时","未超时")),"") -> 未超时
A58: 57 | B58: ==_xlfn.XLOOKUP(C58,总表!B:B,总表!A:A,无,0) -> 161 | C58: 双龙集团有限公司 | D58: ==_xlfn.XLOOKUP(C58,总表!B:B,总表!J:J,无0) -> 埃米平台+埃米陪跑服务 | E58: ==_xlfn.XLOOKUP(C58,总表!B:B,总表!L:L,无,0) -> 46099 | F58: ==_xlfn.XLOOKUP(C58,总表!B:B,总表!M:M,无,0) -> FB,TK, Youtube, Linkedin, VK | G58: ==_xlfn.XLOOKUP(C58,总表!B:B,总表!C:C,无,0) -> 46094.452 | H58: ==_xlfn.XLOOKUP(C58,总表!B:B,总表!F:F,无,0) -> 刘帝 | J58: 46099 | K58: 北京 | L58: 李睿琦 | M58: 46106 | N58: 服务中 | P58: ==IF(K58<>"",IF(ISBLANK(M58),IF(TODAY()-J58>14,"超时","未超时"),IF(M58-J58>14,"超时","未超时")),"") -> 未超时
A59: 58 | B59: ==_xlfn.XLOOKUP(C59,总表!B:B,总表!A:A,无,0) -> 163 | C59: 浙江众兴智能科技股份有限公司 | D59: ==_xlfn.XLOOKUP(C59,总表!B:B,总表!J:J,无0) -> 埃米平台+埃米陪跑服务 | E59: ==_xlfn.XLOOKUP(C59,总表!B:B,总表!L:L,无,0) -> 46098 | F59: ==_xlfn.XLOOKUP(C59,总表!B:B,总表!M:M,无,0) -> TK, Youtube, FB | G59: ==_xlfn.XLOOKUP(C59,总表!B:B,总表!C:C,无,0) -> 46094.551 | H59: ==_xlfn.XLOOKUP(C59,总表!B:B,总表!F:F,无,0) -> 谭婷 | J59: 46098 | K59: 北京 | L59: 宋佳美 | M59: 46113 | N59: 服务中 | P59: ==IF(K59<>"",IF(ISBLANK(M59),IF(TODAY()-J59>14,"超时","未超时"),IF(M59-J59>14,"超时","未超时")),"") -> 超时 | Q59: 注册岗位人员变动，需要内部交接
A60: 59 | B60: ==_xlfn.XLOOKUP(C60,总表!B:B,总表!A:A,无,0) -> 165 | C60: 成都良木屿汽车销售有限责任公司 | D60: ==_xlfn.XLOOKUP(C60,总表!B:B,总表!J:J,无0) -> 埃米平台+埃米陪跑服务 | E60: ==_xlfn.XLOOKUP(C60,总表!B:B,总表!L:L,无,0) -> 46100 | F60: ==_xlfn.XLOOKUP(C60,总表!B:B,总表!M:M,无,0) -> TK, X, INS, Youtube, FB, VK | G60: ==_xlfn.XLOOKUP(C60,总表!B:B,总表!C:C,无,0) -> 46094.685 | H60: ==_xlfn.XLOOKUP(C60,总表!B:B,总表!F:F,无,0) -> 张楠 | J60: 46101 | K60: 北京 | L60: 王芷娇 | M60: 46121 | N60: 服务中 | P60: ==IF(K60<>"",IF(ISBLANK(M60),IF(TODAY()-J60>14,"超时","未超时"),IF(M60-J60>14,"超时","未超时")),"") -> 超时 | Q60: 客户资料提供超时
A61: 60 | B61: ==_xlfn.XLOOKUP(C61,总表!B:B,总表!A:A,无,0) -> 166 | C61: 永康市精航观光车有限公司 | D61: ==_xlfn.XLOOKUP(C61,总表!B:B,总表!J:J,无0) -> 埃米平台+埃米代运营服务 | E61: ==_xlfn.XLOOKUP(C61,总表!B:B,总表!L:L,无,0) -> 46098 | F61: ==_xlfn.XLOOKUP(C61,总表!B:B,总表!M:M,无,0) -> FB | G61: ==_xlfn.XLOOKUP(C61,总表!B:B,总表!C:C,无,0) -> 46094.67 | H61: ==_xlfn.XLOOKUP(C61,总表!B:B,总表!F:F,无,0) -> 刘帝 | J61: 46098 | K61: 北京 | L61: 周俣昕 | M61: 46106 | N61: 服务中 | P61: ==IF(K61<>"",IF(ISBLANK(M61),IF(TODAY()-J61>14,"超时","未超时"),IF(M61-J61>14,"超时","未超时")),"") -> 未超时
A62: 61 | B62: ==_xlfn.XLOOKUP(C62,总表!B:B,总表!A:A,无,0) -> 168 | C62: 佛山市松汇科技有限公司 | D62: ==_xlfn.XLOOKUP(C62,总表!B:B,总表!J:J,无0) -> 埃米平台+埃米代运营服务 | E62: ==_xlfn.XLOOKUP(C62,总表!B:B,总表!L:L,无,0) -> 46097 | F62: ==_xlfn.XLOOKUP(C62,总表!B:B,总表!M:M,无,0) -> TK, X, Youtube, FB, INS | G62: ==_xlfn.XLOOKUP(C62,总表!B:B,总表!C:C,无,0) -> 46094.654 | H62: ==_xlfn.XLOOKUP(C62,总表!B:B,总表!F:F,无,0) -> 谭婷 | J62: 46097 | K62: 北京 | L62: 高吉 | M62: 46104 | N62: 服务中 | P62: ==IF(K62<>"",IF(ISBLANK(M62),IF(TODAY()-J62>14,"超时","未超时"),IF(M62-J62>14,"超时","未超时")),"") -> 未超时
A63: 62 | B63: ==_xlfn.XLOOKUP(C63,总表!B:B,总表!A:A,无,0) -> 171 | C63: 佛山市英菲桁架器材有限公司 | D63: ==_xlfn.XLOOKUP(C63,总表!B:B,总表!J:J,无0) -> 埃米平台+埃米陪跑服务 | E63: ==_xlfn.XLOOKUP(C63,总表!B:B,总表!L:L,无,0) -> 46097 | F63: ==_xlfn.XLOOKUP(C63,总表!B:B,总表!M:M,无,0) -> TK, X, INS, FB, Youtube | G63: ==_xlfn.XLOOKUP(C63,总表!B:B,总表!C:C,无,0) -> 46094.706 | H63: ==_xlfn.XLOOKUP(C63,总表!B:B,总表!F:F,无,0) -> 武卓玉 | J63: 46097 | K63: 北京 | L63: 王芷娇 | M63: 46104 | N63: 服务中 | P63: ==IF(K63<>"",IF(ISBLANK(M63),IF(TODAY()-J63>14,"超时","未超时"),IF(M63-J63>14,"超时","未超时")),"") -> 未超时
A64: 63 | B64: ==_xlfn.XLOOKUP(C64,总表!B:B,总表!A:A,无,0) -> 174 | C64: 北京惠丰佳业汽车销售有限公司 | D64: ==_xlfn.XLOOKUP(C64,总表!B:B,总表!J:J,无0) -> 埃米平台+埃米陪跑服务 | E64: ==_xlfn.XLOOKUP(C64,总表!B:B,总表!L:L,无,0) -> 46099 | F64: ==_xlfn.XLOOKUP(C64,总表!B:B,总表!M:M,无,0) -> TK, X, INS, Youtube, FB, VK | G64: ==_xlfn.XLOOKUP(C64,总表!B:B,总表!C:C,无,0) -> 46093.737 | H64: ==_xlfn.XLOOKUP(C64,总表!B:B,总表!F:F,无,0) -> 谭婷 | J64: 46099 | K64: 北京 | L64: 王芷娇 | M64: 46114 | N64: 服务中 | P64: ==IF(K64<>"",IF(ISBLANK(M64),IF(TODAY()-J64>14,"超时","未超时"),IF(M64-J64>14,"超时","未超时")),"") -> 超时 | Q64: 注册岗人员变动，facebook封控严重
A65: 64 | B65: ==_xlfn.XLOOKUP(C65,总表!B:B,总表!A:A,无,0) -> 178 | C65: 佛山瑞电新能源有限公司 | D65: ==_xlfn.XLOOKUP(C65,总表!B:B,总表!J:J,无0) -> 埃米平台+埃米陪跑服务 | E65: ==_xlfn.XLOOKUP(C65,总表!B:B,总表!L:L,无,0) -> 46097 | F65: ==_xlfn.XLOOKUP(C65,总表!B:B,总表!M:M,无,0) -> TK, INS, FB | G65: ==_xlfn.XLOOKUP(C65,总表!B:B,总表!C:C,无,0) -> 46095.599 | H65: ==_xlfn.XLOOKUP(C65,总表!B:B,总表!F:F,无,0) -> 谭婷 | J65: 46097 | K65: 北京 | L65: 宋佳美 | M65: 46111 | N65: 服务中 | P65: ==IF(K65<>"",IF(ISBLANK(M65),IF(TODAY()-J65>14,"超时","未超时"),IF(M65-J65>14,"超时","未超时")),"") -> 未超时
A66: 65 | B66: ==_xlfn.XLOOKUP(C66,总表!B:B,总表!A:A,无,0) -> 181 | C66: 河南狄鑫机械设备安装有限公司 | D66: ==_xlfn.XLOOKUP(C66,总表!B:B,总表!J:J,无0) -> 埃米平台+埃米陪跑服务 | E66: ==_xlfn.XLOOKUP(C66,总表!B:B,总表!L:L,无,0) -> 0 | F66: ==_xlfn.XLOOKUP(C66,总表!B:B,总表!M:M,无,0) -> 0 | G66: ==_xlfn.XLOOKUP(C66,总表!B:B,总表!C:C,无,0) -> 46094.762 | H66: ==_xlfn.XLOOKUP(C66,总表!B:B,总表!F:F,无,0) -> 谭婷 | P66: ==IF(K66<>"",IF(ISBLANK(M66),IF(TODAY()-J66>14,"超时","未超时"),IF(M66-J66>14,"超时","未超时")),"")
A67: 66 | B67: ==_xlfn.XLOOKUP(C67,总表!B:B,总表!A:A,无,0) -> 192 | C67: 清远市华南铜铝业有限公司 | D67: ==_xlfn.XLOOKUP(C67,总表!B:B,总表!J:J,无0) -> 埃米平台+埃米代运营服务 | E67: ==_xlfn.XLOOKUP(C67,总表!B:B,总表!L:L,无,0) -> 46112 | F67: ==_xlfn.XLOOKUP(C67,总表!B:B,总表!M:M,无,0) -> TK, X, INS, FB | G67: ==_xlfn.XLOOKUP(C67,总表!B:B,总表!C:C,无,0) -> 46094.761 | H67: ==_xlfn.XLOOKUP(C67,总表!B:B,总表!F:F,无,0) -> 刘帝 | I67: 3月31日下午 | J67: 46112 | K67: 北京 | L67: 刘颖 | N67: 注册装修中 | P67: ==IF(K67<>"",IF(ISBLANK(M67),IF(TODAY()-J67>14,"超时","未超时"),IF(M67-J67>14,"超时","未超时")),"") -> 未超时
A68: 67 | B68: ==_xlfn.XLOOKUP(C68,总表!B:B,总表!A:A,无,0) -> 193 | C68: 上海大蕴文化传播有限公司 | D68: ==_xlfn.XLOOKUP(C68,总表!B:B,总表!J:J,无0) -> 埃米平台+埃米陪跑服务 | E68: ==_xlfn.XLOOKUP(C68,总表!B:B,总表!L:L,无,0) -> 0 | F68: ==_xlfn.XLOOKUP(C68,总表!B:B,总表!M:M,无,0) -> 0 | G68: ==_xlfn.XLOOKUP(C68,总表!B:B,总表!C:C,无,0) -> 46094.75 | H68: ==_xlfn.XLOOKUP(C68,总表!B:B,总表!F:F,无,0) -> 刘帝 | P68: ==IF(K68<>"",IF(ISBLANK(M68),IF(TODAY()-J68>14,"超时","未超时"),IF(M68-J68>14,"超时","未超时")),"")
A69: 68 | B69: ==_xlfn.XLOOKUP(C69,总表!B:B,总表!A:A,无,0) -> 194 | C69: 深圳市德天诚电子有限公司 | D69: ==_xlfn.XLOOKUP(C69,总表!B:B,总表!J:J,无0) -> 埃米平台+埃米陪跑服务 | E69: ==_xlfn.XLOOKUP(C69,总表!B:B,总表!L:L,无,0) -> 46101 | F69: ==_xlfn.XLOOKUP(C69,总表!B:B,总表!M:M,无,0) -> TK, X, INS, Youtube, FB | G69: ==_xlfn.XLOOKUP(C69,总表!B:B,总表!C:C,无,0) -> 46094.742 | H69: ==_xlfn.XLOOKUP(C69,总表!B:B,总表!F:F,无,0) -> 刘帝 | J69: 46101 | K69: 北京 | L69: 王芷娇 | M69: 46106 | N69: 服务中 | P69: ==IF(K69<>"",IF(ISBLANK(M69),IF(TODAY()-J69>14,"超时","未超时"),IF(M69-J69>14,"超时","未超时")),"") -> 未超时
A70: 69 | B70: ==_xlfn.XLOOKUP(C70,总表!B:B,总表!A:A,无,0) -> 197 | C70: 浙江盛思户外用品有限公司 | D70: ==_xlfn.XLOOKUP(C70,总表!B:B,总表!J:J,无0) -> 埃米平台+埃米陪跑服务 | E70: ==_xlfn.XLOOKUP(C70,总表!B:B,总表!L:L,无,0) -> 46099 | F70: ==_xlfn.XLOOKUP(C70,总表!B:B,总表!M:M,无,0) -> TK, X, INS, Youtube, FB | G70: ==_xlfn.XLOOKUP(C70,总表!B:B,总表!C:C,无,0) -> 46094.71 | H70: ==_xlfn.XLOOKUP(C70,总表!B:B,总表!F:F,无,0) -> 武卓玉 | J70: 46099 | K70: 北京 | L70: 王芷娇 | M70: 46108 | N70: 服务中 | P70: ==IF(K70<>"",IF(ISBLANK(M70),IF(TODAY()-J70>14,"超时","未超时"),IF(M70-J70>14,"超时","未超时")),"") -> 未超时
A71: 70 | B71: ==_xlfn.XLOOKUP(C71,总表!B:B,总表!A:A,无,0) -> 182 | C71: 河南丰尔牧业设备有限公司 | D71: ==_xlfn.XLOOKUP(C71,总表!B:B,总表!J:J,无0) -> 埃米平台+埃米陪跑服务 | E71: ==_xlfn.XLOOKUP(C71,总表!B:B,总表!L:L,无,0) -> 46100 | F71: ==_xlfn.XLOOKUP(C71,总表!B:B,总表!M:M,无,0) -> TK, Youtube, FB, VK | G71: ==_xlfn.XLOOKUP(C71,总表!B:B,总表!C:C,无,0) -> 46094.745 | H71: ==_xlfn.XLOOKUP(C71,总表!B:B,总表!F:F,无,0) -> 张楠 | J71: 46100 | K71: 北京 | L71: 李睿琦 | M71: 46111 | N71: 服务中 | P71: ==IF(K71<>"",IF(ISBLANK(M71),IF(TODAY()-J71>14,"超时","未超时"),IF(M71-J71>14,"超时","未超时")),"") -> 未超时
A72: 71 | B72: ==_xlfn.XLOOKUP(C72,总表!B:B,总表!A:A,无,0) -> 203 | C72: 上海金箭水射流设备制造有限公司 | D72: ==_xlfn.XLOOKUP(C72,总表!B:B,总表!J:J,无0) -> 埃米平台+埃米陪跑服务 | E72: ==_xlfn.XLOOKUP(C72,总表!B:B,总表!L:L,无,0) -> 46099 | F72: ==_xlfn.XLOOKUP(C72,总表!B:B,总表!M:M,无,0) -> TK, X, INS, Youtube, FB, VK, Linkedin | G72: ==_xlfn.XLOOKUP(C72,总表!B:B,总表!C:C,无,0) -> 46097.44 | H72: ==_xlfn.XLOOKUP(C72,总表!B:B,总表!F:F,无,0) -> 谭婷 | J72: 46099 | K72: 北京 | L72: 王芷娇 | M72: 46106 | N72: 服务中 | P72: ==IF(K72<>"",IF(ISBLANK(M72),IF(TODAY()-J72>14,"超时","未超时"),IF(M72-J72>14,"超时","未超时")),"") -> 未超时
A73: 72 | B73: ==_xlfn.XLOOKUP(C73,总表!B:B,总表!A:A,无,0) -> 204 | C73: 威海斯茂莱柯户外运动有限公司 | D73: ==_xlfn.XLOOKUP(C73,总表!B:B,总表!J:J,无0) -> 埃米平台+埃米代运营服务 | E73: ==_xlfn.XLOOKUP(C73,总表!B:B,总表!L:L,无,0) -> 46100 | F73: ==_xlfn.XLOOKUP(C73,总表!B:B,总表!M:M,无,0) -> Youtube, FB,TK, X, INS | G73: ==_xlfn.XLOOKUP(C73,总表!B:B,总表!C:C,无,0) -> 46097.63 | H73: ==_xlfn.XLOOKUP(C73,总表!B:B,总表!F:F,无,0) -> 张楠 | J73: 46101 | K73: 北京 | L73: 强硕 | M73: 46105 | N73: 服务中 | P73: ==IF(K73<>"",IF(ISBLANK(M73),IF(TODAY()-J73>14,"超时","未超时"),IF(M73-J73>14,"超时","未超时")),"") -> 未超时
A74: 73 | B74: ==_xlfn.XLOOKUP(C74,总表!B:B,总表!A:A,无,0) -> 208 | C74: 山东华企国际贸易有限公司 | D74: ==_xlfn.XLOOKUP(C74,总表!B:B,总表!J:J,无0) -> 埃米平台+埃米陪跑服务 | E74: ==_xlfn.XLOOKUP(C74,总表!B:B,总表!L:L,无,0) -> 46099 | F74: ==_xlfn.XLOOKUP(C74,总表!B:B,总表!M:M,无,0) -> TK, X, INS, Youtube, FB | G74: ==_xlfn.XLOOKUP(C74,总表!B:B,总表!C:C,无,0) -> 46097.742 | H74: ==_xlfn.XLOOKUP(C74,总表!B:B,总表!F:F,无,0) -> 刘帝 | J74: 46100 | K74: 北京 | L74: 李睿琦 | M74: 46104 | N74: 服务中 | P74: ==IF(K74<>"",IF(ISBLANK(M74),IF(TODAY()-J74>14,"超时","未超时"),IF(M74-J74>14,"超时","未超时")),"") -> 未超时
A75: 74 | B75: ==_xlfn.XLOOKUP(C75,总表!B:B,总表!A:A,无,0) -> 211 | C75: 速帕斯（苏州）贸易有限公司 | D75: ==_xlfn.XLOOKUP(C75,总表!B:B,总表!J:J,无0) -> 埃米平台+埃米陪跑服务 | E75: ==_xlfn.XLOOKUP(C75,总表!B:B,总表!L:L,无,0) -> 46099 | F75: ==_xlfn.XLOOKUP(C75,总表!B:B,总表!M:M,无,0) -> X, INS, FB,TK, VK | G75: ==_xlfn.XLOOKUP(C75,总表!B:B,总表!C:C,无,0) -> 46098.402 | H75: ==_xlfn.XLOOKUP(C75,总表!B:B,总表!F:F,无,0) -> 谭婷 | J75: 46099 | K75: 北京 | L75: 宋佳美 | M75: 46114 | N75: 服务中 | P75: ==IF(K75<>"",IF(ISBLANK(M75),IF(TODAY()-J75>14,"超时","未超时"),IF(M75-J75>14,"超时","未超时")),"") -> 超时 | Q75: 注册岗位人员变动，需要内部交接
A76: 75 | B76: ==_xlfn.XLOOKUP(C76,总表!B:B,总表!A:A,无,0) -> 212 | C76: 亿将科技（广东）有限公司 | D76: ==_xlfn.XLOOKUP(C76,总表!B:B,总表!J:J,无0) -> 埃米平台+埃米陪跑服务 | E76: ==_xlfn.XLOOKUP(C76,总表!B:B,总表!L:L,无,0) -> 46104 | F76: ==_xlfn.XLOOKUP(C76,总表!B:B,总表!M:M,无,0) -> FB,TK, Youtube, X, VK | G76: ==_xlfn.XLOOKUP(C76,总表!B:B,总表!C:C,无,0) -> 46098.508 | H76: ==_xlfn.XLOOKUP(C76,总表!B:B,总表!F:F,无,0) -> 张楠 | J76: 46104 | K76: 北京 | L76: 王芷娇 | M76: 46108 | N76: 服务中 | P76: ==IF(K76<>"",IF(ISBLANK(M76),IF(TODAY()-J76>14,"超时","未超时"),IF(M76-J76>14,"超时","未超时")),"") -> 未超时
A77: 76 | B77: ==_xlfn.XLOOKUP(C77,总表!B:B,总表!A:A,无,0) -> 214 | C77: 上海络华物流设备有限公司 | D77: ==_xlfn.XLOOKUP(C77,总表!B:B,总表!J:J,无0) -> 埃米平台+埃米陪跑服务 | E77: ==_xlfn.XLOOKUP(C77,总表!B:B,总表!L:L,无,0) -> 46120 | F77: ==_xlfn.XLOOKUP(C77,总表!B:B,总表!M:M,无,0) -> TK, X, INS, Youtube, FB, Linkedin | G77: ==_xlfn.XLOOKUP(C77,总表!B:B,总表!C:C,无,0) -> 46098.488 | H77: ==_xlfn.XLOOKUP(C77,总表!B:B,总表!F:F,无,0) -> 刘帝 | J77: 46120 | K77: 北京 | L77: 李睿琦 | N77: 注册装修中 | P77: ==IF(K77<>"",IF(ISBLANK(M77),IF(TODAY()-J77>14,"超时","未超时"),IF(M77-J77>14,"超时","未超时")),"") -> 未超时
A78: 77 | B78: ==_xlfn.XLOOKUP(C78,总表!B:B,总表!A:A,无,0) -> 218 | C78: 建德市新裕塑胶材料有限公司 | D78: ==_xlfn.XLOOKUP(C78,总表!B:B,总表!J:J,无0) -> 埃米平台+埃米陪跑服务 | E78: ==_xlfn.XLOOKUP(C78,总表!B:B,总表!L:L,无,0) -> 46099 | F78: ==_xlfn.XLOOKUP(C78,总表!B:B,总表!M:M,无,0) -> TK, X, INS, Youtube, FB, VK, Linkedin | G78: ==_xlfn.XLOOKUP(C78,总表!B:B,总表!C:C,无,0) -> 46098.634 | H78: ==_xlfn.XLOOKUP(C78,总表!B:B,总表!F:F,无,0) -> 武卓玉 | J78: 46100 | K78: 北京 | L78: 宋佳美 | M78: 46112 | N78: 服务中 | P78: ==IF(K78<>"",IF(ISBLANK(M78),IF(TODAY()-J78>14,"超时","未超时"),IF(M78-J78>14,"超时","未超时")),"") -> 未超时
A79: 78 | B79: ==_xlfn.XLOOKUP(C79,总表!B:B,总表!A:A,无,0) -> 57 | C79: 威海托罗服饰有限公司 | D79: ==_xlfn.XLOOKUP(C79,总表!B:B,总表!J:J,无0) -> 埃米平台+埃米陪跑服务 | E79: ==_xlfn.XLOOKUP(C79,总表!B:B,总表!L:L,无,0) -> 46097 | F79: ==_xlfn.XLOOKUP(C79,总表!B:B,总表!M:M,无,0) -> TK, X, INS, Youtube, FB | G79: ==_xlfn.XLOOKUP(C79,总表!B:B,总表!C:C,无,0) -> 46081.673 | H79: ==_xlfn.XLOOKUP(C79,总表!B:B,总表!F:F,无,0) -> 武卓玉 | J79: 46099 | K79: 北京 | L79: 宋佳美 | M79: 46114 | N79: 服务中 | P79: ==IF(K79<>"",IF(ISBLANK(M79),IF(TODAY()-J79>14,"超时","未超时"),IF(M79-J79>14,"超时","未超时")),"") -> 超时 | Q79: 注册岗位人员变动，需要内部交接
A80: 79 | B80: ==_xlfn.XLOOKUP(C80,总表!B:B,总表!A:A,无,0) -> 216 | C80: 苏州市轻舟智能科技有限公司 | D80: ==_xlfn.XLOOKUP(C80,总表!B:B,总表!J:J,无0) -> 埃米平台+埃米陪跑服务 | E80: ==_xlfn.XLOOKUP(C80,总表!B:B,总表!L:L,无,0) -> 46104 | F80: ==_xlfn.XLOOKUP(C80,总表!B:B,总表!M:M,无,0) -> FB,TK, INS, Linkedin | G80: ==_xlfn.XLOOKUP(C80,总表!B:B,总表!C:C,无,0) -> 46098.71 | H80: ==_xlfn.XLOOKUP(C80,总表!B:B,总表!F:F,无,0) -> 张楠 | J80: 46104 | K80: 北京 | L80: 王芷娇 | M80: 46108 | N80: 服务中 | P80: ==IF(K80<>"",IF(ISBLANK(M80),IF(TODAY()-J80>14,"超时","未超时"),IF(M80-J80>14,"超时","未超时")),"") -> 未超时
A81: 80 | B81: ==_xlfn.XLOOKUP(C81,总表!B:B,总表!A:A,无,0) -> 217 | C81: 长沙普惠环保机械有限公司 | D81: ==_xlfn.XLOOKUP(C81,总表!B:B,总表!J:J,无0) -> 埃米平台+埃米陪跑服务 | E81: ==_xlfn.XLOOKUP(C81,总表!B:B,总表!L:L,无,0) -> 0 | F81: ==_xlfn.XLOOKUP(C81,总表!B:B,总表!M:M,无,0) -> 0 | G81: ==_xlfn.XLOOKUP(C81,总表!B:B,总表!C:C,无,0) -> 46098.714 | H81: ==_xlfn.XLOOKUP(C81,总表!B:B,总表!F:F,无,0) -> 谭婷 | P81: ==IF(K81<>"",IF(ISBLANK(M81),IF(TODAY()-J81>14,"超时","未超时"),IF(M81-J81>14,"超时","未超时")),"")
A82: 81 | B82: ==_xlfn.XLOOKUP(C82,总表!B:B,总表!A:A,无,0) -> 219 | C82: 威海云海户外用品有限公司 | D82: ==_xlfn.XLOOKUP(C82,总表!B:B,总表!J:J,无0) -> 埃米平台+埃米陪跑服务 | E82: ==_xlfn.XLOOKUP(C82,总表!B:B,总表!L:L,无,0) -> 0 | F82: ==_xlfn.XLOOKUP(C82,总表!B:B,总表!M:M,无,0) -> 0 | G82: ==_xlfn.XLOOKUP(C82,总表!B:B,总表!C:C,无,0) -> 46098.722 | H82: ==_xlfn.XLOOKUP(C82,总表!B:B,总表!F:F,无,0) -> 彭才杰 | P82: ==IF(K82<>"",IF(ISBLANK(M82),IF(TODAY()-J82>14,"超时","未超时"),IF(M82-J82>14,"超时","未超时")),"")
A83: 82 | B83: ==_xlfn.XLOOKUP(C83,总表!B:B,总表!A:A,无,0) -> 222 | C83: 詹晓东（SF：429001197806307437） | D83: ==_xlfn.XLOOKUP(C83,总表!B:B,总表!J:J,无0) -> 埃米平台+埃米陪跑服务 | E83: ==_xlfn.XLOOKUP(C83,总表!B:B,总表!L:L,无,0) -> 0 | F83: ==_xlfn.XLOOKUP(C83,总表!B:B,总表!M:M,无,0) -> 0 | G83: ==_xlfn.XLOOKUP(C83,总表!B:B,总表!C:C,无,0) -> 46098.769 | H83: ==_xlfn.XLOOKUP(C83,总表!B:B,总表!F:F,无,0) -> 0 | P83: ==IF(K83<>"",IF(ISBLANK(M83),IF(TODAY()-J83>14,"超时","未超时"),IF(M83-J83>14,"超时","未超时")),"")
A84: 83 | B84: ==_xlfn.XLOOKUP(C84,总表!B:B,总表!A:A,无,0) -> 225 | C84: 湖南泵多多科技有限公司 | D84: ==_xlfn.XLOOKUP(C84,总表!B:B,总表!J:J,无0) -> 埃米平台+埃米陪跑服务 | E84: ==_xlfn.XLOOKUP(C84,总表!B:B,总表!L:L,无,0) -> 46107 | F84: ==_xlfn.XLOOKUP(C84,总表!B:B,总表!M:M,无,0) -> INS, Youtube, FB, Linkedin,TK | G84: ==_xlfn.XLOOKUP(C84,总表!B:B,总表!C:C,无,0) -> 46098.742 | H84: ==_xlfn.XLOOKUP(C84,总表!B:B,总表!F:F,无,0) -> 刘帝 | I84: 3月26日下午 信息收集表客户填错，修改成ins youtube fb 领英 tk | J84: 46107 | K84: 北京 | L84: 李睿琦 | M84: 46122 | N84: 服务中 | P84: ==IF(K84<>"",IF(ISBLANK(M84),IF(TODAY()-J84>14,"超时","未超时"),IF(M84-J84>14,"超时","未超时")),"") -> 超时 | Q84: Facebook风控严重
A85: 84 | B85: ==_xlfn.XLOOKUP(C85,总表!B:B,总表!A:A,无,0) -> 226 | C85: 佛山市顺科彩印包装有限公司 | D85: ==_xlfn.XLOOKUP(C85,总表!B:B,总表!J:J,无0) -> 埃米平台+埃米代运营服务 | E85: ==_xlfn.XLOOKUP(C85,总表!B:B,总表!L:L,无,0) -> 0 | F85: ==_xlfn.XLOOKUP(C85,总表!B:B,总表!M:M,无,0) -> 0 | G85: ==_xlfn.XLOOKUP(C85,总表!B:B,总表!C:C,无,0) -> 46099.424 | H85: ==_xlfn.XLOOKUP(C85,总表!B:B,总表!F:F,无,0) -> 彭才杰 | P85: ==IF(K85<>"",IF(ISBLANK(M85),IF(TODAY()-J85>14,"超时","未超时"),IF(M85-J85>14,"超时","未超时")),"")
A86: 85 | B86: ==_xlfn.XLOOKUP(C86,总表!B:B,总表!A:A,无,0) -> 227 | C86: 江苏营力创电子材料有限公司 | D86: ==_xlfn.XLOOKUP(C86,总表!B:B,总表!J:J,无0) -> 埃米平台+埃米陪跑服务 | E86: ==_xlfn.XLOOKUP(C86,总表!B:B,总表!L:L,无,0) -> 46099 | F86: ==_xlfn.XLOOKUP(C86,总表!B:B,总表!M:M,无,0) -> TK, X, INS, Youtube, FB | G86: ==_xlfn.XLOOKUP(C86,总表!B:B,总表!C:C,无,0) -> 46099.447 | H86: ==_xlfn.XLOOKUP(C86,总表!B:B,总表!F:F,无,0) -> 武卓玉 | J86: 46104 | K86: 北京 | L86: 李睿琦 | M86: 46108 | N86: 服务中 | P86: ==IF(K86<>"",IF(ISBLANK(M86),IF(TODAY()-J86>14,"超时","未超时"),IF(M86-J86>14,"超时","未超时")),"") -> 未超时
A87: 86 | B87: ==_xlfn.XLOOKUP(C87,总表!B:B,总表!A:A,无,0) -> 228 | C87: 青岛利康源医疗器械有限公司 | D87: ==_xlfn.XLOOKUP(C87,总表!B:B,总表!J:J,无0) -> 埃米平台+埃米陪跑服务 | E87: ==_xlfn.XLOOKUP(C87,总表!B:B,总表!L:L,无,0) -> 46104 | F87: ==_xlfn.XLOOKUP(C87,总表!B:B,总表!M:M,无,0) -> tk、ins、X、youtube、FB | G87: ==_xlfn.XLOOKUP(C87,总表!B:B,总表!C:C,无,0) -> 46099.4 | H87: ==_xlfn.XLOOKUP(C87,总表!B:B,总表!F:F,无,0) -> 张楠 | J87: 46104 | K87: 北京 | L87: 王芷娇 | M87: 46112 | N87: 服务中 | P87: ==IF(K87<>"",IF(ISBLANK(M87),IF(TODAY()-J87>14,"超时","未超时"),IF(M87-J87>14,"超时","未超时")),"") -> 未超时
A88: 87 | B88: ==_xlfn.XLOOKUP(C88,总表!B:B,总表!A:A,无,0) -> 235 | C88: 山东联成橡塑制品有限公司 | D88: ==_xlfn.XLOOKUP(C88,总表!B:B,总表!J:J,无0) -> 埃米平台+埃米陪跑服务 | E88: ==_xlfn.XLOOKUP(C88,总表!B:B,总表!L:L,无,0) -> 46100 | F88: ==_xlfn.XLOOKUP(C88,总表!B:B,总表!M:M,无,0) -> TK, FB, Youtube, INS, VK | G88: ==_xlfn.XLOOKUP(C88,总表!B:B,总表!C:C,无,0) -> 46099.597 | H88: ==_xlfn.XLOOKUP(C88,总表!B:B,总表!F:F,无,0) -> 谭婷 | J88: 46100 | K88: 北京 | L88: 宋佳美 | M88: 46108 | N88: 服务中 | P88: ==IF(K88<>"",IF(ISBLANK(M88),IF(TODAY()-J88>14,"超时","未超时"),IF(M88-J88>14,"超时","未超时")),"") -> 未超时
A89: 88 | B89: ==_xlfn.XLOOKUP(C89,总表!B:B,总表!A:A,无,0) -> 234 | C89: 深圳市鑫日升机械有限公司 | D89: ==_xlfn.XLOOKUP(C89,总表!B:B,总表!J:J,无0) -> 埃米平台+埃米陪跑服务 | E89: ==_xlfn.XLOOKUP(C89,总表!B:B,总表!L:L,无,0) -> 46106 | F89: ==_xlfn.XLOOKUP(C89,总表!B:B,总表!M:M,无,0) -> TK, X, INS, Youtube, FB | G89: ==_xlfn.XLOOKUP(C89,总表!B:B,总表!C:C,无,0) -> 46099.589 | H89: ==_xlfn.XLOOKUP(C89,总表!B:B,总表!F:F,无,0) -> 谭婷 | I89: 3月25日上午 | J89: 46106 | K89: 北京 | L89: 李睿琦 | M89: 46119 | N89: 服务中 | P89: ==IF(K89<>"",IF(ISBLANK(M89),IF(TODAY()-J89>14,"超时","未超时"),IF(M89-J89>14,"超时","未超时")),"") -> 未超时 | Q89: fb公共主页在申请
A90: 89 | B90: ==_xlfn.XLOOKUP(C90,总表!B:B,总表!A:A,无,0) -> 236 | C90: 义乌市稠城宗帆制笔厂 | D90: ==_xlfn.XLOOKUP(C90,总表!B:B,总表!J:J,无0) -> 埃米平台+埃米陪跑服务 | E90: ==_xlfn.XLOOKUP(C90,总表!B:B,总表!L:L,无,0) -> 46104 | F90: ==_xlfn.XLOOKUP(C90,总表!B:B,总表!M:M,无,0) -> TK, INS, Youtube, FB, VK | G90: ==_xlfn.XLOOKUP(C90,总表!B:B,总表!C:C,无,0) -> 46099.534 | H90: ==_xlfn.XLOOKUP(C90,总表!B:B,总表!F:F,无,0) -> 彭才杰 | J90: 46104 | K90: 北京 | L90: 李睿琦 | M90: 46115 | N90: 服务中 | P90: ==IF(K90<>"",IF(ISBLANK(M90),IF(TODAY()-J90>14,"超时","未超时"),IF(M90-J90>14,"超时","未超时")),"") -> 未超时 | Q90: fb公共主页在申请
A91: 90 | B91: ==_xlfn.XLOOKUP(C91,总表!B:B,总表!A:A,无,0) -> 239 | C91: 木牛动力科技（武汉）有限公司 | D91: ==_xlfn.XLOOKUP(C91,总表!B:B,总表!J:J,无0) -> 埃米平台+埃米陪跑服务 | E91: ==_xlfn.XLOOKUP(C91,总表!B:B,总表!L:L,无,0) -> 46101 | F91: ==_xlfn.XLOOKUP(C91,总表!B:B,总表!M:M,无,0) -> TK, INS, Youtube, FB, VK | G91: ==_xlfn.XLOOKUP(C91,总表!B:B,总表!C:C,无,0) -> 46099.716 | H91: ==_xlfn.XLOOKUP(C91,总表!B:B,总表!F:F,无,0) -> 武卓玉 | I91: 加急 | J91: 46101 | K91: 北京 | L91: 李睿琦 | M91: 46104 | N91: 服务中 | P91: ==IF(K91<>"",IF(ISBLANK(M91),IF(TODAY()-J91>14,"超时","未超时"),IF(M91-J91>14,"超时","未超时")),"") -> 未超时
A92: 91 | B92: ==_xlfn.XLOOKUP(C92,总表!B:B,总表!A:A,无,0) -> 242 | C92: 武汉格美诺家居有限公司 | D92: ==_xlfn.XLOOKUP(C92,总表!B:B,总表!J:J,无0) -> 埃米平台+埃米陪跑服务 | E92: ==_xlfn.XLOOKUP(C92,总表!B:B,总表!L:L,无,0) -> 46103 | F92: ==_xlfn.XLOOKUP(C92,总表!B:B,总表!M:M,无,0) -> TK | G92: ==_xlfn.XLOOKUP(C92,总表!B:B,总表!C:C,无,0) -> 46099.673 | H92: ==_xlfn.XLOOKUP(C92,总表!B:B,总表!F:F,无,0) -> 刘帝 | J92: 46104 | K92: 北京 | L92: 王芷娇 | M92: 46107 | N92: 服务中 | P92: ==IF(K92<>"",IF(ISBLANK(M92),IF(TODAY()-J92>14,"超时","未超时"),IF(M92-J92>14,"超时","未超时")),"") -> 未超时
A93: 92 | B93: ==_xlfn.XLOOKUP(C93,总表!B:B,总表!A:A,无,0) -> 248 | C93: 山东依妍服饰有限公司 | D93: ==_xlfn.XLOOKUP(C93,总表!B:B,总表!J:J,无0) -> 埃米平台+埃米陪跑服务 | E93: ==_xlfn.XLOOKUP(C93,总表!B:B,总表!L:L,无,0) -> 46101 | F93: ==_xlfn.XLOOKUP(C93,总表!B:B,总表!M:M,无,0) -> INS FB TikTok YouTube X | G93: ==_xlfn.XLOOKUP(C93,总表!B:B,总表!C:C,无,0) -> 46100.639 | H93: ==_xlfn.XLOOKUP(C93,总表!B:B,总表!F:F,无,0) -> 张楠 | J93: 46101 | K93: 北京 | L93: 李睿琦 | M93: 46106 | N93: 服务中 | P93: ==IF(K93<>"",IF(ISBLANK(M93),IF(TODAY()-J93>14,"超时","未超时"),IF(M93-J93>14,"超时","未超时")),"") -> 未超时
A94: 93 | B94: ==_xlfn.XLOOKUP(C94,总表!B:B,总表!A:A,无,0) -> 251 | C94: 山东佰悦广告传媒有限公司 | D94: ==_xlfn.XLOOKUP(C94,总表!B:B,总表!J:J,无0) -> 埃米平台+埃米陪跑服务 | E94: ==_xlfn.XLOOKUP(C94,总表!B:B,总表!L:L,无,0) -> 46108 | F94: ==_xlfn.XLOOKUP(C94,总表!B:B,总表!M:M,无,0) -> TK,X,INS,Youtube,FB | G94: ==_xlfn.XLOOKUP(C94,总表!B:B,总表!C:C,无,0) -> 46100.672 | H94: ==_xlfn.XLOOKUP(C94,总表!B:B,总表!F:F,无,0) -> 彭才杰 | I94: 3月27日下午 | J94: 46108 | K94: 北京 | L94: 李睿琦 | M94: 46115 | N94: 服务中 | P94: ==IF(K94<>"",IF(ISBLANK(M94),IF(TODAY()-J94>14,"超时","未超时"),IF(M94-J94>14,"超时","未超时")),"") -> 未超时 | Q94: fb封控严重
A95: 94 | B95: ==_xlfn.XLOOKUP(C95,总表!B:B,总表!A:A,无,0) -> 252 | C95: 浙江威金斯工具有限公司 | D95: ==_xlfn.XLOOKUP(C95,总表!B:B,总表!J:J,无0) -> 埃米平台+埃米代运营服务 | E95: ==_xlfn.XLOOKUP(C95,总表!B:B,总表!L:L,无,0) -> 46101 | F95: ==_xlfn.XLOOKUP(C95,总表!B:B,总表!M:M,无,0) -> TK,X,INS,Youtube,FB | G95: ==_xlfn.XLOOKUP(C95,总表!B:B,总表!C:C,无,0) -> 46100.707 | H95: ==_xlfn.XLOOKUP(C95,总表!B:B,总表!F:F,无,0) -> 谭婷 | J95: 46101 | K95: 北京 | L95: 李雅童 | M95: 46112 | N95: 服务中 | P95: ==IF(K95<>"",IF(ISBLANK(M95),IF(TODAY()-J95>14,"超时","未超时"),IF(M95-J95>14,"超时","未超时")),"") -> 未超时
A96: 95 | B96: ==_xlfn.XLOOKUP(C96,总表!B:B,总表!A:A,无,0) -> 264 | C96: 深圳市瑞创锂能科技有限公司 | D96: ==_xlfn.XLOOKUP(C96,总表!B:B,总表!J:J,无0) -> 埃米平台+埃米陪跑服务 | E96: ==_xlfn.XLOOKUP(C96,总表!B:B,总表!L:L,无,0) -> 46104 | F96: ==_xlfn.XLOOKUP(C96,总表!B:B,总表!M:M,无,0) -> TK,X,INS,Youtube,FB | G96: ==_xlfn.XLOOKUP(C96,总表!B:B,总表!C:C,无,0) -> 46101.706 | H96: ==_xlfn.XLOOKUP(C96,总表!B:B,总表!F:F,无,0) -> 彭才杰 | I96: 3月25日下午 | J96: 46106 | K96: 北京 | L96: 王芷娇 | M96: 46114 | N96: 服务中 | P96: ==IF(K96<>"",IF(ISBLANK(M96),IF(TODAY()-J96>14,"超时","未超时"),IF(M96-J96>14,"超时","未超时")),"") -> 未超时
A97: 96 | B97: ==_xlfn.XLOOKUP(C97,总表!B:B,总表!A:A,无,0) -> 266 | C97: 湖南益格特钢科技有限公司 | D97: ==_xlfn.XLOOKUP(C97,总表!B:B,总表!J:J,无0) -> 埃米平台+埃米陪跑服务 | E97: ==_xlfn.XLOOKUP(C97,总表!B:B,总表!L:L,无,0) -> 46106 | F97: ==_xlfn.XLOOKUP(C97,总表!B:B,总表!M:M,无,0) -> VK, Youtube, FB,TK, Linkedin | G97: ==_xlfn.XLOOKUP(C97,总表!B:B,总表!C:C,无,0) -> 46101.751 | H97: ==_xlfn.XLOOKUP(C97,总表!B:B,总表!F:F,无,0) -> 刘帝 | I97: 3月25日上午 | J97: 46106 | K97: 北京 | L97: 李睿琦 | M97: 46115 | N97: 注册装修中 | P97: ==IF(K97<>"",IF(ISBLANK(M97),IF(TODAY()-J97>14,"超时","未超时"),IF(M97-J97>14,"超时","未超时")),"") -> 未超时
A98: 97 | B98: ==_xlfn.XLOOKUP(C98,总表!B:B,总表!A:A,无,0) -> 268 | C98: 佛山市博客家具有限公司 | D98: ==_xlfn.XLOOKUP(C98,总表!B:B,总表!J:J,无0) -> 埃米平台+埃米陪跑服务 | E98: ==_xlfn.XLOOKUP(C98,总表!B:B,总表!L:L,无,0) -> 46104 | F98: ==_xlfn.XLOOKUP(C98,总表!B:B,总表!M:M,无,0) -> TK、X、INS、Youtube、FB | G98: ==_xlfn.XLOOKUP(C98,总表!B:B,总表!C:C,无,0) -> 46104.37 | H98: ==_xlfn.XLOOKUP(C98,总表!B:B,总表!F:F,无,0) -> 彭才杰 | J98: 46104 | K98: 北京 | L98: 李睿琦 | M98: 46111 | N98: 服务中 | P98: ==IF(K98<>"",IF(ISBLANK(M98),IF(TODAY()-J98>14,"超时","未超时"),IF(M98-J98>14,"超时","未超时")),"") -> 未超时
A99: 98 | B99: ==_xlfn.XLOOKUP(C99,总表!B:B,总表!A:A,无,0) -> 269 | C99: 江苏宏昌天马物流装备有限公司 | D99: ==_xlfn.XLOOKUP(C99,总表!B:B,总表!J:J,无0) -> 埃米平台+埃米代运营服务 | E99: ==_xlfn.XLOOKUP(C99,总表!B:B,总表!L:L,无,0) -> 46104 | F99: ==_xlfn.XLOOKUP(C99,总表!B:B,总表!M:M,无,0) -> TK,INS,youtube,FB,领英 | G99: ==_xlfn.XLOOKUP(C99,总表!B:B,总表!C:C,无,0) -> 46101.843 | H99: ==_xlfn.XLOOKUP(C99,总表!B:B,总表!F:F,无,0) -> 彭才杰 | J99: 46104 | K99: 北京 | L99: 刘晟甫 | M99: 46115 | N99: 服务中 | P99: ==IF(K99<>"",IF(ISBLANK(M99),IF(TODAY()-J99>14,"超时","未超时"),IF(M99-J99>14,"超时","未超时")),"") -> 未超时
A100: 99 | B100: ==_xlfn.XLOOKUP(C100,总表!B:B,总表!A:A,无,0) -> 273 | C100: 苏州心之力机器人有限公司 | D100: ==_xlfn.XLOOKUP(C100,总表!B:B,总表!J:J,无0) -> 埃米平台+埃米陪跑服务 | E100: ==_xlfn.XLOOKUP(C100,总表!B:B,总表!L:L,无,0) -> 46104 | F100: ==_xlfn.XLOOKUP(C100,总表!B:B,总表!M:M,无,0) -> TK, X, Youtube, FB | G100: ==_xlfn.XLOOKUP(C100,总表!B:B,总表!C:C,无,0) -> 46104.429 | H100: ==_xlfn.XLOOKUP(C100,总表!B:B,总表!F:F,无,0) -> 武卓玉 | J100: 46104 | K100: 北京 | L100: 宋佳美 | M100: 46113 | N100: 服务中 | P100: ==IF(K100<>"",IF(ISBLANK(M100),IF(TODAY()-J100>14,"超时","未超时"),IF(M100-J100>14,"超时","未超时")),"") -> 未超时 | Q100: fb公共主页再申请
...

Sheet 服务进度表-客成

Sheet 客诉及营销汇总表
A1: 序号 | B1: 客户名称 | C1: 投诉日期 | D1: 投诉主体 | E1: 渠道来源 | F1: 性质 | G1: 客诉类型 | H1: 投诉内容描述 | I1: 处理状态 | J1: 处理人 | K1: 处理时间 | L1: 补充截图
A2: 1 | B2: 军芳复合材料科技（威海）有限公司 | C2: 46101 | D2: 产品功能 | E2: 企微群 | F2: 客诉 | G2: 产品客诉 | H2: 12个月，成长版，埃米AIMI a. AI 视频内容生成质量差，完全不能使用 b. 图片和内容生成质量较低，AI 生成图片和内容不匹配，且内容中 AI 痕迹明显 c. 无法通过统一指令对内容、图片、视频进行描述后生成结果 d. ai给出排期时，也默认制定了不同平台的发布频次，但按ai发布频次的规划，客户的曝光效果大幅降低，客户质疑ai并未结合平台给出对的解决方案
A3: 2 | B3: 济南鑫沃通达贸易有限公司 | C3: 46101 | D3: 产品功能 | E3: 企微群 | F3: 客诉 | G3: 产品客诉 | H3: 12个月，成长版，埃米AIMI a. 生成内容和文本无关联，无法使用 b. 直接发送给社媒平台的图片与 iME 通过 API 接口发送的图片格式不一致，客户对图片的加工成本过高
A4: 3 | B4: 威海市庆东渔具有限公司 | C4: 46101 | D4: 产品功能 | E4: 企微群 | F4: 潜在客诉 | G4: 产品客诉 | H4: 12个月，成长版，埃米AIMI 图片和文字不一致，客户原话“驴唇不对马嘴”，客户解码信息填写非常详细
A5: 4 | B5: 湖北美睦恩医疗设备有限公司 | C5: 46101 | D5: 产品功能 | E5: 企微群 | F5: 潜在客诉 | G5: 产品客诉 | H5: 12个月，成长版，埃米AIMI 解码和素材均按要求上传，但生成贴文中图片/视频与文案不匹配，匹配逻辑存在错误
A6: 5 | B6: 青岛腾本味食品有限公司 | C6: 46101 | D6: 产品功能 | E6: 企微群 | F6: 潜在客诉 | G6: 产品客诉 | H6: 12个月，成长版，埃米AIMI 图片和文字不一致，客户反馈无法使用
A7: 6 | B7: 江苏营力创电子材料有限公司（武卓玉） | C7: 46105 | F7: 交叉营销 | H7: 陪跑，已下订单
A8: 7 | B8: 威海托罗服饰有限公司（武卓玉） | C8: 46101 | F8: 交叉营销 | H8: 独立站
A9: 8 | B9: 瑞欧机械配件制造（山东）有限公司 | C9: 46099 | D9: 产品功能 | E9: 企微群 | F9: 潜在客诉 | G9: 产品客诉 | H9: 12个月，成长版，埃米AIMI 图片和文字不一致，生成的视频直接改变上传图片的细节，客户原话“驴唇不对马嘴，跟傻子似的，你这个东西弄进去啥也不是，”，客户解码信息填写非常详细，用别的ai生成的东西非常精准 客户指令如下： 此设计旨在为阿里国际站提供一个具有视觉冲击力且符合高端品牌调性的促销海报。 1. 视觉核心与构图 • 构图形式：采用垂直分层构图。 • 上部（信息区）：醒目的“SUPER MARCH EXPO”艺术字占位，下方紧跟“UP TO 20% OFF”促销标签。 • 下部（产品区）：将高光泽的十字轴产品置于视觉中心。通过前后构图，将产品置于模糊的日系车模型前方，形成“核心零部件”的视觉暗示。 • 比例：1080 * 1920（9:16），适配手机移动端全屏展示。 2. 色彩与材质表现 • 色调组合： • 白色和黑色：代表专业性、技术积淀与信任感。 • 品牌绿色：延展自 KORO 包装色，代表生命力与品牌独特性。 • 质感渲染：利用右上方落下的冷光，刻画不锈钢材质的冷冽感与金属倒角的光泽，展现轴承的精密度。 3. 设计元素细节 • 产品元素：精选十字轴（Universal Joint）多角度堆叠，展现产品细节（如注脂嘴、外圈质感）。 • 辅助元素：背景融入线条流畅的轿车模型，强化“汽车零配件”的应用场景，增加画面的空间深度。 • 地面效果：采用镜面反射效果，不仅增加了海报的高级感，也使底部产品更显沉稳。 4. 营销策略体现 • 紧迫感：通过“MARCH EXPO”字样营造年度大促的节日感。 • 吸引力：明确的“20% OFF”折扣信息，采用对比色或艺术字体，确保用户在滑动屏幕时能瞬间捕获核心利益点。
A10: 9 | B10: 江阴市吉丰铝业 | C10: 46106 | D10: 商务 | E10: 企微群 | F10: 潜在客诉 | G10: 服务客诉-商务 | H10: 12个月，成长版，埃米AIMI 客户表示自己没有时间用埃米平台，自己也不懂英语，所以不会对社媒平台进行运营，以及表示自己的员工也没有时间运营。目前与商务沟通，商务表示自己来帮客户运营埃米平台，后期可能存在客诉
A11: 10 | B11: 杭州迅影科技有限公司 | C11: 46104 | D11: 商务 | E11: 企微群 | F11: 潜在客诉 | G11: 服务客诉-商务 | H11: 12个月，成长版，埃米AIMI 客户表示AIMI已开始计算时间一个月了，白白浪费了。群中发消息阴阳商务，表示被欺骗，下次不买了。商务表示后续补偿，客户未理会。后续又出现客户阴阳商务的词句。询问客户使用情况，不再回复
A12: 11 | B12: 山东岚德工程机械 | C12: 46108 | D12: 商务 | E12: 企微群 | F12: 潜在客诉 | G12: 服务客诉-商务 | H12: 12个月，成长版，埃米AIMI 客户说销售承诺我们可以通过发布视频和图文来养号，客户的预期可能比较高，销售目前看到消息已读不回，有潜在客诉的可能
A13: 12 | B13: 河间市邵普玻璃制品有限公司 | C13: 46111 | D13: 商务 | E13: 其他 | F13: 客诉 | G13: 服务客诉-商务 | H13: 12个月，成长版，埃米AIMI客户反馈：1、合作是签订的纸质合同，合同上商务承诺帮忙注册社媒账号，但是合同被商务带走了；2、目前对接的商务专业性差，导致账号注册未完成谷歌邮箱及YouTube、Facebook账号刚注册就被封，商务要求自己更换手机号码，对此无法接受。3、因以上问题不想继续合作，联系商务杨经理表达退款诉求，对方态度差。（以上是客诉团队核实后发的邮件，商务过度承诺） 客户已投诉、举报12345、投诉黑猫、发起法律诉讼，目前售后已进行妥善沟通及安抚，城市分司帮助客户进行全额退款，解决客诉
A14: 13 | B14: 佛山市豪特自动化科技有限公司 | F14: 潜在客诉 | H14: 账号开通1个月以上一直没有开启服务，商务同步客户出国，回国后开始服务
A15: 14 | B15: 广州大鲸游乐设备有限公司 | C15: 46115 | D15: 商务 | E15: 企微群 | F15: 潜在客诉 | G15: 服务客诉-商务 | H15: 商务没和客户说过有积分和消耗的事情，客户群里情绪激烈
A16: 15 | B16: 梁山铭大机械设备有限公司 | C16: 46115 | D16: 交付专员 | E16: 企微群 | F16: 潜在客诉 | G16: 服务客诉-交付 | H16: 不满意帖子图片/视频的审美 facebook封号 缺失了多天的帖子计划——> 咱们正常的发帖频率是每周发3条视频加3条图文，因为账号是刚刚启动，不建议一下子发布大量的帖文，避免识别异常被封号 加上由于最近海外社媒审核升级 所以上周我们是做了一个低频次的发布更新 并结合了养号来提高账号权重 本周会继续更新，并搭配上图文一起，咱们这个发帖频率是会根据当前的运营状态来灵活调整的 有问题我随时联系你 运营这块是我在负责 有需要您随时联系我哈
A17: 16 | B17: 河北卓好科技有限公司 | C17: 46122 | D17: 交付专员 | E17: 企微群 | F17: 潜在客诉 | G17: 服务客诉-交付 | H17: 埃米+代运营。目前代运营发帖数量不够，且专员不及时回复客户消息，商务给专员打电话也不接，客成给专员发消息，专员冷处理；平台掉线了，也不管，商务来找客成，已经找到运营总监，目前开始运营，有潜在投诉风险
A18: 17 | B18: 北京奥信戴克商贸有限公司 | C18: 46122 | D18: 商务 | E18: 企微群 | F18: 潜在客诉 | G18: 服务客诉-商务 | H18: 埃米+陪跑。1、商务答应客户做领英，过度承诺，没有账号，客成说不能做，需换平台，客户不高兴 2、客户买了6个平台，目前想少做一个（暂时不做VK），其他账号先注册，胡总监说让客户必须走邮件说明情况，商务很不高兴，商务总监表示先赶紧注册，邮件后续发（后续发这个情况已和胡沟通过，胡答应可以先注册）3、安排客户填写21项表，客户表示没空，只能先提供手机号，已问运营总监不填写表，先提供上手机号这些，是否可以先注册，运营总监明确表示不可以，必须填表，目前已协调商务去帮忙填写表
A19: 18 | B19: 武汉嘉润汇茗茶叶 | C19: 46122 | D19: 产品功能 | E19: 企微群 | F19: 潜在客诉 | G19: 产品客诉 | H19: 关于ins和领英在客户自己手机登录社媒可以发帖成功，使用我们的埃米需要修改尺寸后才可以发送成功的问题。客户不认可，客户诉求：我买这个工具一共就绑定了5个平台，平时用的多的，就4个，你能不能把ins的使用不了的这部分退给我，等你们什么时候可以优化升级了，我再补给你们

Sheet 交付实施进度
A1: 序号 | B1: 客成序号 | C1: 公司名称 （标红为未进入伙伴工作台的服务单） | D1: 购买产品 | E1: 分配日期 | F1: 分配专员 | G1: 服务开始时间 | H1: 注册完成时间 | I1: 主页装修完成时间 | J1: 账号授权绑定时间 | K1: 养号
A2: =='服务进度表-交付实施'!A2 -> 1 | C2: =='服务进度表-交付实施'!C2 -> 邯郸市扬发贸易有限公司 | D2: =='服务进度表-交付实施'!D2 -> 埃米平台+埃米陪跑服务 | E2: =='服务进度表-交付实施'!J2 -> 46080 | F2: =='服务进度表-交付实施'!L2 -> 曾欢 | G2: =='服务进度表-交付实施'!M2 -> 46090 | H2: ==WORKDAY(E2,5) -> 46087 | I2: ==WORKDAY(H2,1) -> 46090 | J2: ==WORKDAY(I2,5) -> 46097 | K2: ==WORKDAY(H2,5) -> 46094
A3: =='服务进度表-交付实施'!A3 -> 2 | C3: =='服务进度表-交付实施'!C3 -> 河北卓好科技有限公司 | D3: =='服务进度表-交付实施'!D3 -> 埃米平台+埃米代运营服务 | E3: =='服务进度表-交付实施'!J3 -> 46080 | F3: =='服务进度表-交付实施'!L3 -> 张艺 | G3: =='服务进度表-交付实施'!M3 -> 46090 | H3: ==WORKDAY(E3,5) -> 46087 | I3: ==WORKDAY(H3,1) -> 46090 | J3: ==WORKDAY(I3,5) -> 46097 | K3: ==WORKDAY(H3,5) -> 46094
A4: =='服务进度表-交付实施'!A4 -> 3 | C4: =='服务进度表-交付实施'!C4 -> 徐州沃卡重工机械有限公司 | D4: =='服务进度表-交付实施'!D4 -> 埃米平台+埃米陪跑服务 | E4: =='服务进度表-交付实施'!J4 -> 46080 | F4: =='服务进度表-交付实施'!L4 -> 李睿琦 | G4: =='服务进度表-交付实施'!M4 -> 46084 | H4: ==WORKDAY(E4,5) -> 46087 | I4: ==WORKDAY(H4,1) -> 46090 | J4: ==WORKDAY(I4,5) -> 46097 | K4: ==WORKDAY(H4,5) -> 46094
A5: =='服务进度表-交付实施'!A5 -> 4 | C5: =='服务进度表-交付实施'!C5 -> 临清市星扬机械设备有限公司 | D5: =='服务进度表-交付实施'!D5 -> 埃米平台+埃米陪跑服务 | E5: =='服务进度表-交付实施'!J5 -> 46080 | F5: =='服务进度表-交付实施'!L5 -> 李睿琦 | G5: =='服务进度表-交付实施'!M5 -> 46086 | H5: ==WORKDAY(E5,5) -> 46087 | I5: ==WORKDAY(H5,1) -> 46090 | J5: ==WORKDAY(I5,5) -> 46097 | K5: ==WORKDAY(H5,5) -> 46094
A6: =='服务进度表-交付实施'!A6 -> 5 | C6: =='服务进度表-交付实施'!C6 -> 山东鸿星工程机械有限公司 | D6: =='服务进度表-交付实施'!D6 -> 埃米平台+埃米陪跑服务 | E6: =='服务进度表-交付实施'!J6 -> 46080 | F6: =='服务进度表-交付实施'!L6 -> 曾欢 | G6: =='服务进度表-交付实施'!M6 -> 46091 | H6: ==WORKDAY(E6,5) -> 46087 | I6: ==WORKDAY(H6,1) -> 46090 | J6: ==WORKDAY(I6,5) -> 46097 | K6: ==WORKDAY(H6,5) -> 46094
A7: =='服务进度表-交付实施'!A7 -> 6 | C7: =='服务进度表-交付实施'!C7 -> 梁山铭大机械设备有限公司 | D7: =='服务进度表-交付实施'!D7 -> 埃米平台+埃米陪跑服务 | E7: =='服务进度表-交付实施'!J7 -> 46083 | F7: =='服务进度表-交付实施'!L7 -> 李睿琦 | G7: =='服务进度表-交付实施'!M7 -> 46085 | H7: ==WORKDAY(E7,5) -> 46090 | I7: ==WORKDAY(H7,1) -> 46091 | J7: ==WORKDAY(I7,5) -> 46098 | K7: ==WORKDAY(H7,5) -> 46097
A8: =='服务进度表-交付实施'!A8 -> 7 | C8: =='服务进度表-交付实施'!C8 -> 威海基尔新能源装备有限公司 | D8: =='服务进度表-交付实施'!D8 -> 埃米平台+埃米代运营服务 | E8: =='服务进度表-交付实施'!J8 -> 46084 | F8: =='服务进度表-交付实施'!L8 -> 韩明伟 | G8: =='服务进度表-交付实施'!M8 -> 46091 | H8: ==WORKDAY(E8,5) -> 46091 | I8: ==WORKDAY(H8,1) -> 46092 | J8: ==WORKDAY(I8,5) -> 46099 | K8: ==WORKDAY(H8,5) -> 46098
A9: =='服务进度表-交付实施'!A9 -> 8 | C9: =='服务进度表-交付实施'!C9 -> 平原百斯特机械工具有限公司 | D9: =='服务进度表-交付实施'!D9 -> 埃米平台+埃米陪跑服务 | E9: =='服务进度表-交付实施'!J9 -> 46084 | F9: =='服务进度表-交付实施'!L9 -> 李睿琦 | G9: =='服务进度表-交付实施'!M9 -> 46087 | H9: ==WORKDAY(E9,5) -> 46091 | I9: ==WORKDAY(H9,1) -> 46092 | J9: ==WORKDAY(I9,5) -> 46099 | K9: ==WORKDAY(H9,5) -> 46098
A10: =='服务进度表-交付实施'!A10 -> 9 | C10: =='服务进度表-交付实施'!C10 -> 永东发（廊坊）科技有限公司 | D10: =='服务进度表-交付实施'!D10 -> 埃米平台+埃米陪跑服务 | E10: =='服务进度表-交付实施'!J10 -> 46091 | F10: =='服务进度表-交付实施'!L10 -> 王芷娇 | G10: =='服务进度表-交付实施'!M10 -> 46101 | H10: ==WORKDAY(E10,5) -> 46098 | I10: ==WORKDAY(H10,1) -> 46099 | J10: ==WORKDAY(I10,5) -> 46106 | K10: ==WORKDAY(H10,5) -> 46105
A11: =='服务进度表-交付实施'!A11 -> 10 | C11: =='服务进度表-交付实施'!C11 -> 聊城市金硕机电设备有限公司 | D11: =='服务进度表-交付实施'!D11 -> 埃米平台+埃米陪跑服务 | E11: =='服务进度表-交付实施'!J11 -> 46098 | F11: =='服务进度表-交付实施'!L11 -> 李睿琦 | G11: =='服务进度表-交付实施'!M11 -> 46112 | H11: ==WORKDAY(E11,5) -> 46105 | I11: ==WORKDAY(H11,1) -> 46106 | J11: ==WORKDAY(I11,5) -> 46113 | K11: ==WORKDAY(H11,5) -> 46112
A12: =='服务进度表-交付实施'!A12 -> 11 | C12: =='服务进度表-交付实施'!C12 -> 山东忠阳化工有限公司 | D12: =='服务进度表-交付实施'!D12 -> 埃米平台+埃米陪跑服务 | E12: =='服务进度表-交付实施'!J12 -> 46105 | F12: =='服务进度表-交付实施'!L12 -> 王芷娇 | G12: =='服务进度表-交付实施'!M12 -> 46114 | H12: ==WORKDAY(E12,5) -> 46112 | I12: ==WORKDAY(H12,1) -> 46113 | J12: ==WORKDAY(I12,5) -> 46120 | K12: ==WORKDAY(H12,5) -> 46119
A13: =='服务进度表-交付实施'!A13 -> 12 | C13: =='服务进度表-交付实施'!C13 -> 焜傲机器人（成都）有限公司 | D13: =='服务进度表-交付实施'!D13 -> 埃米平台+埃米陪跑服务 | E13: =='服务进度表-交付实施'!J13 -> 46085 | F13: =='服务进度表-交付实施'!L13 -> 李睿琦 | G13: =='服务进度表-交付实施'!M13 -> 46094 | H13: ==WORKDAY(E13,5) -> 46092 | I13: ==WORKDAY(H13,1) -> 46093 | J13: ==WORKDAY(I13,5) -> 46100 | K13: ==WORKDAY(H13,5) -> 46099
... A167: =='服务进度表-交付实施'!A167 -> 166 | C167: =='服务进度表-交付实施'!C167 -> 湖北松港汽车科技有限公司 | D167: =='服务进度表-交付实施'!D167 -> 埃米平台+埃米代运营服务 | E167: =='服务进度表-交付实施'!J167 -> 46121 | F167: =='服务进度表-交付实施'!L167 -> 刘晟甫 | G167: =='服务进度表-交付实施'!M167 -> 0 | H167: ==WORKDAY(E167,5) -> 46128 | I167: ==WORKDAY(H167,1) -> 46129 | J167: ==WORKDAY(I167,5) -> 46136 | K167: ==WORKDAY(H167,5) -> 46135
